Workbook
Name aa: 投资计划!$J$28
Name ab: 投资计划!$K$28
Name ac: 投资计划!$L$28
Name b: 投资计划!$J$27
Name cc: 投资计划!$J$29
Name i: 投资计划!$J$26
Name j: 投资计划!$J$30
Name 存款利率: 参数表!#REF!
Name 短期贷款利息: 参数表!$C$29
Name 公益金: 指标汇总!#REF!
Name 流动资金贷款比例: 参数表!#REF!
Name 流动资金贷款利率: 参数表!$C$28
Name 流动资金总额: 参数表!$C$24
Name 年发电量: 指标汇总!$D$22
Name 其他费用费率: 参数表!$C$48
Name 所得税率: 参数表!$C$35
Name 盈余公积金: 参数表!$C$38
Name 增值税率: 参数表!$C$31
Name 装机容量: 指标汇总!$D$21
Name 总投资: 指标汇总!$D$23

Sheet 参数表
A1: 序号 | B1: 名 称 | C1: 指标 | D1: 单位 | E1: 说明
A2: 1 | B2: 装机容量 | C2: 2 | D2: 万kW | E2: 数据来源：预可行性研究报告或可行性研究报告
A3: 2 | B3: 利用小时数 | C3: 2431 | D3: 小时 | E3: 参考值，数据来源：预可行性研究报告或可行性研究报告；初步测算时，可根据各单位风机选型软件取值
A4: 3 | B4: 运营年度 | C4: 2020 | D4: 2021 | E4: 2022 | F4: 2023 | G4: 2024 | H4: 2025 | I4: 2026 | J4: 2027 | K4: 2028 | L4: 2029 | M4: 2030 | N4: 2031 | O4: 2032 | P4: 2033 | Q4: 2034 | R4: 2035 | S4: 2036 | T4: 2037 | U4: 2038 | V4: 2039 | W4: 2040
A5: 5 | B5: 负荷率 | C5: 0 | D5: 1 | E5: 1 | F5: 1 | G5: 1 | H5: 1 | I5: 1 | J5: 1 | K5: 1 | L5: 1 | M5: 1 | N5: 1 | O5: 1 | P5: 1 | Q5: 1 | R5: 1 | S5: 1 | T5: 1 | U5: 1 | V5: 1 | W5: 1
A6: 7 | B6: 上网电价 | C6: =C7+C8 -> 0.421 | D6: 元/kW·h | E6: 参考值，平价上网项目为当地煤电标杆电价（现称基准电价，含脱硫脱硝除尘电价，含增值税），竞价项目为含补贴电价（含增值税）
A7: 7.1 | B7: 无补贴上网电价 | C7: 0.411 | D7: 元/kW·h | E7: 参考值，该电价为批准无补贴上网电价，为当地煤电标杆电价（现称基准电价），综合考虑市场化交易（若有）和“两个细则”考核成本
A8: 7.2 | B8: 度电补贴强度 | C8: 0.01 | D8: 元/kW·h | E8: 参考值，竞价项目为度电补贴强度（含增值税），平价项目为0
A9: 7.3 | B9: 补贴到位率 | C9: =C4 -> 2020 | D9: =D4 -> 2021 | E9: =E4 -> 2022 | F9: =F4 -> 2023 | G9: =G4 -> 2024 | H9: =H4 -> 2025 | I9: =I4 -> 2026 | J9: =J4 -> 2027 | ... W9: =W4 -> 2040
D10: 0 | E10: 2 | F10: 1 | G10: 1 | H10: 1 | I10: 1 | J10: 1 | K10: 1 | L10: 1 | M10: 1 | N10: 1 | O10: 1 | P10: 1 | Q10: 1 | R10: 1 | S10: 1 | T10: 1 | U10: 1 | V10: 1 | W10: 1
A11: 8 | B11: 静态投资 | C11: =C12+C13+C14+C17 -> 42440 | D11: 万元 | E11: 参考值，自动计算
A12: 8.1 | B12: 建安工程费 | C12: 20000 | D12: 万元 | E12: 参考值，数据来源：预可行性研究报告或可行性研究报告
A13: 8.2 | B13: 设备购置费 | C13: 20000 | D13: 万元 | E13: 参考值，数据来源：预可行性研究报告或可行性研究报告
A14: 8.3 | B14: 其他费用 | C14: 2000 | D14: 万元 | E14: 参考值，数据来源：预可行性研究报告或可行性研究报告
A15: 8.3.1 | B15: 其中：建设用地费 | C15: 500 | D15: 万元 | E15: 参考值，含土地补偿费、土地征用费、安置补助费、耕地占用税、城镇土地使用税（若有）、耕地开垦费、勘测定界费、征地管理费、证书费、手续费，另有森林植被恢复费（若有）、草原植被恢复费（若有）
A16: 8.3.2 | B16: 其中：勘察设计费 | C16: 200 | D16: 万元 | E16: 参考值，数据来源：预可行性研究报告或可行性研究报告
A17: 8.4 | B17: 基本预备费 | C17: 440 | D17: 万元 | E17: 参考值，数据来源：预可行性研究报告或可行性研究报告
B18: 单位静态投资 | C18: =(C12+C13+C14+C17)/C2 -> 21220 | D18: 元/kW | E18: 参考值，自动计算
B19: EPC单价 | C19: =(C12+C13+C16)/C2 -> 20100 | D19: 元/kW | E19: 参考值，自动计算
A20: 8.5 | B20: 建设期可抵扣增值税 | C20: =C12/(1+C21)*C21+C13/(1+C22)*C22+C16/(1+C23)*C23 -> 3963.5819 | D20: 万元 | E20: 参考值，自动计算，假定建安工程费、设备购置费、勘察设计费可足额开具增值税发票
A21: 8.5.1 | B21: 建安工程费增值税税率 | C21: 0.09 | E21: 可不调整
A22: 8.5.2 | B22: 设备购置费增值税税率 | C22: 0.13 | E22: 可不调整
A23: 8.5.3 | B23: 勘察设计费增值税税率 | C23: 0.06 | E23: 可不调整
A24: 9 | B24: 流动资金总额 | C24: =参数表!C2*30 -> 60 | D24: 万元 | E24: 数据来源：预可行性研究报告或可行性研究报告
A25: 10 | B25: 资本金比例 | C25: 0.2 | E25: 根据《国务院关于加强固定资产投资项目资本金管理的通知》（国发〔2019〕26号），电力项目最低资本金比例取20%。须与可行性研究报告一致。计算资本金基数的总投资，是指投资项目的固定资产投资与铺底流动资金之和，具体核定时以经批准的动态概算为依据
A26: 11 | B26: 长期借款利率 | C26: 0.049 | E26: 参考值，根据项目情况向银行初步询价
A27: 18 | B27: 长期借款年限（不含建设期） | C27: 15 | D27: 年 | E27: 参考值，根据项目情况向银行初步询价
A28: 12 | B28: 流动资金贷款利率 | C28: 0.0435 | E28: 参考值，根据项目情况向银行初步询价
A29: 13 | B29: 短期贷款利息 | C29: 0.0435 | E29: 参考值，根据项目情况向银行初步询价
A30: 14 | B30: 建设周期 | C30: 10 | D30: 月 | E30: 参考值，数据来源：预可行性研究报告或可行性研究报告
A31: 15 | B31: 增值税率 | C31: 0.13 | E31: 目前风电项目增值税税率为13%，若有其他优惠政策可更改该税率。参见《风电、光伏发电项目涉税事项》
A32: 16 | B32: 增值税优惠享受年限 | C32: 2045 | D32: 年 | E32: 即征即退享受年限，目前风电项目享受该政策
A33: 17 | B33: 城市建设维护税率 | C33: 0.05 | E33: 参见《风电、光伏发电项目涉税事项》
A34: 18 | B34: 教育费附加费率 | C34: 0.05 | E34: 参见《风电、光伏发电项目涉税事项》
A35: 19 | B35: 所得税税率 | C35: 0.25 | E35: 目前风电项目享受所得税三免三减半优惠政策，若为西部省份，可查询有关省份风电项目是否享受所得税15%优惠政策
A36: 19.1 | B36: 西部大开发优惠税率享受年限 | C36: 否 | E36: 根据《关于延续西部大开发企业所得税政策的公告》（财政部 税务总局 国家发展改革委公告2020年第23号）自2021年1月1日至2030年12月31日，对设在西部地区的鼓励类产业企业减按15%的税率征收企业所得税。根据《西部地区鼓励类产业目录（2014年修订版）》，甘肃省、青海省、宁夏回族自治区、新疆维吾尔自治区、内蒙古自治区鼓励产业目录含风力发电场建设及运营、太阳能发电系统建设及运营，可享受15%的所得税税率。参见《风电、光伏发电项目涉税事项》
A37: 19.2 | B37: 西部大开发优惠所得税税率 | C37: 0.15
A38: 20 | B38: 法定盈余公积金比率 | C38: 0.1 | E38: 可不调整
A39: 21 | B39: 折旧年限 | C39: 15 | E39: 可不调整。数据来源：预可行性研究报告或可行性研究报告
A40: 22 | B40: 残值率 | C40: 0.05 | E40: 可不调整。数据来源：预可行性研究报告或可行性研究报告
A41: 23 | B41: 折旧率 | C41: =(1-参数表!C40)/参数表!C39 -> 0.063333333 | E41: 参考值
A42: 23 | B42: 年运维费费率 | C42: =(成本!Y7+成本!Y8+成本!Y10+成本!Y18)/参数表!C2/20 -> 342.10343 | D42: 元/kW | E42: 参考值
A43: 23.1 | B43: 年修理费率 | C43: =C4 -> 2020 | D43: =D4 -> 2021 | E43: =E4 -> 2022 | F43: =F4 -> 2023 | G43: =G4 -> 2024 | H43: =H4 -> 2025 | I43: =I4 -> 2026 | J43: =J4 -> 2027 | ... W43: =W4 -> 2040
D44: 0.002 | E44: 0.002 | F44: 0.002 | G44: 0.002 | H44: 0.002 | I44: 0.01 | J44: 0.01 | K44: 0.01 | L44: 0.01 | M44: 0.01 | N44: 0.015 | O44: 0.015 | P44: 0.015 | Q44: 0.015 | R44: 0.015 | S44: 0.02 | T44: 0.02 | U44: 0.02 | V44: 0.02 | W44: 0.02
A45: 23.2 | B45: 员工人数 | C45: 10 | E45: 参考值，数据来源：预可行性研究报告或可行性研究报告
A46: 23.3 | B46: 年均工资 | C46: 9 | D46: 万元 | E46: 参考值，数据来源：预可行性研究报告或可行性研究报告
A47: 23.4 | B47: 福利费率 | C47: 0.6 | E47: 参考值，数据来源：预可行性研究报告或可行性研究报告
A48: 23.5 | B48: 年其他费用费率 | C48: 30 | D48: 元/kW | E48: 参考值，数据来源：预可行性研究报告或可行性研究报告
A49: 23.6 | B49: 年材料费费率 | C49: 10 | D49: 元/kW | E49: 参考值，数据来源：预可行性研究报告或可行性研究报告
A50: 23.7 | B50: 年保险费费率 | C50: 0.0025 | E50: 参考值，数据来源：预可行性研究报告或可行性研究报告
A51: 24 | B51: 首年土地租金 | C51: =C53*C54/10000 -> 0
A52: 24.1 | B52: 单位占地面积 | C52: 0 | D52: hm2/10MW
A53: 24.2 | B53: 占地面积 | C53: =C2*C52*10000/(1000*2/3) -> 0 | D53: 亩
B54: 首年每亩土地租金 | C54: 0 | D54: 元/亩
B55: 土地租金上浮率 | C55: 0
A56: 24.3 | B56: 土地租金支付频率 | C56: 1 | D56: 年/次
C57: =C4 -> 2020 | D57: =D4 -> 2021 | E57: =E4 -> 2022 | F57: =F4 -> 2023 | G57: =G4 -> 2024 | H57: =H4 -> 2025 | I57: =I4 -> 2026 | J57: =J4 -> 2027 | ... W57: =W4 -> 2040
A58: 24.4 | B58: 土地租金支付（万元） | C58: =IF((C57-$C$57)/$C$56-INT((C57-$C$57)/$C$56)=0,IF(INT((C57-$C$57)/$C$56)=INT(25/$C$56),$C$51*MOD(25,$C$56)*(1+$C$55)^(C57-$C$57),$C$51*$C$56*(1+$C$55)^(C57-$C$57)),0) -> 0 | D58: =IF((D57-$C$57)/$C$56-INT((D57-$C$57)/$C$56)=0,IF(INT((D57-$C$57)/$C$56)=INT(25/$C$56),$C$51*MOD(25,$C$56)*(1+$C$55)^(D57-$C$57),$C$51*$C$56*(1+$C$55)^(D57-$C$57)),0) -> 0 | E58: =IF((E57-$C$57)/$C$56-INT((E57-$C$57)/$C$56)=0,IF(INT((E57-$C$57)/$C$56)=INT(25/$C$56),$C$51*MOD(25,$C$56)*(1+$C$55)^(E57-$C$57),$C$51*$C$56*(1+$C$55)^(E57-$C$57)),0) -> 0 | F58: =IF((F57-$C$57)/$C$56-INT((F57-$C$57)/$C$56)=0,IF(INT((F57-$C$57)/$C$56)=INT(25/$C$56),$C$51*MOD(25,$C$56)*(1+$C$55)^(F57-$C$57),$C$51*$C$56*(1+$C$55)^(F57-$C$57)),0) -> 0 | G58: =IF((G57-$C$57)/$C$56-INT((G57-$C$57)/$C$56)=0,IF(INT((G57-$C$57)/$C$56)=INT(25/$C$56),$C$51*MOD(25,$C$56)*(1+$C$55)^(G57-$C$57),$C$51*$C$56*(1+$C$55)^(G57-$C$57)),0) -> 0 | H58: =IF((H57-$C$57)/$C$56-INT((H57-$C$57)/$C$56)=0,IF(INT((H57-$C$57)/$C$56)=INT(25/$C$56),$C$51*MOD(25,$C$56)*(1+$C$55)^(H57-$C$57),$C$51*$C$56*(1+$C$55)^(H57-$C$57)),0) -> 0 | I58: =IF((I57-$C$57)/$C$56-INT((I57-$C$57)/$C$56)=0,IF(INT((I57-$C$57)/$C$56)=INT(25/$C$56),$C$51*MOD(25,$C$56)*(1+$C$55)^(I57-$C$57),$C$51*$C$56*(1+$C$55)^(I57-$C$57)),0) -> 0 | J58: =IF((J57-$C$57)/$C$56-INT((J57-$C$57)/$C$56)=0,IF(INT((J57-$C$57)/$C$56)=INT(25/$C$56),$C$51*MOD(25,$C$56)*(1+$C$55)^(J57-$C$57),$C$51*$C$56*(1+$C$55)^(J57-$C$57)),0) -> 0 | ... V58: =IF((V57-$C$57)/$C$56-INT((V57-$C$57)/$C$56)=0,IF(INT((V57-$C$57)/$C$56)=INT(25/$C$56),$C$51*MOD(25,$C$56)*(1+$C$55)^(V57-$C$57),$C$51*$C$56*(1+$C$55)^(V57-$C$57)),0) -> 0 | W58: =IF((W57-$C$57)/$C$56-INT((W57-$C$57)/$C$56)=0,IF(INT((W57-$C$57)/$C$56)=INT(26/$C$56),$C$51*MOD(25,$C$56)*(1+$C$55)^(W57-$C$57),$C$51*$C$56*(1+$C$55)^(W57-$C$57)),0) -> 0
A59: 24.5 | B59: 土地租金年摊销（租金，万元） | C59: =$C$51*(1+$C$55)^(INT((C57-$C$57)/$C$56)*$C$56) -> 0 | D59: =$C$51*(1+$C$55)^(INT((D57-$C$57)/$C$56)*$C$56) -> 0 | E59: =$C$51*(1+$C$55)^(INT((E57-$C$57)/$C$56)*$C$56) -> 0 | F59: =$C$51*(1+$C$55)^(INT((F57-$C$57)/$C$56)*$C$56) -> 0 | G59: =$C$51*(1+$C$55)^(INT((G57-$C$57)/$C$56)*$C$56) -> 0 | H59: =$C$51*(1+$C$55)^(INT((H57-$C$57)/$C$56)*$C$56) -> 0 | I59: =$C$51*(1+$C$55)^(INT((I57-$C$57)/$C$56)*$C$56) -> 0 | J59: =$C$51*(1+$C$55)^(INT((J57-$C$57)/$C$56)*$C$56) -> 0 | ... W59: =$C$51*(1+$C$55)^(INT((W57-$C$57)/$C$56)*$C$56) -> 0
A60: 25 | B60: 年度分红比例 | C60: 0.8 | E60: 参考值，计算投资方内部收益率时适用该参数
A61: 26 | B61: 购买方基准收益率（资本金） | C61: 0.085 | E61: 参考值，购买方对项目的预期资本金财务内部收益率
A62: 27 | B62: 股权出售所得税税率 | C62: 0.15 | E62: 参考值，项目公司股东的所得税税率
A63: 28 | B63: EPC签约价 | C63: =C19 -> 20100 | D63: 元/kW | E63: 参考值，含增值税
A64: 29 | B64: EPC成本价 | C64: 7500 | D64: 元/kW | E64: 参考值，含勘察设计费、项目管理费及增值税等
A65: 30 | B65: 管理费分摊比率 | C65: 0.03 | E65: 参考值，根据各单位管理费分摊比率确定（可参考上一年度财务报表）
A66: 使用说明：填写本表中底色为绿色的单元格，主要指标计算结果见指标汇总表

Sheet 指标汇总
E2: 工程概况及关键指标表
B4: 序号 | C4: 名 称 | D4: 指标 | E4: 单位 | F4: 序号 | G4: 名 称 | H4: 指标 | I4: 单位
B5: 1 | C5: 装机容量 | D5: =参数表!C2 -> 2 | E5: 万kW | F5: 10 | G5: 年发电量 | H5: =参数表!C2*D9 -> 4862 | I5: 万kWh
B6: 2 | C6: 单位千瓦投资（静态） | D6: =参数表!C18 -> 21220 | E6: 元/kw | F6: 11 | G6: 静态投资 | H6: =参数表!C2*参数表!C18 -> 42440 | I6: 万元
B7: 3 | C7: 资本金比例设定 | D7: =参数表!C25*100 -> 20 | E7: % | F7: 12 | G7: 动态投资 | H7: =投资计划!C9 -> 43130.124 | I7: 万元
B8: 4 | C8: 含税上网电价 | D8: =参数表!C6 -> 0.421 | E8: 元/kW·h
B9: 5 | C9: 年发电小时数 | D9: =参数表!C3 -> 2431 | E9: 小时 | F9: 13 | G9: 盈利能力指标
B10: 6 | C10: 单位电度投资（动态） | D10: =H7/H5 -> 8.8708605 | E10: 元/kwh | F10: 14 | G10: 项目投资财务内部收益率（所得税前） | H10: =现金流量!L29 -> -3.7478742 | I10: %
C11: 经营指标 | G11: 资本金财务内部收益率（所得税后） | H11: =现金流量!H61*100 -> -7.1453352 | I11: %
B12: 7 | C12: 年均经营成本 | D12: =成本!Y22/25 -> 577.3279 | E12: 万元 | F12: 15 | G12: 偿债能力指标
B13: 8 | C13: 单位电度经营成本 | D13: =D12/年发电量 -> 0.11874288 | E13: 元/kW·h | F13: 16 | G13: 最大资产负债率 | H13: =H38 -> 2079.3249 | I13: %
B14: 9 | C14: 单位千瓦经营成本 | D14: =D12/装机容量 -> 288.66395 | E14: 元/kW | F14: 17 | G14: 累计最大短期借款 | H14: =H40 -> 41907.578 | I14: 万元
F15: 18 | G15: 贷款还贷年限（不含建设期） | H15: =参数表!C27 -> 15 | I15: 年
E18: 财务指标汇总表
B20: 序号 | C20: 名 称 | D20: 指标 | E20: 单位 | F20: 序号 | G20: 名 称 | H20: 指标 | I20: 单位
B21: 1 | C21: 装机容量 | D21: =参数表!C2 -> 2 | E21: 万kW | G21: 盈利能力指标
B22: 2 | C22: 年发电量 | D22: =H5 -> 4862 | E22: 万kWh | F22: 18 | G22: 项目投资回收期 | H22: =现金流量!I31 -> 0 | I22: 年
B23: 3 | C23: 总投资 | D23: =投资计划!C5 -> 43190.124 | E23: 万元 | F23: 19 | G23: 项目投资财务内部收益率（所得税前） | H23: =现金流量!L29 -> -3.7478742 | I23: %
B24: 4 | C24: 建设期利息 | D24: =投资计划!H7 -> 690.12366 | E24: 万元 | G24: 项目投资财务净现值（所得税前 ic=5%） | H24: =现金流量!L30 -> -23459.716 | I24: 万元
B25: 5 | C25: 流动资金 | D25: =投资计划!C8 -> 60 | E25: 万元 | F25: 20 | G25: 财务内部收益率（所得税后）
B26: 6 | C26: 电价 | F26: 20.1 | G26: 项目投资 | H26: =现金流量!I29 -> -3.0946558 | I26: %
B27: 6.1 | C27: 上网电价（不含增值税） | D27: =D28/(1+增值税率) -> 0.37256637 | E27: 元/kW·h | F27: 20.2 | G27: 资本金 | H27: =现金流量!H61*100 -> -7.1453352 | I27: %
B28: 6.2 | C28: 上网电价（含增值税） | D28: =参数表!C6 -> 0.421 | E28: 元/kW·h | F28: 20.3 | G28: 投资方 | H28: =现金流量!H97*100 -> -7.1453352 | I28: %
C29: 经营指标 | F29: 21 | G29: 财务净现值（所得税后）
B30: 7 | C30: 发电销售收入总额 | D30: =损益!AA8 -> 36228.354 | E30: 万元 | F30: 21.1 | G30: 项目投资（ic=5%） | H30: =现金流量!I30 -> -21779.114 | I30: %
B31: 8 | C31: 总成本费用总额 | D31: =成本!Y21 -> 85089.478 | E31: 万元 | F31: 21.2 | G31: 资本金（ic=8%） | H31: =现金流量!H62 -> -7598.027 | I31: 万元
B32: 9 | C32: 销售税金附加总额 | D32: =损益!AA9 -> 74.610416 | E32: 万元 | F32: 21.3 | G32: 投资方（ic=8%） | H32: =现金流量!H98 -> -7598.027 | I32: 万元
B33: 10 | C33: 发电利润总额 | D33: =损益!AA15 -> -48562.682 | E33: 万元 | F33: 22 | G33: 单位电度投资（动态） | H33: =D10 -> 8.8708605 | I33: 元/kwh
B34: 11 | C34: 年均经营成本 | D34: =成本!Y22/25 -> 577.3279 | E34: 万元 | F34: 23 | G34: 投资利润率（生产期平均） | H34: =D33/总投资/25*100 -> -4.4975729 | I34: %
B35: 12 | C35: 单位电度经营成本 | D35: =D34/年发电量 -> 0.11874288 | E35: 元/kW·h | F35: 24 | G35: 投资利税率（生产期平均） | H35: =(D32+D33+D30*增值税率)/总投资/25*100 -> -4.0544812 | I35: %
B36: 13 | C36: 单位千瓦经营成本 | D36: =D34/装机容量 -> 288.66395 | E36: 元/kW | F36: 25 | G36: 资本金净利润率 | H36: =损益!AA26/25/投资计划!C11*100 -> 0 | I36: %
C37: 其他指标 | G37: 偿债负债指标
B38: 14 | C38: 年发电小时数 | D38: =D9 -> 2431 | E38: 小时 | F38: 26 | G38: 最大资产负债率 | H38: =资产负债!D28*100 -> 2079.3249 | I38: %
B39: 15 | C39: 单位电度投资（动态） | D39: =D23/D22 -> 8.8832011 | E39: 元/kwh | F39: 27 | G39: 最大累计亏损额 | H39: =损益!AA16 -> -15735.84 | I39: 万元
B40: 16 | C40: 单位千瓦投资（静态） | D40: =参数表!C18 -> 21220 | E40: 元/KW | F40: 28 | G40: 累计最大短期借款 | H40: =财务计划!C22 -> 41907.578 | I40: 万元
B41: 17 | C41: 资本金比例 | D41: =参数表!C25*100 -> 20 | E41: % | F41: 29 | G41: 长期借款还贷年限（不含建设期） | H41: =参数表!C27 -> 15 | I41: 年
C42: 股权出售净利润 | F42: 30 | G42: 全部贷款还贷年限（不含建设期） | H42: =参数表!C27 -> 15 | I42: 年
C43: 资本金出资额 | D43: =投资计划!B27 -> 8638.0247 | E43: 万元 | F43: 31 | G43: 利息备付率（平均） | H43: =还贷!Y29 -> -0.33395728
C44: 电站转让净利润 | D44: =估值结果!B11-估值结果!B14 -> -8243.1354 | E44: 万元 | F44: 32 | G44: 偿债备付率（平均） | H44: =还贷!Y32 -> 0.42571535
C45: EPC净利润 | D45: =((参数表!C63-参数表!C64)*参数表!C2-参数表!C63*参数表!C2/(1+12%)*参数表!C65-((参数表!C63-参数表!C64)*参数表!C2/(1+12%)*12%*1.12))*(1-参数表!C62) -> 17934.332 | G45: 总投资收益率（ROI） | H45: =现金流量!Y20/总投资/25 -> -0.013998216
C46: 电站转让净利润+EPC净利润 | D46: =D44+D45 -> 9691.1967 | E46: 万元

Sheet 投资计划
A1: 投资计划与资金筹措表
A2: 序号 | B2: 年限 | C2: 合计 | D2: 1 | E2: 2 | F2: 1 | G2: 2 | H2: 累计
B3: 静态投资完成比例 | C3: 1 | D3: =aa -> 0 | E3: =ab -> 0 | F3: =ac -> 1 | G3: 0 | H3: 1
B4: 资本金使用比例 | C4: 1 | D4: =D11/$C$11 -> 0 | E4: =E11/$C$11 -> 0 | F4: =F11/$C$11 -> 1 | G4: =G11/$C$11 -> 0 | H4: =SUM(D4:G4) -> 1
A5: 1 | B5: 总投资 | C5: =SUM(C6:C8) -> 43190.124 | D5: =D6+D7+D8 -> 0 | E5: =E6+E7+E8 -> 0 | F5: =F6+F7+F8 -> 43130.124 | G5: =G6+G7+G8 -> 60 | H5: =SUM(D5:G5) -> 43190.124
A6: 1.1 | B6: 建设投资 | C6: =指标汇总!H6 -> 42440 | D6: =$C$6*D3 -> 0 | E6: =$C$6*E3 -> 0 | F6: =$C$6*F3 -> 42440 | G6: =成本!D54 -> 0 | H6: =SUM(D6:G6) -> 42440
A7: 1.2 | B7: 建设期利息 | C7: =B32 -> 690.12366 | D7: =C32 -> 0 | E7: =F32 -> 0 | F7: =G32 -> 690.12366 | H7: =SUM(D7:G7) -> 690.12366
A8: 1.3 | B8: 流动资金 | C8: =流动资金总额 -> 60 | D8: =SUM(D13,D18) -> 0 | E8: =SUM(E13,E18) -> 0 | F8: =SUM(F13,F18) -> 0 | G8: =SUM(G13,G18) -> 60 | H8: =SUM(D8:G8) -> 60
B9: 动态投资 | C9: =C6+C7 -> 43130.124
A10: 2 | B10: 资金筹措 | C10: =SUM(C11,C14) -> 43190.124 | D10: =SUM(D11,D14) -> 0 | E10: =SUM(E11,E14) -> 0 | F10: =SUM(F11,F14) -> 43118.124 | G10: =SUM(G11,G14) -> 60 | H10: =SUM(D10:G10)+D17 -> 43178.124
A11: 2.1 | B11: 自有资金 | C11: =C12+C13 -> 8626.0247 | D11: =D12+D13 -> 0 | E11: =E12+E13 -> 0 | F11: =SUM(F12:F13) -> 8626.0247 | G11: =SUM(G12:G13) -> 0 | H11: =SUM(D11:G11) -> 8626.0247 | I11: =C11/C5 -> 0.19972216
A12: 2.1.1 | B12: 用于建设投资 | C12: =C9*参数表!C25 -> 8626.0247 | D12: 0 | E12: 0 | F12: =C12*F3 -> 8626.0247 | G12: =C12*G3 -> 0 | H12: =SUM(D12:G12) -> 8626.0247
A13: 2.1.2 | B13: 用于流动资金 | C13: =C8*0% -> 0 | G13: =C13 -> 0 | H13: =SUM(D13:G13) -> 0
A14: 2.2 | B14: 借款 | C14: =SUM(C15:C19) -> 34564.099 | D14: =SUM(D15:D19) -> 0 | E14: =SUM(E15:E19) -> 0 | F14: =F15+F18 -> 34492.099 | G14: =SUM(G15:G19) -> 60 | H14: =SUM(D14:G14) -> 34552.099
A15: 2.2.1 | B15: 长期借款 | C15: =C9*(1-参数表!C25) -> 34504.099 | D15: =D16+D17 -> 0 | E15: =SUM(E7,E16) -> 0 | F15: =F16+F17 -> 34492.099 | G15: =SUM(G7,G16) -> 0 | H15: =SUM(D15:G15) -> 34492.099
A16: 2.2.1.1 | B16: 长期借款本金 | D16: =C31 -> 0 | E16: =F31 -> 0 | F16: =G31 -> 33801.975 | G16: =G6-G12 -> 0
A17: 2.2.1.2 | B17: 长期借款利息 | D17: =C32 -> 0 | E17: =F32 -> 0 | F17: =G32 -> 690.12366 | G17: =G15-G16 -> 0
A18: 2.2.2 | B18: 流动资金借款 | C18: =C8*100% -> 60 | G18: =C18 -> 60 | H18: =SUM(D18:G18) -> 60
A19: 2.2.3 | B19: 其他短期贷款 | H19: =SUM(D19:G19) -> 0
A20: 2.3 | B20: 其他 | G20: =G7 -> 0 | H20: =SUM(D20:G20) -> 0
A22: 辅助测算表
A23: 合计 | C23: 1 | F23: 2 | G23: 3
A24: 总投资 | B24: =J32 -> 43190.124
A25: 动态投资 | B25: =J31 -> 43130.124
A26: 静态投资 | B26: =参数表!C18*参数表!C2 -> 42440 | I26: i | J26: =参数表!C26*(参数表!C30/12) -> 0.040833333
A27: 资本金 | B27: =B24*J27 -> 8638.0247 | I27: b | J27: =参数表!C25 -> 0.2
A28: 贷款 | B28: =B26-B27 -> 33801.975 | I28: a | J28: 0 | K28: 0 | L28: 1
A29: 年度静态投资 | B29: =C29+F29+G29 -> 42440 | C29: =$B$26*J28 -> 0 | F29: =$B$26*K28 -> 0 | G29: =$B$26*L28 -> 42440 | I29: c | J29: =C8 -> 60
A30: 年度资本金 | B30: =C30+F30+G30 -> 8638.0247 | C30: =$B$27*J28 -> 0 | F30: =$B$27*K28 -> 0 | G30: =$B$27*L28 -> 8638.0247 | I30: j | J30: =B26 -> 42440
A31: 年度贷款 | B31: =C31+F31+G31 -> 33801.975 | C31: =C29-C30 -> 0 | F31: =F29-F30 -> 0 | G31: =G29-G30 -> 33801.975 | I31: D | J31: =(j*(2+i)*(aa*(1+i)^2+ab*(1+i)+ac)+2*cc)/(b*(2+i)*(aa*(1+i)^2+ab*(1+i)+ac)+2*(1-b))-cc -> 43130.124
A32: 年度利息 | B32: =C32+F32+G32 -> 690.12366 | C32: =C31/2*J26 -> 0 | F32: =(F31/2+C32+C31)*J26 -> 0 | G32: =(G31/2+SUM(C31:F32))*J26 -> 690.12366 | I32: Z | J32: =J31+cc -> 43190.124

Sheet 损益
B1: 损 益 表
B3: 序号 | C3: 项目 | G3: 运 营 期 | AA3: 合计
D4: =成本!#REF! -> #REF! | E4: =成本!#REF! -> #REF! | F4: =参数表!C4 -> 2020 | G4: =参数表!D4 -> 2021 | H4: =参数表!E4 -> 2022 | I4: =参数表!F4 -> 2023 | J4: =参数表!G4 -> 2024 | K4: =参数表!H4 -> 2025 | L4: =参数表!I4 -> 2026 | M4: =参数表!J4 -> 2027 | ... Z4: =参数表!W4 -> 2040
C5: 上网电量(万kW.h) | G5: =参数表!$C$3*参数表!D5*参数表!$C$2 -> 4862 | H5: =参数表!$C$3*参数表!E5*参数表!$C$2 -> 4862 | I5: =参数表!$C$3*参数表!F5*参数表!$C$2 -> 4862 | J5: =参数表!$C$3*参数表!G5*参数表!$C$2 -> 4862 | K5: =参数表!$C$3*参数表!H5*参数表!$C$2 -> 4862 | L5: =参数表!$C$3*参数表!I5*参数表!$C$2 -> 4862 | M5: =参数表!$C$3*参数表!J5*参数表!$C$2 -> 4862 | N5: =参数表!$C$3*参数表!K5*参数表!$C$2 -> 4862 | ... Z5: =参数表!$C$3*参数表!W5*参数表!$C$2 -> 4862
C6: 上网电价（含增值税）(元/kW.h) | G6: =参数表!$C$6 -> 0.421 | H6: =参数表!$C$6 -> 0.421 | I6: =H6 -> 0.421 | J6: =I6 -> 0.421 | K6: =J6 -> 0.421 | L6: =K6 -> 0.421 | M6: =L6 -> 0.421 | N6: =M6 -> 0.421 | O6: =N6 -> 0.421 | P6: =O6 -> 0.421 | ... Z6: =Y6 -> 0.421
C7: 上网电价（不含增值税）(元/kW.h) | G7: =G6/(1+增值税率) -> 0.37256637 | H7: =H6/(1+增值税率) -> 0.37256637 | I7: =H7 -> 0.37256637 | J7: =I7 -> 0.37256637 | K7: =J7 -> 0.37256637 | L7: =K7 -> 0.37256637 | M7: =L7 -> 0.37256637 | N7: =M7 -> 0.37256637 | O7: =N7 -> 0.37256637 | P7: =O7 -> 0.37256637 | ... Z7: =Y7 -> 0.37256637
B8: 1 | C8: 发电销售收入 | G8: =G5*G7 -> 1811.4177 | H8: =H5*H7 -> 1811.4177 | I8: =I5*I7 -> 1811.4177 | J8: =J5*J7 -> 1811.4177 | K8: =K5*K7 -> 1811.4177 | L8: =L5*L7 -> 1811.4177 | M8: =M5*M7 -> 1811.4177 | N8: =N5*N7 -> 1811.4177 | ... Z8: =Z5*Z7 -> 1811.4177 | AA8: =SUM(D8:Z8) -> 36228.354
B9: 2 | C9: 销售税金附加 | G9: =G10+G11 -> 0 | H9: =H10+H11 -> 0 | I9: =I10+I11 -> 0 | J9: =J10+J11 -> 0 | K9: =K10+K11 -> 0 | L9: =L10+L11 -> 0 | M9: =M10+M11 -> 0 | N9: =N10+N11 -> 0 | ... Z9: =Z10+Z11 -> 23.54843 | AA9: =SUM(D9:Z9) -> 74.610416
B10: 2.1 | C10: 城市维护建设费 | G10: =G40*参数表!$C$33 -> 0 | H10: =H40*参数表!$C$33 -> 0 | I10: =I40*参数表!$C$33 -> 0 | J10: =J40*参数表!$C$33 -> 0 | K10: =K40*参数表!$C$33 -> 0 | L10: =L40*参数表!$C$33 -> 0 | M10: =M40*参数表!$C$33 -> 0 | N10: =N40*参数表!$C$33 -> 0 | ... Z10: =Z40*参数表!$C$33 -> 11.774215 | AA10: =SUM(D10:Z10) -> 37.305208
B11: 2.2 | C11: 教育费附加 | G11: =G40*参数表!$C$34 -> 0 | H11: =H40*参数表!$C$34 -> 0 | I11: =I40*参数表!$C$34 -> 0 | J11: =J40*参数表!$C$34 -> 0 | K11: =K40*参数表!$C$34 -> 0 | L11: =L40*参数表!$C$34 -> 0 | M11: =M40*参数表!$C$34 -> 0 | N11: =N40*参数表!$C$34 -> 0 | ... Z11: =Z40*参数表!$C$34 -> 11.774215 | AA11: =SUM(D11:Z11) -> 37.305208
B12: 4 | C12: 增值税即征即退补贴 | G12: =IF(G4>参数表!$C$32,0,损益!G41) -> 0 | H12: =IF(H4>参数表!$C$32,0,损益!H41) -> 0 | I12: =IF(I4>参数表!$C$32,0,损益!I41) -> 0 | J12: =IF(J4>参数表!$C$32,0,损益!J41) -> 0 | K12: =IF(K4>参数表!$C$32,0,损益!K41) -> 0 | L12: =IF(L4>参数表!$C$32,0,损益!L41) -> 0 | M12: =IF(M4>参数表!$C$32,0,损益!M41) -> 0 | N12: =IF(N4>参数表!$C$32,0,损益!N41) -> 0 | ... Z12: =IF(Z4>参数表!$C$32,0,损益!Z41) -> 117.74215 | AA12: =SUM(D12:Z12) -> 373.05208
B13: 5 | C13: 营业外收入 | AA13: =SUM(D13:Z13) -> 0
B14: 6 | C14: 总成本费用 | G14: =成本!E21 -> 4567.3186 | H14: =成本!F21 -> 4556.1023 | I14: =成本!G21 -> 4539.7339 | J14: =成本!H21 -> 4524.3128 | K14: =成本!I21 -> 4507.743 | L14: =成本!J21 -> 4803.2833 | M14: =成本!K21 -> 4797.8213 | N14: =成本!L21 -> 4791.57 | ... Z14: =成本!X21 -> 2797.801 | AA14: =SUM(D14:Z14) -> 85089.478
B15: 7 | C15: 利润总额 | G15: =G8-G9-G14+G12+G13 -> -2755.9009 | H15: =H8-H9-H14+H12+H13 -> -2744.6846 | I15: =I8-I9-I14+I12+I13 -> -2728.3162 | J15: =J8-J9-J14+J12+J13 -> -2712.8951 | K15: =K8-K9-K14+K12+K13 -> -2696.3253 | L15: =L8-L9-L14+L12+L13 -> -2991.8656 | M15: =M8-M9-M14+M12+M13 -> -2986.4036 | N15: =N8-N9-N14+N12+N13 -> -2980.1523 | ... Z15: =Z8-Z9-Z14+Z12+Z13 -> -892.18955 | AA15: =SUM(D15:Z15) -> -48562.682
B16: 8 | C16: 累计税后利润及弥补亏损 | F16: -0.001 | G16: =G15-G25+G24+F16 -> -2755.9019 | H16: =H15-H25+H24+G16 -> -5500.5865 | I16: =I15-I25+I24+H16 -> -8228.9027 | J16: =J15-J25+J24+I16 -> -10941.798 | K16: =K15-K25+K24+J16 -> -13638.123 | L16: =L15-L25+L24+K16 -> -13874.088 | M16: =M15-M25+M24+L16 -> -14115.807 | N16: =N15-N25+N24+M16 -> -14367.643 | ... Z16: =Z15-Z25+Z24+Y16 -> -4292.2178 | AA16: =MIN(G16:Z16) -> -15735.84
A19: C | C19: 所得税
C20: 所得税率 | G20: 0 | H20: 0 | I20: 0 | J20: =IF(参数表!C36="否",所得税率/2,IF(J4<=2030,参数表!C37/2,所得税率/2)) -> 0.125 | K20: =J20 -> 0.125 | L20: =K20 -> 0.125 | M20: =IF(参数表!C36="否",所得税率,IF(J4<=2030,参数表!C37,所得税率)) -> 0.25 | N20: =M20 -> 0.25 | O20: =N20 -> 0.25 | P20: =O20 -> 0.25 | Q20: =P20 -> 0.25 | R20: =Q20 -> 0.25 | S20: =R20 -> 0.25 | T20: =S20 -> 0.25 | U20: =T20 -> 0.25 | ... Z20: =Y20 -> 0.25
B21: 9 | C21: 所得税 | G21: =IF(G15<0,0,(G15-G22)*G20) -> 0 | H21: =IF(H15<0,0,(H15-H22)*H20) -> 0 | I21: =IF(I15<0,0,(I15-I22)*I20) -> 0 | J21: =IF(J15<0,0,(J15-J22)*J20) -> 0 | K21: =IF(K15<0,0,(K15-K22)*K20) -> 0 | L21: =IF(L15<0,0,(L15-L22)*L20) -> 0 | M21: =IF(M15<0,0,(M15-M22)*M20) -> 0 | N21: =IF(N15<0,0,(N15-N22)*N20) -> 0 | ... Z21: =IF(Z15<0,0,(Z15-Z22)*Z20) -> 0
B22: 7 | C22: 弥补以前年度亏损 | G22: =IF(G15<0,0,IF(F16>0,0,MIN(G15,-F16))) -> 0 | H22: =IF(H15<0,0,IF(G16>0,0,MIN(H15,-G16))) -> 0 | I22: =IF(I15<0,0,IF(H16>0,0,MIN(I15,-H16))) -> 0 | J22: =IF(J15<0,0,IF(I16>0,0,MIN(J15,-I16))) -> 0 | K22: =IF(K15<0,0,IF(J16>0,0,MIN(K15,-J16))) -> 0 | L22: =IF(L15<0,0,IF(K16>0,0,MIN(L15,-K16))) -> 0 | M22: =IF(M15<0,0,IF(L16>0,0,MIN(M15,-L16))) -> 0 | N22: =IF(N15<0,0,IF(M16>0,0,MIN(N15,-M16))) -> 0 | ... Z22: =IF(Z15<0,0,IF(Y16>0,0,MIN(Z15,-Y16))) -> 0
C23: 新增亏损 | G23: =IF(G15<0,-G15,0) -> 2755.9009 | H23: =IF(H15<0,-H15,0) -> 2744.6846 | I23: =IF(I15<0,-I15,0) -> 2728.3162 | J23: =IF(J15<0,-J15,0) -> 2712.8951 | K23: =IF(K15<0,-K15,0) -> 2696.3253 | L23: =IF(L15<0,-L15,0) -> 2991.8656 | M23: =IF(M15<0,-M15,0) -> 2986.4036 | N23: =IF(N15<0,-N15,0) -> 2980.1523 | ... Z23: =IF(Z15<0,-Z15,0) -> 892.18955
C24: 到期亏损 | L24: =IF(SUM($G$23:G23)>(SUM($G$22:L22)+SUM($G$24:K24)),SUM($G$23:G23)-(SUM($G$22:L22)+SUM($G$24:K24)),0) -> 2755.9009 | M24: =IF(SUM($G$23:H23)>(SUM($G$22:M22)+SUM($G$24:L24)),SUM($G$23:H23)-(SUM($G$22:M22)+SUM($G$24:L24)),0) -> 2744.6846 | N24: =IF(SUM($G$23:I23)>(SUM($G$22:N22)+SUM($G$24:M24)),SUM($G$23:I23)-(SUM($G$22:N22)+SUM($G$24:M24)),0) -> 2728.3162 | O24: =IF(SUM($G$23:J23)>(SUM($G$22:O22)+SUM($G$24:N24)),SUM($G$23:J23)-(SUM($G$22:O22)+SUM($G$24:N24)),0) -> 2712.8951 | P24: =IF(SUM($G$23:K23)>(SUM($G$22:P22)+SUM($G$24:O24)),SUM($G$23:K23)-(SUM($G$22:P22)+SUM($G$24:O24)),0) -> 2696.3253 | Q24: =IF(SUM($G$23:L23)>(SUM($G$22:Q22)+SUM($G$24:P24)),SUM($G$23:L23)-(SUM($G$22:Q22)+SUM($G$24:P24)),0) -> 2991.8656 | R24: =IF(SUM($G$23:M23)>(SUM($G$22:R22)+SUM($G$24:Q24)),SUM($G$23:M23)-(SUM($G$22:R22)+SUM($G$24:Q24)),0) -> 2986.4036 | S24: =IF(SUM($G$23:N23)>(SUM($G$22:S22)+SUM($G$24:R24)),SUM($G$23:N23)-(SUM($G$22:S22)+SUM($G$24:R24)),0) -> 2980.1523 | ... Z24: =IF(SUM($G$23:U23)>(SUM($G$22:Z22)+SUM($G$24:Y24)),SUM($G$23:U23)-(SUM($G$22:Z22)+SUM($G$24:Y24)),0) -> 3140.7997
C25: 所得税 | G25: =G21 -> 0 | H25: =H21 -> 0 | I25: =I21 -> 0 | J25: =J21 -> 0 | K25: =K21 -> 0 | L25: =L21 -> 0 | M25: =M21 -> 0 | N25: =N21 -> 0 | ... Z25: =Z21 -> 0
B26: 10 | C26: 净利润 | G26: =IF(G15<=0,0,G15-G22-G25) -> 0 | H26: =IF(H15<=0,0,H15-H22-H25) -> 0 | I26: =IF(I15<=0,0,I15-I22-I25) -> 0 | J26: =IF(J15<=0,0,J15-J22-J25) -> 0 | K26: =IF(K15<=0,0,K15-K22-K25) -> 0 | L26: =IF(L15<=0,0,L15-L22-L25) -> 0 | M26: =IF(M15<=0,0,M15-M22-M25) -> 0 | N26: =IF(N15<=0,0,N15-N22-N25) -> 0 | ... Z26: =IF(Z15<=0,0,Z15-Z22-Z25) -> 0 | AA26: =SUM(D26:Z26) -> 0
B27: 11 | C27: 法定盈余公积金 | G27: =IF(G16<=0,0,G26*盈余公积金) -> 0 | H27: =IF(H16<=0,0,H26*盈余公积金) -> 0 | I27: =IF(I16<=0,0,I26*盈余公积金) -> 0 | J27: =IF(J16<=0,0,J26*盈余公积金) -> 0 | K27: =IF(K16<=0,0,K26*盈余公积金) -> 0 | L27: =IF(L16<=0,0,L26*盈余公积金) -> 0 | M27: =IF(M16<=0,0,M26*盈余公积金) -> 0 | N27: =IF(N16<=0,0,N26*盈余公积金) -> 0 | ... Z27: =IF(Z16<=0,0,Z26*盈余公积金) -> 0 | AA27: =SUM(D27:Z27) -> 0
B28: 12 | C28: 法定公益金 | G28: 0 | H28: 0 | I28: 0 | J28: 0 | K28: 0 | L28: 0 | M28: 0 | N28: 0 | O28: 0 | P28: 0 | Q28: 0 | R28: 0 | S28: 0 | T28: 0 | U28: 0 | V28: 0 | W28: 0 | X28: 0 | Y28: 0 | Z28: 0 | AA28: =SUM(D28:Z28) -> 0
B29: 13 | C29: 可供分配利润 | G29: =IF(G16<=0,0,G26-G27-G28) -> 0 | H29: =IF(H16<=0,0,H26-H27-H28) -> 0 | I29: =IF(I16<=0,0,I26-I27-I28) -> 0 | J29: =IF(J16<=0,0,J26-J27-J28) -> 0 | K29: =IF(K16<=0,0,K26-K27-K28) -> 0 | L29: =IF(L16<=0,0,L26-L27-L28) -> 0 | M29: =IF(M16<=0,0,M26-M27-M28) -> 0 | N29: =IF(N16<=0,0,N26-N27-N28) -> 0 | ... Z29: =IF(Z16<=0,0,Z26-Z27-Z28) -> 0 | AA29: =SUM(D29:Z29) -> 0
B30: 14 | C30: 偿还上年短期借款需要利润
B31: 15 | C31: 偿还本年长期贷款需要利润
B32: 16 | C32: 实际利润分配 | G32: =财务计划!E31 -> 0 | H32: =财务计划!F31 -> 0 | I32: =财务计划!G31 -> 0 | J32: =财务计划!H31 -> 0 | K32: =财务计划!I31 -> 0 | L32: =财务计划!J31 -> 0 | M32: =财务计划!K31 -> 0 | N32: =财务计划!L31 -> 0 | ... Z32: =财务计划!X31 -> 0
B33: 17 | C33: 未分配利润 | G33: =G29-G32+IF(G15<0,G15,G22) -> -2755.9009 | H33: =H29-H32+IF(H15<0,H15,H22) -> -2744.6846 | I33: =I29-I32+IF(I15<0,I15,I22) -> -2728.3162 | J33: =J29-J32+IF(J15<0,J15,J22) -> -2712.8951 | K33: =K29-K32+IF(K15<0,K15,K22) -> -2696.3253 | L33: =L29-L32+IF(L15<0,L15,L22) -> -2991.8656 | M33: =M29-M32+IF(M15<0,M15,M22) -> -2986.4036 | N33: =N29-N32+IF(N15<0,N15,N22) -> -2980.1523 | ... Z33: =Z29-Z32+IF(Z15<0,Z15,Z22) -> -892.18955
B34: 18 | C34: 累计未分配利润
C35: 营业外收入(增值税即征即退)
C36: 设备进项税总额 | G36: =成本!D28 -> 3963.5819
C37: 销项税额 | G37: =G8*增值税率 -> 235.4843 | H37: =H8*增值税率 -> 235.4843 | I37: =I8*增值税率 -> 235.4843 | J37: =J8*增值税率 -> 235.4843 | K37: =K8*增值税率 -> 235.4843 | L37: =L8*增值税率 -> 235.4843 | M37: =M8*增值税率 -> 235.4843 | N37: =N8*增值税率 -> 235.4843 | ... Z37: =Z8*增值税率 -> 235.4843
C38: 代抵扣的增值税进项净值 | G38: =G36-G37 -> 3728.0976 | H38: =G38-H37 -> 3492.6133 | I38: =IF(H38-I37>0,H38-I37,0) -> 3257.129 | J38: =IF(I38-J37>0,I38-J37,0) -> 3021.6447 | K38: =IF(J38-K37>0,J38-K37,0) -> 2786.1604 | L38: =IF(K38-L37>0,K38-L37,0) -> 2550.6761 | M38: =IF(L38-M37>0,L38-M37,0) -> 2315.1918 | N38: =IF(M38-N37>0,M38-N37,0) -> 2079.7075 | O38: =IF(N38-O37>0,N38-O37,0) -> 1844.2231 | P38: =IF(O38-P37>0,O38-P37,0) -> 1608.7388 | ... Z38: =IF(Y38-Z37>0,Y38-Z37,0) -> 0
C39: 进项税额抵扣 | G39: =G37 -> 235.4843 | H39: =IF(G38>H37,H37,G38) -> 235.4843 | I39: =IF(H38>I37,I37,H38) -> 235.4843 | J39: =IF(I38>J37,J37,I38) -> 235.4843 | K39: =IF(J38>K37,K37,J38) -> 235.4843 | L39: =IF(K38>L37,L37,K38) -> 235.4843 | M39: =IF(L38>M37,M37,L38) -> 235.4843 | N39: =IF(M38>N37,N37,M38) -> 235.4843 | O39: =IF(N38>O37,O37,N38) -> 235.4843 | ... Z39: =IF(Y38>Z37,Z37,Y38) -> 0
C40: 应交税金 | G40: =(G37-G39)/2 -> 0 | H40: =(H37-H39)/2 -> 0 | I40: =(I37-I39) -> 0 | J40: =(J37-J39) -> 0 | K40: =(K37-K39) -> 0 | L40: =(L37-L39) -> 0 | M40: =(M37-M39) -> 0 | N40: =(N37-N39) -> 0 | O40: =(O37-O39) -> 0 | P40: =(P37-P39) -> 0 | ... Z40: =(Z37-Z39) -> 235.4843
C41: 营业外收入(增值税减半征收) | G41: =(G37-G39)/2 -> 0 | H41: =(H37-H39)/2 -> 0 | I41: =(I37-I39)/2 -> 0 | J41: =(J37-J39)/2 -> 0 | K41: =(K37-K39)/2 -> 0 | L41: =(L37-L39)/2 -> 0 | M41: =(M37-M39)/2 -> 0 | N41: =(N37-N39)/2 -> 0 | ... Z41: =(Z37-Z39)/2 -> 117.74215

Sheet 成本
B1: 总成本估算表
B2: 表
B3: 序号 | C3: 项目 | D3: 建设期 | E3: 运 营 期
D4: 1 | E4: 1 | F4: =E4+1 -> 2 | G4: =F4+1 -> 3 | H4: =G4+1 -> 4 | I4: =H4+1 -> 5 | J4: =I4+1 -> 6 | K4: =J4+1 -> 7 | L4: =K4+1 -> 8 | M4: =L4+1 -> 9 | ... X4: =W4+1 -> 20
B6: 1 | C6: 折旧费 | E6: =E30 -> 2480.5476 | F6: =F30 -> 2480.5476 | G6: =G30 -> 2480.5476 | H6: =H30 -> 2480.5476 | I6: =I30 -> 2480.5476 | J6: =J30 -> 2480.5476 | K6: =K30 -> 2480.5476 | L6: =L30 -> 2480.5476 | ... X6: =X30 -> 0 | Y6: =SUM(D6:X6) -> 37208.215
B7: 2 | C7: 修理费 | E7: =$D$29*参数表!D44 -> 78.333084 | F7: =$D$29*参数表!E44 -> 78.333084 | G7: =$D$29*参数表!F44 -> 78.333084 | H7: =$D$29*参数表!G44 -> 78.333084 | I7: =$D$29*参数表!H44 -> 78.333084 | J7: =$D$29*参数表!I44 -> 391.66542 | K7: =$D$29*参数表!J44 -> 391.66542 | L7: =$D$29*参数表!K44 -> 391.66542 | ... X7: =$D$29*参数表!W44 -> 783.33084 | Y7: =SUM(D7:X7) -> 9204.1373
B8: 3 | C8: 工资及福利等 | E8: =参数表!$C$45*参数表!$C$46*(1+参数表!$C$47) -> 144 | F8: =参数表!$C$45*参数表!$C$46*(1+参数表!$C$47) -> 144 | G8: =参数表!$C$45*参数表!$C$46*(1+参数表!$C$47) -> 144 | H8: =参数表!$C$45*参数表!$C$46*(1+参数表!$C$47) -> 144 | I8: =参数表!$C$45*参数表!$C$46*(1+参数表!$C$47) -> 144 | J8: =参数表!$C$45*参数表!$C$46*(1+参数表!$C$47) -> 144 | K8: =参数表!$C$45*参数表!$C$46*(1+参数表!$C$47) -> 144 | L8: =参数表!$C$45*参数表!$C$46*(1+参数表!$C$47) -> 144 | ... X8: =参数表!$C$45*参数表!$C$46*(1+参数表!$C$47) -> 144 | Y8: =SUM(D8:X8) -> 2880
B9: 4 | C9: 保险费 | E9: =E31*参数表!$C$50 -> 91.714985 | F9: =F31*参数表!$C$50 -> 85.513616 | G9: =G31*参数表!$C$50 -> 79.312247 | H9: =H31*参数表!$C$50 -> 73.110878 | I9: =I31*参数表!$C$50 -> 66.909509 | J9: =J31*参数表!$C$50 -> 60.70814 | K9: =K31*参数表!$C$50 -> 54.506771 | L9: =L31*参数表!$C$50 -> 48.305402 | ... X9: =X31*参数表!$C$50 -> 4.8958177 | Y9: =SUM(D9:X9) -> 749.06011
B10: 5 | C10: 材料费 | E10: =参数表!$C$49*参数表!$C$2 -> 20 | F10: =参数表!$C$49*参数表!$C$2 -> 20 | G10: =参数表!$C$49*参数表!$C$2 -> 20 | H10: =参数表!$C$49*参数表!$C$2 -> 20 | I10: =参数表!$C$49*参数表!$C$2 -> 20 | J10: =参数表!$C$49*参数表!$C$2 -> 20 | K10: =参数表!$C$49*参数表!$C$2 -> 20 | L10: =参数表!$C$49*参数表!$C$2 -> 20 | ... X10: =参数表!$C$49*参数表!$C$2 -> 20 | Y10: =SUM(D10:X10) -> 400
B11: 6 | C11: 境外银行转贷费 | Y11: =SUM(D11:X11) -> 0
B12: 7 | C12: 摊销费 | E12: =F56 -> 0 | F12: =G56 -> 0 | G12: =H56 -> 0 | H12: =I56 -> 0 | I12: =J56 -> 0 | J12: =K56 -> 0 | K12: =L56 -> 0 | L12: =M56 -> 0 | ... X12: =Y56 -> 0 | Y12: =SUM(D12:X12) -> 0
B13: 8 | C13: 利息支出 | E13: =SUM(E14:E17) -> 1692.7228 | F13: =SUM(F14:F17) -> 1687.708 | G13: =SUM(G14:G17) -> 1677.5409 | H13: =SUM(H14:H17) -> 1668.3212 | I13: =SUM(I14:I17) -> 1657.9527 | J13: =SUM(J14:J17) -> 1646.3621 | K13: =SUM(K14:K17) -> 1647.1015 | L13: =SUM(L14:L17) -> 1647.0516 | ... X13: =SUM(X14:X17) -> 1785.5743 | Y13: =SUM(D13:X13) -> 33448.066
B14: 8.1 | C14: 长期贷款利息 | E14: =还贷!E11 -> 1690.1128 | F14: =还贷!F11 -> 1611.1415 | G14: =还贷!G11 -> 1528.3006 | H14: =还贷!H11 -> 1441.4005 | I14: =还贷!I11 -> 1350.2423 | J14: =还贷!J11 -> 1254.6173 | K14: =还贷!K11 -> 1154.3067 | L14: =还贷!L11 -> 1049.0809 | ... X14: =还贷!X11 -> -1.2050627 | Y14: =SUM(D14:X14) -> 15003.867
B15: 8.2 | C15: 流动资金贷款利息 | E15: =还贷!E16 -> 2.61 | F15: =还贷!F16 -> 2.61 | G15: =还贷!G16 -> 2.61 | H15: =还贷!H16 -> 2.61 | I15: =还贷!I16 -> 2.61 | J15: =还贷!J16 -> 2.61 | K15: =还贷!K16 -> 2.61 | L15: =还贷!L16 -> 2.61 | ... X15: =还贷!X16 -> 2.61 | Y15: =SUM(D15:X15) -> 52.2
B16: 8.3 | C16: 短期借款利息 | E16: =还贷!E21 -> 0 | F16: =还贷!F21 -> 73.956452 | G16: =还贷!G21 -> 146.63031 | H16: =还贷!H21 -> 224.31069 | I16: =还贷!I21 -> 305.10041 | J16: =还贷!J21 -> 389.13472 | K16: =还贷!K21 -> 490.18473 | L16: =还贷!L21 -> 595.36064 | ... X16: =还贷!X21 -> 1784.1694 | Y16: =SUM(D16:X16) -> 18391.999
B17: 8.4 | C17: 盈余资金利息收入 | Y17: =SUM(D17:X17) -> 0
B18: 9 | C18: 其他费用 | E18: =参数表!$C$48*参数表!$C$2 -> 60 | F18: =参数表!$C$48*参数表!$C$2 -> 60 | G18: =参数表!$C$48*参数表!$C$2 -> 60 | H18: =参数表!$C$48*参数表!$C$2 -> 60 | I18: =参数表!$C$48*参数表!$C$2 -> 60 | J18: =参数表!$C$48*参数表!$C$2 -> 60 | K18: =参数表!$C$48*参数表!$C$2 -> 60 | L18: =参数表!$C$48*参数表!$C$2 -> 60 | ... X18: =参数表!$C$48*参数表!$C$2 -> 60 | Y18: =SUM(D18:X18) -> 1200
C19: 固定成本 | Y19: =SUM(D19:X19) -> 0
C20: 可变成本 | Y20: =SUM(D20:X20) -> 0
C21: 总成本费用 | E21: =SUM(E6:E13)+E18 -> 4567.3186 | F21: =SUM(F6:F13)+F18 -> 4556.1023 | G21: =SUM(G6:G13)+G18 -> 4539.7339 | H21: =SUM(H6:H13)+H18 -> 4524.3128 | I21: =SUM(I6:I13)+I18 -> 4507.743 | J21: =SUM(J6:J13)+J18 -> 4803.2833 | K21: =SUM(K6:K13)+K18 -> 4797.8213 | L21: =SUM(L6:L13)+L18 -> 4791.57 | ... X21: =SUM(X6:X13)+X18 -> 2797.801 | Y21: =SUM(D21:X21) -> 85089.478
C22: 其中：经营成本 | E22: =E7+E8+E9+E10+E18 -> 394.04807 | F22: =F7+F8+F9+F10+F18 -> 387.8467 | G22: =G7+G8+G9+G10+G18 -> 381.64533 | H22: =H7+H8+H9+H10+H18 -> 375.44396 | I22: =I7+I8+I9+I10+I18 -> 369.24259 | J22: =J7+J8+J9+J10+J18 -> 676.37356 | K22: =K7+K8+K9+K10+K18 -> 670.17219 | L22: =L7+L8+L9+L10+L18 -> 663.97082 | ... X22: =X7+X8+X9+X10+X18 -> 1012.2267 | Y22: =SUM(D22:X22) -> 14433.197
S24: 人民币单位：万元
B25: 序号 | C25: 项目 | D25: 合计 | E25: 运 营 期
E26: 1 | F26: =F4 -> 2 | G26: =G4 -> 3 | H26: =H4 -> 4 | I26: =I4 -> 5 | J26: =J4 -> 6 | K26: =K4 -> 7 | L26: =L4 -> 8 | M26: =M4 -> 9 | ... X26: =X4 -> 20
B27: 1 | C27: 固定资产
C28: 待抵扣的固定资产进项税额 | D28: =参数表!C20 -> 3963.5819
C29: 原值 | D29: =投资计划!C9-D28 -> 39166.542
C30: 当期折旧费 | E30: =IF(参数表!$C$39-E26+$E$26-1>=0,$D$29*参数表!$C$41*参数表!D5,0) -> 2480.5476 | F30: =IF(参数表!$C$39-F26+$E$26-1>=0,$D$29*参数表!$C$41*参数表!E5,0) -> 2480.5476 | G30: =IF(参数表!$C$39-G26+$E$26-1>=0,$D$29*参数表!$C$41*参数表!F5,0) -> 2480.5476 | H30: =IF(参数表!$C$39-H26+$E$26-1>=0,$D$29*参数表!$C$41*参数表!G5,0) -> 2480.5476 | I30: =IF(参数表!$C$39-I26+$E$26-1>=0,$D$29*参数表!$C$41*参数表!H5,0) -> 2480.5476 | J30: =IF(参数表!$C$39-J26+$E$26-1>=0,$D$29*参数表!$C$41*参数表!I5,0) -> 2480.5476 | K30: =IF(参数表!$C$39-K26+$E$26-1>=0,$D$29*参数表!$C$41*参数表!J5,0) -> 2480.5476 | L30: =IF(参数表!$C$39-L26+$E$26-1>=0,$D$29*参数表!$C$41*参数表!K5,0) -> 2480.5476 | ... X30: =IF(参数表!$C$39-X26+$E$26-1>=0,$D$29*参数表!$C$41*参数表!W5,0) -> 0
C31: 净值 | E31: =D29-E30 -> 36685.994 | F31: =E31-F30 -> 34205.447 | G31: =F31-G30 -> 31724.899 | H31: =G31-H30 -> 29244.351 | I31: =H31-I30 -> 26763.804 | J31: =I31-J30 -> 24283.256 | K31: =J31-K30 -> 21802.708 | L31: =K31-L30 -> 19322.161 | M31: =L31-M30 -> 16841.613 | ... X31: =W31-X30 -> 1958.3271
B45: 流动负债-购进固定资产进项税待抵扣估算表
S46: 人民币单位：万元
B47: 序号 | C47: 项目 | D47: 合计 | E47: 建设期 | F47: 运营期
E48: 1 | F48: 1 | G48: =F26 -> 2 | H48: =G26 -> 3 | I48: =H26 -> 4 | J48: =I26 -> 5 | K48: =J26 -> 6 | L48: =K26 -> 7 | M48: =L26 -> 8 | N48: =M26 -> 9 | ... Y48: =X26 -> 20
B49: 1 | C49: 递延资产(代抵扣固定资产进项税额)
C50: 原值 | D50: =D28 -> 3963.5819
C51: 当期摊销费 | F51: =损益!G8*增值税率 -> 235.4843 | G51: =IF(F52<=损益!H8*增值税率,F52,损益!H8*增值税率) -> 235.4843 | H51: =IF(G52<=损益!I8*增值税率,G52,损益!I8*增值税率) -> 235.4843 | I51: =IF(H52<=损益!J8*增值税率,H52,损益!J8*增值税率) -> 235.4843 | J51: =IF(I52<=损益!K8*增值税率,I52,损益!K8*增值税率) -> 235.4843 | K51: =IF(J52<=损益!L8*增值税率,J52,损益!L8*增值税率) -> 235.4843 | L51: =IF(K52<=损益!M8*增值税率,K52,损益!M8*增值税率) -> 235.4843 | M51: =IF(L52<=损益!N8*增值税率,L52,损益!N8*增值税率) -> 235.4843 | N51: =IF(M52<=损益!O8*增值税率,M52,损益!O8*增值税率) -> 235.4843 | ... Y51: =IF(X52<=损益!Z8*增值税率,X52,损益!Z8*增值税率) -> 0
C52: 净值 | F52: =D50-F51 -> 3728.0976 | G52: =F52-G51 -> 3492.6133 | H52: =G52-H51 -> 3257.129 | I52: =H52-I51 -> 3021.6447 | J52: =I52-J51 -> 2786.1604 | K52: =J52-K51 -> 2550.6761 | L52: =K52-L51 -> 2315.1918 | M52: =L52-M51 -> 2079.7075 | N52: =M52-N51 -> 1844.2231 | ... Y52: =X52-Y51 -> 0
B54: 2 | C54: 长期待摊费用 | D54: 0
C55: 原值 | E55: =参数表!C58 -> 0 | F55: =参数表!D58 -> 0 | G55: =参数表!E58 -> 0 | H55: =参数表!F58 -> 0 | I55: =参数表!G58 -> 0 | J55: =参数表!H58 -> 0 | K55: =参数表!I58 -> 0 | L55: =参数表!J58 -> 0 | ... Y55: =参数表!W58 -> 0
C56: 当期摊销费 | F56: =参数表!D59 -> 0 | G56: =参数表!E59 -> 0 | H56: =参数表!F59 -> 0 | I56: =参数表!G59 -> 0 | J56: =参数表!H59 -> 0 | K56: =参数表!I59 -> 0 | L56: =参数表!J59 -> 0 | M56: =参数表!K59 -> 0 | ... Y56: =参数表!W59 -> 0
C57: 净值 | E57: =-E56+E55 -> 0 | F57: =E57-F56+F55 -> 0 | G57: =F57-G56+G55 -> 0 | H57: =G57-H56+H55 -> 0 | I57: =H57-I56+I55 -> 0 | J57: =I57-J56+J55 -> 0 | K57: =J57-K56+K55 -> 0 | L57: =K57-L56+L55 -> 0 | M57: =L57-M56+M55 -> 0 | ... Y57: =X57-Y56+Y55 -> 0

Sheet 现金流量
B1: 项目现金流量表
B3: 序号 | C3: 项目 | D3: 建设期 | E3: 运 营 期 | Y3: 合计
D4: =成本!D4 -> 1 | E4: 1 | F4: 2 | G4: 3 | H4: 4 | I4: 5 | J4: 6 | K4: 7 | L4: 8 | M4: 9 | N4: 10 | O4: 11 | P4: 12 | Q4: 13 | R4: 14 | S4: 15 | T4: 16 | U4: 17 | V4: 18 | W4: 19 | X4: 20
B5: 1 | C5: 现金流入 | E5: =SUM(E6:E10) -> 1998.282 | F5: =SUM(F6:F10) -> 2095.522 | G5: =SUM(G6:G10) -> 2046.902 | H5: =SUM(H6:H10) -> 2046.902 | I5: =SUM(I6:I10) -> 2046.902 | J5: =SUM(J6:J10) -> 2046.902 | K5: =SUM(K6:K10) -> 2046.902 | L5: =SUM(L6:L10) -> 2046.902 | ... X5: =SUM(X6:X10) -> 4182.9712 | Y5: =SUM(E5:X5) -> 43329.419
B6: 1.1 | C6: 发电销售收入 | E6: =损益!G8-财务计划!E10 -> 1762.7977 | F6: =损益!H8-财务计划!F10 -> 1860.0377 | G6: =损益!I8-财务计划!G10 -> 1811.4177 | H6: =损益!J8-财务计划!H10 -> 1811.4177 | I6: =损益!K8-财务计划!I10 -> 1811.4177 | J6: =损益!L8-财务计划!J10 -> 1811.4177 | K6: =损益!M8-财务计划!K10 -> 1811.4177 | L6: =损益!N8-财务计划!L10 -> 1811.4177 | ... X6: =损益!Z8-财务计划!X10 -> 1811.4177 | Y6: =SUM(E6:X6) -> 36228.354
C7: 增值税即征即退补贴 | E7: =损益!G12 -> 0 | F7: =损益!H12 -> 0 | G7: =损益!I12 -> 0 | H7: =损益!J12 -> 0 | I7: =损益!K12 -> 0 | J7: =损益!L12 -> 0 | K7: =损益!M12 -> 0 | L7: =损益!N12 -> 0 | ... X7: =损益!Z12 -> 117.74215 | Y7: =SUM(E7:X7) -> 373.05208
C8: 增值税销项税额 | E8: =损益!G37 -> 235.4843 | F8: =损益!H37 -> 235.4843 | G8: =损益!I37 -> 235.4843 | H8: =损益!J37 -> 235.4843 | I8: =损益!K37 -> 235.4843 | J8: =损益!L37 -> 235.4843 | K8: =损益!M37 -> 235.4843 | L8: =损益!N37 -> 235.4843 | ... X8: =损益!Z37 -> 235.4843 | Y8: =SUM(E8:X8) -> 4709.686
B9: 1.2 | C9: 回收固定资产余值 | E9: 0 | F9: 0 | G9: 0 | H9: 0 | I9: 0 | J9: 0 | K9: 0 | L9: 0 | M9: 0 | N9: 0 | O9: 0 | P9: 0 | Q9: 0 | R9: 0 | S9: 0 | T9: 0 | U9: 0 | V9: 0 | W9: 0 | X9: =成本!X31 -> 1958.3271 | Y9: =SUM(E9:X9) -> 1958.3271
B10: 1.3 | C10: 回收流动资金 | E10: 0 | F10: 0 | G10: 0 | H10: 0 | I10: 0 | J10: 0 | K10: 0 | L10: 0 | M10: 0 | N10: 0 | O10: 0 | P10: 0 | Q10: 0 | R10: 0 | S10: 0 | T10: 0 | U10: 0 | V10: 0 | W10: 0 | X10: =流动资金总额 -> 60 | Y10: =SUM(E10:X10) -> 60
Y11: =SUM(E11:X11) -> 0
B12: 2 | C12: 现金流出 | D12: =SUM(D13:D19) -> 42500 | E12: =SUM(E13:E19) -> 394.04807 | F12: =SUM(F13:F19) -> 387.8467 | G12: =SUM(G13:G19) -> 381.64533 | H12: =SUM(H13:H19) -> 244.87222 | I12: =SUM(I13:I19) -> 239.44602 | J12: =SUM(J13:J19) -> 508.18562 | K12: =SUM(K13:K19) -> 335.34665 | ... X12: =SUM(X13:X19) -> 1494.6056 | Y12: =SUM(E12:X12) -> 12696.547
B13: 2.1 | C13: 固定资产投资 | D13: =投资计划!F6 -> 42440 | E13: =投资计划!G6 -> 0 | F13: 0 | G13: 0 | H13: 0 | I13: 0 | J13: 0 | K13: 0 | L13: 0 | M13: 0 | N13: 0 | O13: 0 | P13: 0 | Q13: 0 | R13: 0 | S13: 0 | T13: 0 | U13: 0 | V13: 0 | W13: 0 | X13: 0 | Y13: =SUM(E13:X13) -> 0
B14: 2.2 | C14: 流动资金 | D14: =投资计划!H8 -> 60 | E14: =投资计划!I8 -> 0 | F14: =投资计划!J8 -> 0 | G14: =投资计划!I8 -> 0 | H14: =投资计划!J8 -> 0 | I14: =投资计划!K8 -> 0 | J14: =投资计划!L8 -> 0 | K14: =投资计划!M8 -> 0 | L14: =投资计划!N8 -> 0 | M14: =投资计划!O8 -> 0 | N14: =投资计划!P8 -> 0 | ... X14: =投资计划!Z8 -> 0 | Y14: =SUM(D14:X14) -> 60
C15: 应交增值税金 | E15: =损益!G40 -> 0 | F15: =损益!H40 -> 0 | G15: =损益!I40 -> 0 | H15: =损益!J40 -> 0 | I15: =损益!K40 -> 0 | J15: =损益!L40 -> 0 | K15: =损益!M40 -> 0 | L15: =损益!N40 -> 0 | ... X15: =损益!Z40 -> 235.4843 | Y15: =SUM(E15:X15) -> 746.10416
C16: 土地租金 | D16: =财务计划!D14 -> 0 | E16: =财务计划!E14 -> 0 | F16: =财务计划!F14 -> 0 | G16: =财务计划!G14 -> 0 | H16: =财务计划!H14 -> 0 | I16: =财务计划!I14 -> 0 | J16: =财务计划!J14 -> 0 | K16: =财务计划!K14 -> 0 | ... X16: =财务计划!X14 -> 0
B17: 2.4 | C17: 经营成本 | E17: =成本!E22 -> 394.04807 | F17: =成本!F22 -> 387.8467 | G17: =成本!G22 -> 381.64533 | H17: =成本!H22 -> 375.44396 | I17: =成本!I22 -> 369.24259 | J17: =成本!J22 -> 676.37356 | K17: =成本!K22 -> 670.17219 | L17: =成本!L22 -> 663.97082 | ... X17: =成本!X22 -> 1012.2267 | Y17: =SUM(E17:X17) -> 14433.197
B18: 2.5 | C18: 销售税金附加 | E18: =损益!G9 -> 0 | F18: =损益!H9 -> 0 | G18: =损益!I9 -> 0 | H18: =损益!J9 -> 0 | I18: =损益!K9 -> 0 | J18: =损益!L9 -> 0 | K18: =损益!M9 -> 0 | L18: =损益!N9 -> 0 | ... X18: =损益!Z9 -> 23.54843 | Y18: =SUM(E18:X18) -> 74.610416
B19: 2.7 | C19: 调整所得税 | E19: 0 | F19: 0 | G19: 0 | H19: =H20*所得税率/2 -> -130.57174 | I19: =I20*所得税率/2 -> -129.79657 | J19: =J20*所得税率/2 -> -168.18794 | K19: =K20*所得税率 -> -334.82553 | L19: =L20*所得税率 -> -333.27519 | M19: =M20*所得税率 -> -331.72485 | N19: =N20*所得税率 -> -330.17451 | O19: =O20*所得税率 -> -377.58234 | P19: =P20*所得税率 -> -376.032 | Q19: =Q20*所得税率 -> -374.48166 | R19: =R20*所得税率 -> -372.93132 | ... X19: =X20*所得税率 -> 223.34619 | Y19: =SUM(E19:X19) -> -2557.3654
C20: 息税前利润 | E20: =损益!G15+成本!E13 -> -1063.178 | F20: =损益!H15+成本!F13 -> -1056.9766 | G20: =损益!I15+成本!G13 -> -1050.7753 | H20: =损益!J15+成本!H13 -> -1044.5739 | I20: =损益!K15+成本!I13 -> -1038.3725 | J20: =损益!L15+成本!J13 -> -1345.5035 | K20: =损益!M15+成本!K13 -> -1339.3021 | L20: =损益!N15+成本!L13 -> -1333.1008 | ... X20: =损益!Z15+成本!X13 -> 893.38477 | Y20: =SUM(E20:X20) -> -15114.617
Y21: =SUM(E21:X21) -> 0
B22: 3 | C22: 净现金流量 | D22: =D5-D12 -> -42500 | E22: =E5-E12 -> 1604.2339 | F22: =F5-F12 -> 1707.6753 | G22: =G5-G12 -> 1665.2567 | H22: =H5-H12 -> 1802.0298 | I22: =I5-I12 -> 1807.456 | J22: =J5-J12 -> 1538.7164 | K22: =K5-K12 -> 1711.5553 | ... X22: =X5-X12 -> 2688.3657 | Y22: =SUM(E22:X22) -> 30632.873
B23: 4 | C23: 累计净现金流量 | D23: =D22 -> -42500 | E23: =D23+E22 -> -40895.766 | F23: =E23+F22 -> -39188.091 | G23: =F23+G22 -> -37522.834 | H23: =G23+H22 -> -35720.804 | I23: =H23+I22 -> -33913.348 | J23: =I23+J22 -> -32374.632 | K23: =J23+K22 -> -30663.077 | L23: =K23+L22 -> -28946.87 | ... X23: =W23+X22 -> -11867.127
C24: 所得税后投资回收年 | J24: =IF(AND(I23<0,J23>0),I4-I23/J22,0) -> 0 | K24: =IF(AND(J23<0,K23>0),J4-J23/K22,0) -> 0 | L24: =IF(AND(K23<0,L23>0),K4-K23/L22,0) -> 0 | M24: =IF(AND(L23<0,M23>0),L4-L23/M22,0) -> 0 | N24: =IF(AND(M23<0,N23>0),M4-M23/N22,0) -> 0 | O24: =IF(AND(N23<0,O23>0),N4-N23/O22,0) -> 0 | P24: =IF(AND(O23<0,P23>0),O4-O23/P22,0) -> 0 | Q24: =IF(AND(P23<0,Q23>0),P4-P23/Q22,0) -> 0 | ... X24: =IF(AND(W23<0,X23>0),W4-W23/X22,0) -> 0 | Y24: =SUM(E24:X24) -> 0
C25: 所得税前净现金流量 | D25: =D22+D19 -> -42500 | E25: =E22+E19 -> 1604.2339 | F25: =F22+F19 -> 1707.6753 | G25: =G22+G19 -> 1665.2567 | H25: =H22+H19 -> 1671.458 | I25: =I22+I19 -> 1677.6594 | J25: =J22+J19 -> 1370.5284 | K25: =K22+K19 -> 1376.7298 | ... X25: =X22+X19 -> 2911.7119
C26: 累计税前净现金流量 | D26: =D25 -> -42500 | E26: =D26+E25 -> -40895.766 | F26: =E26+F25 -> -39188.091 | G26: =F26+G25 -> -37522.834 | H26: =G26+H25 -> -35851.376 | I26: =H26+I25 -> -34173.717 | J26: =I26+J25 -> -32803.188 | K26: =J26+K25 -> -31426.458 | L26: =K26+L25 -> -30043.527 | ... X26: =W26+X25 -> -14424.493
C27: 所得税前投资回收年 | D27: =0 -> 0 | E27: =IF(AND(D26<0,E26>0),D4-D26/E25,0) -> 0 | F27: =IF(AND(E26<0,F26>0),E4-E26/F25,0) -> 0 | G27: =IF(AND(F26<0,G26>0),F4-F26/G25,0) -> 0 | H27: =IF(AND(G26<0,H26>0),G4-G26/H25,0) -> 0 | I27: =IF(AND(H26<0,I26>0),H4-H26/I25,0) -> 0 | J27: =IF(AND(I26<0,J26>0),I4-I26/J25,0) -> 0 | K27: =IF(AND(J26<0,K26>0),J4-J26/K25,0) -> 0 | L27: =IF(AND(K26<0,L26>0),K4-K26/L25,0) -> 0 | ... X27: =IF(AND(W26<0,X26>0),W4-W26/X25,0) -> 0 | Y27: =SUM(E27:X27) -> 0
I28: 所得税后 | L28: 所得税前
C29: 计算指标：财务内部收益率(％) | I29: =IRR(D22:X22)*100 -> -3.0946558 | L29: =IRR(D25:X25)*100 -> -3.7478742
C30: 财务净现值(万元) | E30: Ic= | F30: 0.05 | I30: =NPV(F30,D22:X22) -> -21779.114 | L30: =NPV(F30,D25:X25) -> -23459.716
C31: 投资回收期(含建设期)(年) | I31: =Y24 -> 0 | L31: =Y27 -> 0
B37: 资本金财务现金流量表
B39: 序号 | C39: 项目 | E39: 运 营 期 | Y39: 合计
D40: =D4 -> 1 | E40: =E4 -> 1 | F40: =F4 -> 2 | G40: =G4 -> 3 | H40: =H4 -> 4 | I40: =I4 -> 5 | J40: =J4 -> 6 | K40: =K4 -> 7 | ... X40: =X4 -> 20
B42: 1 | C42: 现金流入 | E42: =SUM(E43:E47) -> 1998.282 | F42: =SUM(F43:F47) -> 2095.522 | G42: =SUM(G43:G47) -> 2046.902 | H42: =SUM(H43:H47) -> 2046.902 | I42: =SUM(I43:I47) -> 2046.902 | J42: =SUM(J43:J47) -> 2046.902 | K42: =SUM(K43:K47) -> 2046.902 | L42: =SUM(L43:L47) -> 2046.902 | ... X42: =SUM(X43:X47) -> 4122.9712 | Y42: =SUM(E42:X42) -> 43269.419
B43: 1.1 | C43: 发电销售收入 | E43: =E6 -> 1762.7977 | F43: =F6 -> 1860.0377 | G43: =G6 -> 1811.4177 | H43: =H6 -> 1811.4177 | I43: =I6 -> 1811.4177 | J43: =J6 -> 1811.4177 | K43: =K6 -> 1811.4177 | L43: =L6 -> 1811.4177 | ... X43: =X6 -> 1811.4177 | Y43: =SUM(E43:X43) -> 36228.354
C44: 增值税即征即退补贴 | E44: =损益!G12 -> 0 | F44: =损益!H12 -> 0 | G44: =损益!I12 -> 0 | H44: =损益!J12 -> 0 | I44: =损益!K12 -> 0 | J44: =损益!L12 -> 0 | K44: =损益!M12 -> 0 | L44: =损益!N12 -> 0 | ... X44: =损益!Z12 -> 117.74215 | Y44: =SUM(E44:X44) -> 373.05208
C45: 增值税销项税额 | E45: =损益!G37 -> 235.4843 | F45: =损益!H37 -> 235.4843 | G45: =损益!I37 -> 235.4843 | H45: =损益!J37 -> 235.4843 | I45: =损益!K37 -> 235.4843 | J45: =损益!L37 -> 235.4843 | K45: =损益!M37 -> 235.4843 | L45: =损益!N37 -> 235.4843 | ... X45: =损益!Z37 -> 235.4843 | Y45: =SUM(E45:X45) -> 4709.686
B46: 1.2 | C46: 回收固定资产余值 | E46: 0 | F46: =F9 -> 0 | G46: 0 | H46: 0 | I46: 0 | J46: 0 | K46: 0 | L46: 0 | M46: 0 | N46: 0 | O46: 0 | P46: 0 | Q46: 0 | R46: 0 | S46: 0 | T46: 0 | U46: 0 | V46: 0 | W46: 0 | X46: =X9 -> 1958.3271 | Y46: =SUM(E46:X46) -> 1958.3271
B47: 1.3 | C47: 回收流动资金 | E47: 0 | F47: 0 | G47: 0 | H47: 0 | I47: 0 | J47: 0 | K47: 0 | L47: 0 | M47: 0 | N47: 0 | O47: 0 | P47: 0 | Q47: 0 | R47: 0 | S47: 0 | T47: 0 | U47: 0 | V47: 0 | W47: 0 | Y47: =SUM(E47:X47) -> 0
Y48: =SUM(E48:X48) -> 0
B49: 2 | C49: 现金流出 | D49: =SUM(D50:D58) -> 8626.0247 | E49: =SUM(E50:E58) -> 1998.282 | F49: =SUM(F50:F58) -> 2095.522 | G49: =SUM(G50:G58) -> 2046.902 | H49: =SUM(H50:H58) -> 2046.902 | I49: =SUM(I50:I58) -> 2046.902 | J49: =SUM(J50:J58) -> 2046.902 | K49: =SUM(K50:K58) -> 2046.902 | ... X49: =SUM(X50:X58) -> 2164.6442 | Y49: =SUM(D49:X49) -> 49937.117
B50: 2.1 | C50: 资本金 | D50: =投资计划!F11 -> 8626.0247 | E50: =投资计划!G11 -> 0 | F50: 0 | G50: 0 | H50: 0 | I50: 0 | J50: 0 | K50: 0 | L50: 0 | M50: 0 | N50: 0 | O50: 0 | P50: 0 | Q50: 0 | R50: 0 | S50: 0 | T50: 0 | U50: 0 | V50: 0 | W50: 0 | X50: 0 | Y50: =SUM(D50:X50) -> 8626.0247
B51: 2.2 | C51: 借款本金偿还 | E51: =还贷!E10-财务计划!E22+财务计划!E28 -> -88.488917 | F51: =还贷!F10-财务计划!F22+财务计划!F28 -> 19.967311 | G51: =还贷!G10-财务计划!G22+财务计划!G28 -> -12.284272 | H51: =还贷!H10-财务计划!H22+财务计划!H28 -> 3.1368249 | I51: =还贷!I10-财务计划!I22+财务计划!I28 -> 19.70669 | J51: =还贷!J10-财务计划!J22+财务计划!J28 -> -275.83362 | K51: =还贷!K10-财务计划!K22+财务计划!K28 -> -270.37166 | L51: =还贷!L10-财务计划!L22+财务计划!L28 -> -264.1204 | ... W51: =还贷!W10-财务计划!W22+财务计划!W28 -> -854.99717 | X51: =还贷!X10-还贷!X18+还贷!X20 -> -892.18955 | Y51: =SUM(E51:X51) -> -7390.8855
B52: 2.3 | C52: 借款利息支付 | E52: =成本!E13 -> 1692.7228 | F52: =成本!F13 -> 1687.708 | G52: =成本!G13 -> 1677.5409 | H52: =成本!H13 -> 1668.3212 | I52: =成本!I13 -> 1657.9527 | J52: =成本!J13 -> 1646.3621 | K52: =成本!K13 -> 1647.1015 | L52: =成本!L13 -> 1647.0516 | ... X52: =成本!X13 -> 1785.5743 | Y52: =SUM(E52:X52) -> 33448.066
B53: 2.4 | C53: 经营成本 | E53: =成本!E22 -> 394.04807 | F53: =成本!F22 -> 387.8467 | G53: =成本!G22 -> 381.64533 | H53: =成本!H22 -> 375.44396 | I53: =成本!I22 -> 369.24259 | J53: =成本!J22 -> 676.37356 | K53: =成本!K22 -> 670.17219 | L53: =成本!L22 -> 663.97082 | ... X53: =成本!X22 -> 1012.2267 | Y53: =SUM(E53:X53) -> 14433.197
C54: 土地租金 | F54: =F16 -> 0 | G54: =G16 -> 0 | H54: =H16 -> 0 | I54: =I16 -> 0 | J54: =J16 -> 0 | K54: =K16 -> 0 | L54: =L16 -> 0 | M54: =M16 -> 0 | ... X54: =X16 -> 0
B55: 2.5 | C55: 应交增值税 | E55: =损益!G40 -> 0 | F55: =损益!H40 -> 0 | G55: =损益!I40 -> 0 | H55: =损益!J40 -> 0 | I55: =损益!K40 -> 0 | J55: =损益!L40 -> 0 | K55: =损益!M40 -> 0 | L55: =损益!N40 -> 0 | ... X55: =损益!Z40 -> 235.4843 | Y55: =SUM(E55:X55) -> 746.10416
B56: 2.7 | C56: 销售税金附加 | E56: =损益!G9 -> 0 | F56: =损益!H9 -> 0 | G56: =损益!I9 -> 0 | H56: =损益!J9 -> 0 | I56: =损益!K9 -> 0 | J56: =损益!L9 -> 0 | K56: =损益!M9 -> 0 | L56: =损益!N9 -> 0 | ... X56: =损益!Z9 -> 23.54843 | Y56: =SUM(E56:X56) -> 74.610416
B57: 2.8 | C57: 所得税 | E57: =损益!G21 -> 0 | F57: =损益!H21 -> 0 | G57: =损益!I21 -> 0 | H57: =损益!J21 -> 0 | I57: =损益!K21 -> 0 | J57: =损益!L21 -> 0 | K57: =损益!M21 -> 0 | L57: =损益!N21 -> 0 | ... X57: =损益!Z21 -> 0 | Y57: =SUM(E57:X57) -> 0 | Z57: =Y57+Y55+Y56 -> 820.71458
B58: 2.9 | C58: 长期待摊租金 | E58: =E13 -> 0
B59: 3 | C59: 净现金流量 | D59: =D42-D49 -> -8626.0247 | E59: =E42-E49 -> 0 | F59: =F42-F49 -> 0 | G59: =G42-G49 -> 0 | H59: =H42-H49 -> 0 | I59: =I42-I49 -> 0 | J59: =J42-J49 -> 0 | K59: =K42-K49 -> 0 | ... X59: =X42-X49 -> 1958.3271 | Y59: =SUM(D59:X59) -> -6667.6976
B60: 4 | C60: 累计净现金流量 | D60: =D59 -> -8626.0247 | E60: =D60+E59 -> -8626.0247 | F60: =E60+F59 -> -8626.0247 | G60: =F60+G59 -> -8626.0247 | H60: =G60+H59 -> -8626.0247 | I60: =H60+I59 -> -8626.0247 | J60: =I60+J59 -> -8626.0247 | K60: =J60+K59 -> -8626.0247 | L60: =K60+L59 -> -8626.0247 | ... X60: =W60+X59 -> -6667.6976
C61: 计算指标：资本金财务内部收益率(%)： | H61: =IRR(D59:X59) -> -0.071453352
C62: 资本金财务净现值(万元) | F62: ic= | G62: 0.08 | H62: =NPV(G62,D59:X59) -> -7598.027
B80: 投资方财务现金流量表
B82: 序号 | C82: 项目 | E82: 建设期 | H82: 运 营 期 | Y82: 合计
D83: =D40 -> 1 | E83: =E40 -> 1 | F83: =F40 -> 2 | G83: =G40 -> 3 | H83: =H40 -> 4 | I83: =I40 -> 5 | J83: =J40 -> 6 | K83: =K40 -> 7 | ... X83: =X40 -> 20
B84: 1 | C84: 现金流入 | E84: =E85+E86 -> 0 | F84: =F85+F86 -> 0 | G84: =G85+G86 -> 0 | H84: =H85+H86 -> 0 | I84: =I85+I86 -> 0 | J84: =J85+J86 -> 0 | K84: =K85+K86 -> 0 | L84: =L85+L86 -> 0 | ... X84: =X85+X86 -> 1958.3271
B85: 1.1 | C85: 利润分配 | E85: =损益!G32 -> 0 | F85: =损益!H32 -> 0 | G85: =损益!I32 -> 0 | H85: =损益!J32 -> 0 | I85: =损益!K32 -> 0 | J85: =损益!L32 -> 0 | K85: =损益!M32 -> 0 | L85: =损益!N32 -> 0 | ... X85: =损益!Z32 -> 0 | Y85: =SUM(E85:X85) -> 0
B86: 1.2 | C86: 资产处置收益分配 | F86: =F87+F88+F89+F90 -> 0 | G86: =G87+G88+G89+G90 -> 0 | H86: =H87+H88+H89+H90 -> 0 | I86: =I87+I88+I89+I90 -> 0 | J86: =J87+J88+J89+J90 -> 0 | K86: =K87+K88+K89+K90 -> 0 | L86: =L87+L88+L89+L90 -> 0 | M86: =M87+M88+M89+M90 -> 0 | ... X86: =X87+X88+X89+X90 -> 1958.3271
B87: 1.2.1 | C87: 回收固定资产和无形资产余值 | X87: =X9 -> 1958.3271
B88: 1.2.2 | C88: 回收累计盈余资金（含法定公积金） | X88: =财务计划!X34 -> 0
B89: 1.2.3 | C89: 回收自有流动资金
B90: 1.2.4 | C90: 回收法定公积金
B91: 2 | C91: 现金流出 | D91: =D92+D93 -> 8626.0247 | E91: =E92+E93 -> 0
B92: 2.1 | C92: 建设投资资本金 | D92: =D50 -> 8626.0247 | E92: 0
B93: 2.2 | C93: 自有流动资金 | E93: =投资计划!G13 -> 0
B94: 3 | C94: 净现金流量 | D94: =D84-D91 -> -8626.0247 | E94: =E84-E91 -> 0 | F94: =F84-F91 -> 0 | G94: =G84-G91 -> 0 | H94: =H84-H91 -> 0 | I94: =I84-I91 -> 0 | J94: =J84-J91 -> 0 | K94: =K84-K91 -> 0 | ... X94: =X84-X91 -> 1958.3271
B95: 4 | C95: 累计净现金流 | D95: =D94 -> -8626.0247 | E95: =E94+D95 -> -8626.0247 | F95: =F94+E95 -> -8626.0247 | G95: =G94+F95 -> -8626.0247 | H95: =H94+G95 -> -8626.0247 | I95: =I94+H95 -> -8626.0247 | J95: =J94+I95 -> -8626.0247 | K95: =K94+J95 -> -8626.0247 | L95: =L94+K95 -> -8626.0247 | ... X95: =X94+W95 -> -6667.6976
C97: 计算指标：投资方财务内部收益率(%)： | H97: =IRR(D94:X94) -> -0.071453352
C98: 投资方财务净现值(万元) | F98: ic= | G98: 0.08 | H98: =NPV(G98,D94:X94) -> -7598.027

Sheet 资产负债
A1: 资产负债表
A3: 序号 | B3: 项目 | C3: 建设期 | D3: 运 营 期
C4: =成本!D4 -> 1 | D4: 1 | E4: 2 | F4: 3 | G4: 4 | H4: 5 | I4: 6 | J4: 7 | K4: 8 | L4: 9 | M4: 10 | N4: 11 | O4: 12 | P4: 13 | Q4: 14 | R4: 15 | S4: 16 | T4: 17 | U4: 18 | V4: 19 | W4: 20
A5: 1 | B5: 资产 | C5: =C6+C10+C11+C12 -> 43130.124 | D5: =D6+D10+D11+D12+D9 -> 40522.712 | E5: =E6+E10+E11+E12+E9 -> 37758.06 | F5: =F6+F10+F11+F12+F9 -> 35042.028 | G5: =G6+G10+G11+G12+G9 -> 32325.996 | H5: =H6+H10+H11+H12+H9 -> 29609.964 | I5: =I6+I10+I11+I12+I9 -> 26893.932 | J5: =J6+J10+J11+J12+J9 -> 24177.9 | K5: =K6+K10+K11+K12+K9 -> 21461.868 | ... W5: =W6+W10+W11+W12+W9 -> 2018.3271
A6: 1.1 | B6: 流动资产总值 | D6: =SUM(D7:D8) -> 60 | E6: =SUM(E7:E8) -> 60 | F6: =SUM(F7:F8) -> 60 | G6: =SUM(G7:G8) -> 60 | H6: =SUM(H7:H8) -> 60 | I6: =SUM(I7:I8) -> 60 | J6: =SUM(J7:J8) -> 60 | K6: =SUM(K7:K8) -> 60 | ... W6: =SUM(W7:W8) -> 60
A7: 1.1.1 | B7: 流动资产 | D7: =投资计划!C8 -> 60 | E7: =D7 -> 60 | F7: =E7 -> 60 | G7: =F7 -> 60 | H7: =G7 -> 60 | I7: =H7 -> 60 | J7: =I7 -> 60 | K7: =J7 -> 60 | L7: =K7 -> 60 | ... W7: =V7 -> 60
A8: 1.1.2 | B8: 累计盈余资金 | D8: =财务计划!E34 -> 0 | E8: =财务计划!F34 -> 0 | F8: =财务计划!G34 -> 0 | G8: =财务计划!H34 -> 0 | H8: =财务计划!I34 -> 0 | I8: =财务计划!J34 -> 0 | J8: =财务计划!K34 -> 0 | K8: =财务计划!L34 -> 0 | ... W8: =财务计划!X34 -> 0
A9: 1.1.3 | B9: 应收账款 | D9: =SUM(财务计划!$E$10:'财务计划'!E10) -> 48.62 | E9: =SUM(财务计划!$E$10:'财务计划'!F10) -> 0 | F9: =SUM(财务计划!$E$10:'财务计划'!G10) -> 0 | G9: =SUM(财务计划!$E$10:'财务计划'!H10) -> 0 | H9: =SUM(财务计划!$E$10:'财务计划'!I10) -> 0 | I9: =SUM(财务计划!$E$10:'财务计划'!J10) -> 0 | J9: =SUM(财务计划!$E$10:'财务计划'!K10) -> 0 | K9: =SUM(财务计划!$E$10:'财务计划'!L10) -> 0 | ... W9: =SUM(财务计划!$E$10:'财务计划'!X10) -> 0
A10: 1.2 | B10: 在建工程 | C10: =投资计划!F5 -> 43130.124 | E10: 0 | F10: 0 | G10: 0 | H10: 0 | I10: 0 | J10: 0 | K10: 0 | L10: 0 | M10: 0 | N10: 0 | O10: 0 | P10: 0 | Q10: 0 | R10: 0 | S10: 0 | T10: 0 | U10: 0 | V10: 0 | W10: 0
A11: 1.3 | B11: 固定资产净值 | D11: =成本!E31 -> 36685.994 | E11: =成本!F31 -> 34205.447 | F11: =成本!G31 -> 31724.899 | G11: =成本!H31 -> 29244.351 | H11: =成本!I31 -> 26763.804 | I11: =成本!J31 -> 24283.256 | J11: =成本!K31 -> 21802.708 | K11: =成本!L31 -> 19322.161 | ... W11: =成本!X31 -> 1958.3271
A12: 1.4 | B12: 无形及其他资产净值 | C12: =成本!E52+成本!E57 -> 0 | D12: =成本!F52+成本!F57 -> 3728.0976 | E12: =成本!G52+成本!G57 -> 3492.6133 | F12: =成本!H52+成本!H57 -> 3257.129 | G12: =成本!I52+成本!I57 -> 3021.6447 | H12: =成本!J52+成本!J57 -> 2786.1604 | I12: =成本!K52+成本!K57 -> 2550.6761 | J12: =成本!L52+成本!L57 -> 2315.1918 | ... W12: =成本!Y52+成本!Y57 -> 0
A13: 2 | B13: 负债及所有者权益 | C13: =C17+C18 -> 43118.124 | D13: =D17+D18 -> 40510.712 | E13: =E17+E18 -> 37746.06 | F13: =F17+F18 -> 35030.028 | G13: =G17+G18 -> 32313.996 | H13: =H17+H18 -> 29597.964 | I13: =I17+I18 -> 26881.932 | J13: =J17+J18 -> 24165.9 | ... W13: =W17+W18 -> 2030.9202
A14: 2.1 | B14: 流动负债总值 | D14: =投资计划!$G$18 -> 60 | E14: =投资计划!$G$18 -> 60 | F14: =投资计划!$G$18 -> 60 | G14: =投资计划!$G$18 -> 60 | H14: =投资计划!$G$18 -> 60 | I14: =投资计划!$G$18 -> 60 | J14: =投资计划!$G$18 -> 60 | K14: =投资计划!$G$18 -> 60 | ... W14: =投资计划!$G$18 -> 60
A15: 2.2 | B15: 长期借款 | C15: =还贷!D6 -> 34492.099 | D15: =还贷!F6 -> 32880.44 | E15: =还贷!G6 -> 31189.809 | F15: =还贷!H6 -> 29416.337 | G15: =还贷!I6 -> 27555.965 | H15: =还贷!J6 -> 25604.435 | I15: =还贷!K6 -> 23557.281 | J15: =还贷!L6 -> 21409.815 | K15: =还贷!M6 -> 19157.124 | ... W15: =还贷!Y6 -> 0
A16: 2.3 | B16: 短期借款 | C16: =财务计划!D22 -> 0 | D16: =财务计划!E22 -> 1700.1483 | E16: =财务计划!F22 -> 3370.8117 | F16: =财务计划!G22 -> 5156.5676 | G16: =财务计划!H22 -> 7013.8026 | H16: =财务计划!I22 -> 8945.6258 | I16: =财务计划!J22 -> 11268.614 | J16: =财务计划!K22 -> 13686.452 | ... W16: =财务计划!X22 -> 41907.578
B17: 负债小计 | C17: =C14+C15+C16 -> 34492.099 | D17: =D14+D15+D16 -> 34640.588 | E17: =E14+E15+E16 -> 34620.621 | F17: =F14+F15+F16 -> 34632.905 | G17: =G14+G15+G16 -> 34629.768 | H17: =H14+H15+H16 -> 34610.061 | I17: =I14+I15+I16 -> 34885.895 | J17: =J14+J15+J16 -> 35156.267 | ... W17: =W14+W15+W16 -> 41967.578
A18: 2.4 | B18: 所有者权益 | C18: =SUM(C19:C21) -> 8626.0247 | D18: =SUM(D19:D21) -> 5870.1239 | E18: =SUM(E19:E21) -> 3125.4392 | F18: =SUM(F19:F21) -> 397.12301 | G18: =SUM(G19:G21) -> -2315.7721 | H18: =SUM(H19:H21) -> -5012.0974 | I18: =SUM(I19:I21) -> -8003.9629 | J18: =SUM(J19:J21) -> -10990.367 | ... W18: =SUM(W19:W21) -> -39936.657
A19: 2.4.1 | B19: 资本金 | C19: =投资计划!F12 -> 8626.0247 | D19: =C19+投资计划!G13 -> 8626.0247 | E19: =现金流量!F50+D19 -> 8626.0247 | F19: =现金流量!G50+E19 -> 8626.0247 | G19: =现金流量!H50+F19 -> 8626.0247 | H19: =现金流量!I50+G19 -> 8626.0247 | I19: =现金流量!J50+H19 -> 8626.0247 | J19: =现金流量!K50+I19 -> 8626.0247 | K19: =现金流量!L50+J19 -> 8626.0247 | L19: =现金流量!M50+K19 -> 8626.0247 | ... W19: =现金流量!X50+V19 -> 8626.0247
A20: 2.4.2 | B20: 累计三金 | D20: =损益!G27+损益!G28 -> 0 | E20: =损益!H27+损益!H28+D20 -> 0 | F20: =损益!I27+损益!I28+E20 -> 0 | G20: =损益!J27+损益!J28+F20 -> 0 | H20: =损益!K27+损益!K28+G20 -> 0 | I20: =损益!L27+损益!L28+H20 -> 0 | J20: =损益!M27+损益!M28+I20 -> 0 | K20: =损益!N27+损益!N28+J20 -> 0 | L20: =损益!O27+损益!O28+K20 -> 0 | ... W20: =损益!Z27+损益!Z28+V20 -> 0
A21: 2.4.3 | B21: 累计未分配利润 | D21: =损益!G33 -> -2755.9009 | E21: =损益!H33+D21 -> -5500.5855 | F21: =损益!I33+E21 -> -8228.9017 | G21: =损益!J33+F21 -> -10941.797 | H21: =损益!K33+G21 -> -13638.122 | I21: =损益!L33+H21 -> -16629.988 | J21: =损益!M33+I21 -> -19616.391 | K21: =损益!N33+J21 -> -22596.544 | L21: =损益!O33+K21 -> -25569.594 | ... W21: =损益!Z33+V21 -> -48562.682
B23: 资产负债率(%) | D23: =D17/D5 -> 0.85484377 | E23: =E17/E5 -> 0.91690677 | F23: =F17/F5 -> 0.98832479 | G23: =G17/G5 -> 1.0712669 | H23: =H17/H5 -> 1.1688654 | I23: =I17/I5 -> 1.297166 | J23: =J17/J5 -> 1.4540662 | K23: =K17/K5 -> 1.6503869 | ... W23: =W17/W5 -> 20.793249
C25: =C5-C13 -> 12 | D25: =D5-D13 -> 12 | E25: =E5-E13 -> 12 | F25: =F5-F13 -> 12 | G25: =G5-G13 -> 12 | H25: =H5-H13 -> 12 | I25: =I5-I13 -> 12 | J25: =J5-J13 -> 12 | ... W25: =W5-W13 -> -12.593117
C26: =C6-C14 -> 0 | D26: =D25-C25 -> 7.2759576e-12 | E26: =E25-D25 -> 0 | F26: =F25-E25 -> 0 | G26: =G25-F25 -> -3.6379788e-12 | H26: =H25-G25 -> -3.6379788e-12 | I26: =I25-H25 -> 0 | J26: =J25-I25 -> -3.6379788e-12 | K26: =K25-J25 -> 3.6379788e-12 | ... W26: =W25-V25 -> -24.593117
D28: =MAX(D23:W23) -> 20.793249

Sheet 还贷
B1: 借款还本付息计划表
B3: 序号 | C3: 项目 | E3: 建设期 | H3: 运 营 期 | Y3: 合计
D4: =成本!D4 -> 1 | E4: =成本!E4 -> 1 | F4: =成本!F4 -> 2 | G4: =成本!G4 -> 3 | H4: =成本!H4 -> 4 | I4: =成本!I4 -> 5 | J4: =成本!J4 -> 6 | K4: =成本!K4 -> 7 | ... X4: =成本!X4 -> 20
B5: 1 | C5: 长期借款
B6: 1.1 | C6: 年初借款余额 | D6: =D8+D7 -> 34492.099 | E6: =E8+E7 -> 34492.099 | F6: =F7+F8 -> 32880.44 | G6: =G7+G8 -> 31189.809 | H6: =H7+H8 -> 29416.337 | I6: =I7+I8 -> 27555.965 | J6: =J7+J8 -> 25604.435 | K6: =K7+K8 -> 23557.281 | L6: =L7+L8 -> 21409.815 | M6: =M7+M8 -> 19157.124 | ... X6: =X7+X8 -> -24.593117
B7: 1.1.1 | C7: 本金 | D7: =投资计划!F16 -> 33801.975 | E7: =SUM(D6:D6) -> 34492.099 | F7: =E6-E10 -> 32880.44 | G7: =F6-F10 -> 31189.809 | H7: =G6-G10 -> 29416.337 | I7: =H6-H10 -> 27555.965 | J7: =I6-I10 -> 25604.435 | K7: =J6-J10 -> 23557.281 | L7: =K6-K10 -> 21409.815 | M7: =L6-L10 -> 19157.124 | ... X7: =W6-W10 -> -24.593117
B8: 1.1.2 | C8: 建设期利息 | D8: =投资计划!F7 -> 690.12366 | E8: =投资计划!G7 -> 0
B9: 1.2 | C9: 当期还本付息 | E9: =$E$35 -> 3301.7723 | F9: =$E$35 -> 3301.7723 | G9: =$E$35 -> 3301.7723 | H9: =$E$35 -> 3301.7723 | I9: =$E$35 -> 3301.7723 | J9: =$E$35 -> 3301.7723 | K9: =$E$35 -> 3301.7723 | L9: =$E$35 -> 3301.7723 | ... S9: =$E$35 -> 3301.7723 | T9: =T10+T11 -> -1.2050627 | U9: =U10+U11 -> -1.2050627 | V9: =V10+V11 -> -1.2050627 | W9: =W10+W11 -> -1.2050627 | X9: =X10+X11 -> -1.2050627
C10: 其中：还本 | E10: =E36 -> 1611.6594 | F10: =F36 -> 1690.6307 | G10: =G36 -> 1773.4716 | H10: =H36 -> 1860.3717 | I10: =I36 -> 1951.53 | J10: =J36 -> 2047.1549 | K10: =K36 -> 2147.4655 | L10: =L36 -> 2252.6913 | ... S10: =S36 -> 3148.6914 | T10: =T37 -> 0 | U10: =U37 -> 0 | V10: =V37 -> 0 | W10: =W37 -> 0 | X10: =X37 -> 0
C11: 付息 | E11: =E6*参数表!$C$26 -> 1690.1128 | F11: =F6*参数表!$C$26 -> 1611.1415 | G11: =G6*参数表!$C$26 -> 1528.3006 | H11: =H6*参数表!$C$26 -> 1441.4005 | I11: =I6*参数表!$C$26 -> 1350.2423 | J11: =J6*参数表!$C$26 -> 1254.6173 | K11: =K6*参数表!$C$26 -> 1154.3067 | L11: =L6*参数表!$C$26 -> 1049.0809 | ... X11: =X6*参数表!$C$26 -> -1.2050627
B12: 2 | C12: 流动资金借款
B13: 2.1 | C13: 年初借款余额 | E13: =投资计划!G18 -> 60 | F13: =E13 -> 60 | G13: =F13 -> 60 | H13: =G13 -> 60 | I13: =H13 -> 60 | J13: =I13 -> 60 | K13: =J13 -> 60 | L13: =K13 -> 60 | M13: =L13 -> 60 | ... X13: =W13 -> 60
B14: 2.2 | C14: 当期还本付息
C15: 其中：还本
C16: 付息 | E16: =E13*流动资金贷款利率 -> 2.61 | F16: =F13*流动资金贷款利率 -> 2.61 | G16: =G13*流动资金贷款利率 -> 2.61 | H16: =H13*流动资金贷款利率 -> 2.61 | I16: =I13*流动资金贷款利率 -> 2.61 | J16: =J13*流动资金贷款利率 -> 2.61 | K16: =K13*流动资金贷款利率 -> 2.61 | L16: =L13*流动资金贷款利率 -> 2.61 | ... X16: =X13*流动资金贷款利率 -> 2.61
B17: 3 | C17: 短期借款
B18: 3.1 | C18: 年初借款余额 | D18: =财务计划!#REF! -> #REF! | E18: =财务计划!D22 -> 0 | F18: =财务计划!E22 -> 1700.1483 | G18: =财务计划!F22 -> 3370.8117 | H18: =财务计划!G22 -> 5156.5676 | I18: =财务计划!H22 -> 7013.8026 | J18: =财务计划!I22 -> 8945.6258 | K18: =财务计划!J22 -> 11268.614 | L18: =财务计划!K22 -> 13686.452 | ... U18: =财务计划!T22 -> 38668.438 | V18: =财务计划!V22 -> 40160.391 | W18: =财务计划!W22 -> 41015.388 | X18: =财务计划!X22 -> 41907.578
B19: 3.2 | C19: 当期还本付息
C20: 其中：还本 | D20: =财务计划!D28 -> 0 | E20: =财务计划!E28 -> 0 | F20: =财务计划!F28 -> 1700.1483 | G20: =财务计划!G28 -> 3370.8117 | H20: =财务计划!H28 -> 5156.5676 | I20: =财务计划!I28 -> 7013.8026 | J20: =财务计划!J28 -> 8945.6258 | K20: =财务计划!K28 -> 11268.614 | ... X20: =财务计划!X28 -> 41015.388
C21: 付息 | D21: =D20*短期贷款利息 -> 0 | E21: =E20*短期贷款利息 -> 0 | F21: =F20*短期贷款利息 -> 73.956452 | G21: =G20*短期贷款利息 -> 146.63031 | H21: =H20*短期贷款利息 -> 224.31069 | I21: =I20*短期贷款利息 -> 305.10041 | J21: =J20*短期贷款利息 -> 389.13472 | K21: =K20*短期贷款利息 -> 490.18473 | ... X21: =X20*短期贷款利息 -> 1784.1694
B22: 4 | C22: 借款合计
B23: 4.1 | C23: 年初借款余额 | E23: =E6+E13+E18 -> 34552.099 | F23: =F6+F13+F18 -> 34640.588 | G23: =G6+G13+G18 -> 34620.621 | H23: =H6+H13+H18 -> 34632.905 | I23: =I6+I13+I18 -> 34629.768 | J23: =J6+J13+J18 -> 34610.061 | K23: =K6+K13+K18 -> 34885.895 | L23: =L6+L13+L18 -> 35156.267 | ... X23: =X6+X13+X18 -> 41942.984
B24: 4.2 | C24: 当期还本付息
C25: 其中：还本 | E25: =E10+E15+E20 -> 1611.6594 | F25: =F10+F15+F20 -> 3390.7791 | G25: =G10+G15+G20 -> 5144.2834 | H25: =H10+H15+H20 -> 7016.9394 | I25: =I10+I15+I20 -> 8965.3325 | J25: =J10+J15+J20 -> 10992.781 | K25: =K10+K15+K20 -> 13416.08 | L25: =L10+L15+L20 -> 15939.143 | ... X25: =X10+X15+X20 -> 41015.388
C26: 付息 | E26: =E11+E16+E21 -> 1692.7228 | F26: =F11+F16+F21 -> 1687.708 | G26: =G11+G16+G21 -> 1677.5409 | H26: =H11+H16+H21 -> 1668.3212 | I26: =I11+I16+I21 -> 1657.9527 | J26: =J11+J16+J21 -> 1646.3621 | K26: =K11+K16+K21 -> 1647.1015 | L26: =L11+L16+L21 -> 1647.0516 | ... X26: =X11+X16+X21 -> 1785.5743
C27: 息税前利润（EBIT） | E27: =成本!E13+损益!G15 -> -1063.178 | F27: =成本!F13+损益!H15 -> -1056.9766 | G27: =成本!G13+损益!I15 -> -1050.7753 | H27: =成本!H13+损益!J15 -> -1044.5739 | I27: =成本!I13+损益!K15 -> -1038.3725 | J27: =成本!J13+损益!L15 -> -1345.5035 | K27: =成本!K13+损益!M15 -> -1339.3021 | L27: =成本!L13+损益!N15 -> -1333.1008 | ... X27: =成本!X13+损益!Z15 -> 893.38477
C28: 息税前利润(含增值税） | E28: =E27+成本!F51 -> -827.69372 | F28: =F27+成本!G51 -> -821.49235 | G28: =G27+成本!H51 -> -815.29098 | H28: =H27+成本!I51 -> -809.08961 | I28: =I27+成本!J51 -> -802.88824 | J28: =J27+成本!K51 -> -1110.0192 | K28: =K27+成本!L51 -> -1103.8178 | L28: =L27+成本!M51 -> -1097.6165 | ... X28: =X27+成本!Y51 -> 893.38477
C29: 利息备付率（ICR） | E29: =E28/成本!E13 -> -0.48897179 | F29: =F28/成本!F13 -> -0.48675029 | G29: =G28/成本!G13 -> -0.48600362 | H29: =H28/成本!H13 -> -0.48497232 | I29: =I28/成本!I13 -> -0.48426486 | J29: =J28/成本!J13 -> -0.67422545 | K29: =K28/成本!K13 -> -0.67015776 | L29: =L28/成本!L13 -> -0.66641293 | ... X29: =X28/成本!X13 -> 0.50033469 | Y29: =AVERAGE(F29:X29) -> -0.33395728
C30: ebitda | E30: =E27+成本!E6 -> 1417.3696 | F30: =F27+成本!F6 -> 1423.571 | G30: =G27+成本!G6 -> 1429.7724 | H30: =H27+成本!H6 -> 1435.9737 | I30: =I27+成本!I6 -> 1442.1751 | J30: =J27+成本!J6 -> 1135.0441 | K30: =K27+成本!K6 -> 1141.2455 | L30: =L27+成本!L6 -> 1147.4469 | ... X30: =X27+成本!X6 -> 893.38477
C31: ebitda+-tax | E31: =E30+成本!F51-损益!G21 -> 1652.8539 | F31: =F30+成本!G51-损益!H21 -> 1659.0553 | G31: =G30+成本!H51-损益!I21 -> 1665.2567 | H31: =H30+成本!I51-损益!J21 -> 1671.458 | I31: =I30+成本!J51-损益!K21 -> 1677.6594 | J31: =J30+成本!K51-损益!L21 -> 1370.5284 | K31: =K30+成本!L51-损益!M21 -> 1376.7298 | L31: =L30+成本!M51-损益!N21 -> 1382.9312 | ... X31: =X30+成本!Y51-损益!Z21 -> 893.38477
C32: 偿债备付率（dscr） | E32: =E31/(E11+E10) -> 0.50059598 | F32: =F31/(F11+F10) -> 0.50247418 | G32: =G31/(G11+G10) -> 0.50435237 | H32: =H31/(H11+H10) -> 0.50623057 | I32: =I31/(I11+I10) -> 0.50810876 | J32: =J31/(J11+J10) -> 0.41508873 | K32: =K31/(K11+K10) -> 0.41696692 | L32: =L31/(L11+L10) -> 0.41884511 | ... S32: =S31/(S11+S10) -> 0.37268108 | Y32: =AVERAGE(F32:X32) -> 0.42571535
E35: =-PMT(参数表!C26,参数表!C27,投资计划!C15) -> 3301.7723
E36: =$E$35-还贷!E11 -> 1611.6594 | F36: =$E$35-还贷!F11 -> 1690.6307 | G36: =$E$35-还贷!G11 -> 1773.4716 | H36: =$E$35-还贷!H11 -> 1860.3717 | I36: =$E$35-还贷!I11 -> 1951.53 | J36: =$E$35-还贷!J11 -> 2047.1549 | K36: =$E$35-还贷!K11 -> 2147.4655 | L36: =$E$35-还贷!L11 -> 2252.6913 | ... S36: =$E$35-还贷!S11 -> 3148.6914

Sheet 财务计划
A1: 财务计划现金流量表
A2: 附表7 | T2: 单位：万元
A3: 序号 | B3: 项 目 | C3: 合计 | E3: 运 营 期
D4: =成本!D4 -> 1 | E4: =成本!E4 -> 1 | F4: =成本!F4 -> 2 | G4: =成本!G4 -> 3 | H4: =成本!H4 -> 4 | I4: =成本!I4 -> 5 | J4: =成本!J4 -> 6 | K4: =成本!K4 -> 7 | ... X4: =成本!X4 -> 20
A5: 1 | B5: 经营活动净现金流量 | D5: =D6-D11 -> 0 | E5: =E6-E11 -> 1604.2339 | F5: =F6-F11 -> 1707.6753 | G5: =G6-G11 -> 1665.2567 | H5: =H6-H11 -> 1671.458 | I5: =I6-I11 -> 1677.6594 | J5: =J6-J11 -> 1370.5284 | K5: =K6-K11 -> 1376.7298 | ... X5: =X6-X11 -> 893.38477
A6: 1.1 | B6: 现金流入 | D6: =D7+D8+D9 -> 0 | E6: =E7+E8+E9-E10 -> 1998.282 | F6: =F7+F8+F9-F10 -> 2095.522 | G6: =G7+G8+G9-G10 -> 2046.902 | H6: =H7+H8+H9-H10 -> 2046.902 | I6: =I7+I8+I9-I10 -> 2046.902 | J6: =J7+J8+J9-J10 -> 2046.902 | K6: =K7+K8+K9-K10 -> 2046.902 | L6: =L7+L8+L9-L10 -> 2046.902 | ... X6: =X7+X8+X9-X10 -> 2164.6442
A7: 1.1.1 | B7: 销售收入 | E7: =损益!G8+损益!G12 -> 1811.4177 | F7: =损益!H8+损益!H12 -> 1811.4177 | G7: =损益!I8+损益!I12 -> 1811.4177 | H7: =损益!J8+损益!J12 -> 1811.4177 | I7: =损益!K8+损益!K12 -> 1811.4177 | J7: =损益!L8+损益!L12 -> 1811.4177 | K7: =损益!M8+损益!M12 -> 1811.4177 | L7: =损益!N8+损益!N12 -> 1811.4177 | ... X7: =损益!Z8+损益!Z12 -> 1929.1598
A8: 1.1.2 | B8: 增值税 | E8: =现金流量!E45 -> 235.4843 | F8: =现金流量!F45 -> 235.4843 | G8: =现金流量!G45 -> 235.4843 | H8: =现金流量!H45 -> 235.4843 | I8: =现金流量!I45 -> 235.4843 | J8: =现金流量!J45 -> 235.4843 | K8: =现金流量!K45 -> 235.4843 | L8: =现金流量!L45 -> 235.4843 | ... X8: =现金流量!X45 -> 235.4843 | Y8: =SUM(D8:X8) -> 4709.686
A9: 1.1.3 | B9: 回收流动资金
A10: 1.1.4 | B10: 补贴未到位资金 | E10: =参数表!$C$8*损益!G5*(1-参数表!D10) -> 48.62 | F10: =参数表!$C$8*损益!H5*(1-参数表!E10) -> -48.62 | G10: =参数表!$C$8*损益!I5*(1-参数表!F10) -> 0 | H10: =参数表!$C$8*损益!J5*(1-参数表!G10) -> 0 | I10: =参数表!$C$8*损益!K5*(1-参数表!H10) -> 0 | J10: =参数表!$C$8*损益!L5*(1-参数表!I10) -> 0 | K10: =参数表!$C$8*损益!M5*(1-参数表!J10) -> 0 | L10: =参数表!$C$8*损益!N5*(1-参数表!K10) -> 0 | ... X10: =参数表!$C$8*损益!Z5*(1-参数表!W10) -> 0
A11: 1.2 | B11: 现金流出 | D11: =D12+D13+D14+D15+D16 -> 0 | E11: =E12+E13+E14+E15+E16 -> 394.04807 | F11: =F12+F13+F14+F15+F16 -> 387.8467 | G11: =G12+G13+G14+G15+G16 -> 381.64533 | H11: =H12+H13+H14+H15+H16 -> 375.44396 | I11: =I12+I13+I14+I15+I16 -> 369.24259 | J11: =J12+J13+J14+J15+J16 -> 676.37356 | K11: =K12+K13+K14+K15+K16 -> 670.17219 | ... X11: =X12+X13+X14+X15+X16 -> 1271.2594 | Y11: =Y12+Y13+Y15+Y16 -> 15253.912
A12: 1.2.1 | B12: 经营成本 | E12: =现金流量!E53 -> 394.04807 | F12: =现金流量!F53 -> 387.8467 | G12: =现金流量!G53 -> 381.64533 | H12: =现金流量!H53 -> 375.44396 | I12: =现金流量!I53 -> 369.24259 | J12: =现金流量!J53 -> 676.37356 | K12: =现金流量!K53 -> 670.17219 | L12: =现金流量!L53 -> 663.97082 | ... X12: =现金流量!X53 -> 1012.2267 | Y12: =SUM(D12:X12) -> 14433.197
A13: 1.2.2 | B13: 城建税及教育附加 | E13: =现金流量!E56 -> 0 | F13: =现金流量!F56 -> 0 | G13: =现金流量!G56 -> 0 | H13: =现金流量!H56 -> 0 | I13: =现金流量!I56 -> 0 | J13: =现金流量!J56 -> 0 | K13: =现金流量!K56 -> 0 | L13: =现金流量!L56 -> 0 | ... X13: =现金流量!X56 -> 23.54843 | Y13: =SUM(D13:X13) -> 74.610416
A14: 1.2.3 | B14: 大额租金 | D14: =参数表!C58 -> 0 | E14: =参数表!D58 -> 0 | F14: =参数表!E58 -> 0 | G14: =参数表!F58 -> 0 | H14: =参数表!G58 -> 0 | I14: =参数表!H58 -> 0 | J14: =参数表!I58 -> 0 | K14: =参数表!J58 -> 0 | ... X14: =参数表!W58 -> 0 | Y14: =SUM(D14:X14) -> 0
A15: 1.2.4 | B15: 所得税 | E15: =现金流量!E57 -> 0 | F15: =现金流量!F57 -> 0 | G15: =现金流量!G57 -> 0 | H15: =现金流量!H57 -> 0 | I15: =现金流量!I57 -> 0 | J15: =现金流量!J57 -> 0 | K15: =现金流量!K57 -> 0 | L15: =现金流量!L57 -> 0 | ... X15: =现金流量!X57 -> 0 | Y15: =SUM(D15:X15) -> 0
A16: 1.2.5 | B16: 应缴增值税 | E16: =现金流量!E55 -> 0 | F16: =现金流量!F55 -> 0 | G16: =现金流量!G55 -> 0 | H16: =现金流量!H55 -> 0 | I16: =现金流量!I55 -> 0 | J16: =现金流量!J55 -> 0 | K16: =现金流量!K55 -> 0 | L16: =现金流量!L55 -> 0 | ... X16: =现金流量!X55 -> 235.4843 | Y16: =SUM(D16:X16) -> 746.10416
A17: 2 | B17: 投资、筹资活动净现金流量 | D17: =D18-D24 -> 0 | E17: =E18-E24 -> -1604.2339 | F17: =F18-F24 -> -7.52697 | G17: =G18-G24 -> 1705.5551 | H17: =H18-H24 -> 3485.1096 | I17: =I18-I24 -> 5336.1432 | J17: =J18-J24 -> 7575.0974 | K17: =K18-K24 -> 9891.8846 | ... Y17: =Y18-Y24 -> -111142.88
A18: 2.1 | B18: 现金流入 | D18: =D19+D20+D21+D22+D23 -> 43118.124 | E18: =E19+E20+E21+E22+E23 -> 1760.1483 | F18: =F19+F20+F21+F22+F23 -> 3370.8117 | G18: =G19+G20+G21+G22+G23 -> 5156.5676 | H18: =H19+H20+H21+H22+H23 -> 7013.8026 | I18: =I19+I20+I21+I22+I23 -> 8945.6258 | J18: =J19+J20+J21+J22+J23 -> 11268.614 | K18: =K19+K20+K21+K22+K23 -> 13686.452 | ... Y18: =Y19+Y20+Y21+Y22+Y23 -> 0
A19: 2.1.1 | B19: 项目资本金投入 | D19: =投资计划!F11 -> 8626.0247 | E19: =投资计划!G11 -> 0
A20: 2.1.2 | B20: 建设投资借款 | D20: =还贷!D6 -> 34492.099
A21: 2.1.3 | B21: 流动资金借款 | E21: =投资计划!G18 -> 60
A22: 2.1.4 | B22: 短期借款 | C22: =MAX(F22:X22) -> 41907.578 | D22: =IF(D5-D24-D28<0,IF(-D24-D28+D19+D20+D21+D5>=0,0,-D5-D19-D20-D21+D24+D28),0) -> 0 | E22: =IF(E5-E24-E28<0,IF(D34-E24-E28+E19+E20+E21+E5>=0,0,-D34-E5-E19-E20-E21+E24+E28),0) -> 1700.1483 | F22: =IF(F5-F24-F28<0,IF(E34-F24-F28+F19+F20+F21+F5>=0,0,-E34-F5-F19-F20-F21+F24+F28),0) -> 3370.8117 | G22: =IF(G5-G24-G28<0,IF(F34-G24-G28+G19+G20+G21+G5>=0,0,-F34-G5-G19-G20-G21+G24+G28),0) -> 5156.5676 | H22: =IF(H5-H24-H28<0,IF(G34-H24-H28+H19+H20+H21+H5>=0,0,-G34-H5-H19-H20-H21+H24+H28),0) -> 7013.8026 | I22: =IF(I5-I24-I28<0,IF(H34-I24-I28+I19+I20+I21+I5>=0,0,-H34-I5-I19-I20-I21+I24+I28),0) -> 8945.6258 | J22: =IF(J5-J24-J28<0,IF(I34-J24-J28+J19+J20+J21+J5>=0,0,-I34-J5-J19-J20-J21+J24+J28),0) -> 11268.614 | K22: =IF(K5-K24-K28<0,IF(J34-K24-K28+K19+K20+K21+K5>=0,0,-J34-K5-K19-K20-K21+K24+K28),0) -> 13686.452 | L22: =IF(L5-L24-L28<0,IF(K34-L24-L28+L19+L20+L21+L5>=0,0,-K34-L5-L19-L20-L21+L24+L28),0) -> 16203.263 | ... X22: =IF(X5-X24-X28<0,IF(W34-X24-X28+X19+X20+X21+X5>=0,0,-W34-X5-X19-X20-X21+X24+X28),0) -> 41907.578
A23: 2.1.5 | B23: 回收固定资产余值
A24: 2.2 | B24: 现金流出 | D24: =D25+D26+D27+D30+D31+D32 -> 43118.124 | E24: =E25+E26+E27+E30+E31+E32 -> 3364.3823 | F24: =F25+F26+F27+F30+F31+F32 -> 3378.3387 | G24: =G25+G26+G27+G30+G31+G32 -> 3451.0126 | H24: =H25+H26+H27+H30+H31+H32 -> 3528.693 | I24: =I25+I26+I27+I30+I31+I32 -> 3609.4827 | J24: =J25+J26+J27+J30+J31+J32 -> 3693.517 | K24: =K25+K26+K27+K30+K31+K32 -> 3794.567 | ... X24: =X25+X26+X27+X30+X31+X32 -> 1785.5743 | Y24: =SUM(D24:X24) -> 111142.88
A25: 2.2.1 | B25: 建设投资 | D25: =投资计划!F10 -> 43118.124 | E25: =投资计划!G15 -> 0
A26: 2.2.2 | B26: 流动资金 | E26: =投资计划!G8 -> 60
A27: 2.2.3 | B27: 长期借款本金偿还 | E27: =还贷!E10 -> 1611.6594 | F27: =还贷!F10 -> 1690.6307 | G27: =还贷!G10 -> 1773.4716 | H27: =还贷!H10 -> 1860.3717 | I27: =还贷!I10 -> 1951.53 | J27: =还贷!J10 -> 2047.1549 | K27: =还贷!K10 -> 2147.4655 | L27: =还贷!L10 -> 2252.6913 | ... S27: =还贷!S10 -> 3148.6914 | Y27: =SUM(D27:X27) -> 34516.692
B28: 短期借款本金偿还 | E28: =D22 -> 0 | F28: =E22 -> 1700.1483 | G28: =F22 -> 3370.8117 | H28: =G22 -> 5156.5676 | I28: =H22 -> 7013.8026 | J28: =I22 -> 8945.6258 | K28: =J22 -> 11268.614 | L28: =K22 -> 13686.452 | ... X28: =W22 -> 41015.388
B29: 流动负债本金偿还
A30: 2.2.4 | B30: 各种利息支出 | E30: =成本!E13 -> 1692.7228 | F30: =成本!F13 -> 1687.708 | G30: =成本!G13 -> 1677.5409 | H30: =成本!H13 -> 1668.3212 | I30: =成本!I13 -> 1657.9527 | J30: =成本!J13 -> 1646.3621 | K30: =成本!K13 -> 1647.1015 | L30: =成本!L13 -> 1647.0516 | ... X30: =成本!X13 -> 1785.5743 | Y30: =SUM(D30:X30) -> 33448.066
A31: 2.2.5 | B31: 各投资方利润分配 | E31: =E41 -> 0 | F31: =F41 -> 0 | G31: =G41 -> 0 | H31: =H41 -> 0 | I31: =I41 -> 0 | J31: =J41 -> 0 | K31: =K41 -> 0 | L31: =L41 -> 0 | ... X31: =X41 -> 0 | Y31: =SUM(F31:X31) -> 0
A32: 2.2.6 | B32: 其他流出 | Y32: =SUM(F32:X32) -> 0
A33: 3 | B33: 净现金流量 | D33: =D5+D17-D28 -> 0 | E33: =E5+E17-E28 -> 0 | F33: =F5+F17-F28 -> 0 | G33: =G5+G17-G28 -> 0 | H33: =H5+H17-H28 -> 0 | I33: =I5+I17-I28 -> 0 | J33: =J5+J17-J28 -> 0 | K33: =K5+K17-K28 -> 0 | ... X33: =X5+X17-X28 -> 0 | Y33: =SUM(F33:X33) -> 0
A34: 4 | B34: 累计盈余资金 | D34: =D33 -> 0 | E34: =D34+E33 -> 0 | F34: =E34+F33 -> 0 | G34: =F34+G33 -> 0 | H34: =G34+H33 -> 0 | I34: =H34+I33 -> 0 | J34: =I34+J33 -> 0 | K34: =J34+K33 -> 0 | L34: =K34+L33 -> 0 | ... X34: =W34+X33 -> 0 | Y34: =SUM(F34:X34) -> 0
D36: =IF(+D28=0,0,IF(D28>0,0)) -> 0 | E36: =IF(D28+E28=0,0,IF(E28>0,0,#REF!+D28/#REF!)) -> 0 | F36: =IF(E28+F28=0,0,IF(F28>0,0,D4+E28/D28)) -> 0 | G36: =IF(F28+G28=0,0,IF(G28>0,0,E4+F28/E28)) -> 0 | H36: =IF(G28+H28=0,0,IF(H28>0,0,F4+G28/F28)) -> 0 | I36: =IF(H28+I28=0,0,IF(I28>0,0,G4+H28/G28)) -> 0 | J36: =IF(I28+J28=0,0,IF(J28>0,0,H4+I28/H28)) -> 0 | K36: =IF(J28+K28=0,0,IF(K28>0,0,I4+J28/I28)) -> 0 | L36: =IF(K28+L28=0,0,IF(L28>0,0,J4+K28/J28)) -> 0 | M36: =IF(L28+M28=0,0,IF(M28>0,0,K4+L28/K28)) -> 0 | ... X36: =IF(W28+X28=0,0,IF(X28>0,0,V4+W28/V28)) -> 0
B38: 不含利润分配的流出 | E38: =SUM(E25:E30)-E18 -> 1604.2339 | F38: =SUM(F25:F30) -> 5078.487 | G38: =SUM(G25:G30) -> 6821.8243 | H38: =SUM(H25:H30) -> 8685.2606 | I38: =SUM(I25:I30) -> 10623.285 | J38: =SUM(J25:J30) -> 12639.143 | K38: =SUM(K25:K30) -> 15063.181 | L38: =SUM(L25:L30) -> 17586.194 | M38: =SUM(M25:M30) -> 20212.487 | ... X38: =SUM(X25:X30) -> 42800.962
B39: 净现金流（不含利润分配） | E39: =E5-E38 -> 0 | F39: =F5-F38 -> -3370.8117 | G39: =G5-G38 -> -5156.5676 | H39: =H5-H38 -> -7013.8026 | I39: =I5-I38 -> -8945.6258 | J39: =J5-J38 -> -11268.614 | K39: =K5-K38 -> -13686.452 | L39: =L5-L38 -> -16203.263 | ... X39: =X5-X38 -> -41907.578
B40: 可分配利润 | E40: =损益!G29*参数表!$C$60 -> 0 | F40: =损益!H29*参数表!$C$60 -> 0 | G40: =损益!I29*参数表!$C$60 -> 0 | H40: =损益!J29*参数表!$C$60 -> 0 | I40: =损益!K29*参数表!$C$60 -> 0 | J40: =损益!L29*参数表!$C$60 -> 0 | K40: =损益!M29*参数表!$C$60 -> 0 | L40: =损益!N29*参数表!$C$60 -> 0 | ... X40: =损益!Z29*参数表!$C$60 -> 0
B41: 实际分配利润 | E41: =E40 -> 0 | F41: =F40 -> 0 | G41: =G40 -> 0 | H41: =H40 -> 0 | I41: =I40 -> 0 | J41: =J40 -> 0 | K41: =K40 -> 0 | L41: =L40 -> 0 | ... X41: =X40 -> 0
B42: 累计盈余资金 | E42: =E5+E17-E28 -> 0 | F42: =F5+F17-F28 -> 0 | G42: =G5+G17-G28 -> 0 | H42: =H5+H17-H28 -> 0 | I42: =I5+I17-I28 -> 0 | J42: =J5+J17-J28 -> 0 | K42: =K5+K17-K28 -> 0 | L42: =L5+L17-L28 -> 0 | ... X42: =X5+X17-X28 -> 0

Sheet 估值结果
A1: 基准内部收益率 | B1: =参数表!C61 -> 0.085
A3: 收益现值法
A4: 运营年 | B4: 1 | C4: 2 | D4: 3 | E4: 4 | F4: 5 | G4: 6 | H4: 7 | I4: 8 | J4: 9 | K4: 10 | L4: 11 | M4: 12 | N4: 13 | O4: 14 | P4: 15 | Q4: 16 | R4: 17 | S4: 18 | T4: 19 | U4: 20
A5: 净现金流量 | B5: =现金流量!E59 -> 0 | C5: =现金流量!F59 -> 0 | D5: =现金流量!G59 -> 0 | E5: =现金流量!H59 -> 0 | F5: =现金流量!I59 -> 0 | G5: =现金流量!J59 -> 0 | H5: =现金流量!K59 -> 0 | I5: =现金流量!L59 -> 0 | ... U5: =现金流量!X59 -> 1958.3271
A6: 终值 | B6: =B5*(1+参数表!$C$61)^(现金流量!$X$4-现金流量!E$4) -> 0 | C6: =C5*(1+参数表!$C$61)^(现金流量!$X$4-现金流量!F$4) -> 0 | D6: =D5*(1+参数表!$C$61)^(现金流量!$X$4-现金流量!G$4) -> 0 | E6: =E5*(1+参数表!$C$61)^(现金流量!$X$4-现金流量!H$4) -> 0 | F6: =F5*(1+参数表!$C$61)^(现金流量!$X$4-现金流量!I$4) -> 0 | G6: =G5*(1+参数表!$C$61)^(现金流量!$X$4-现金流量!J$4) -> 0 | H6: =H5*(1+参数表!$C$61)^(现金流量!$X$4-现金流量!K$4) -> 0 | I6: =I5*(1+参数表!$C$61)^(现金流量!$X$4-现金流量!L$4) -> 0 | ... U6: =U5*(1+参数表!$C$61)^(现金流量!$X$4-现金流量!X$4) -> 1958.3271
A7: 该年末卖出价格 | B7: =SUM(B6:$U6)/(1+参数表!$C$61)^(现金流量!$X4-现金流量!E4+1) -> 383.08087 | C7: =SUM(C6:$U6)/(1+参数表!$C$61)^(现金流量!$X4-现金流量!F4+1) -> 415.64275 | D7: =SUM(D6:$U6)/(1+参数表!$C$61)^(现金流量!$X4-现金流量!G4+1) -> 450.97238 | E7: =SUM(E6:$U6)/(1+参数表!$C$61)^(现金流量!$X4-现金流量!H4+1) -> 489.30503 | F7: =SUM(F6:$U6)/(1+参数表!$C$61)^(现金流量!$X4-现金流量!I4+1) -> 530.89596 | G7: =SUM(G6:$U6)/(1+参数表!$C$61)^(现金流量!$X4-现金流量!J4+1) -> 576.02212 | H7: =SUM(H6:$U6)/(1+参数表!$C$61)^(现金流量!$X4-现金流量!K4+1) -> 624.984 | I7: =SUM(I6:$U6)/(1+参数表!$C$61)^(现金流量!$X4-现金流量!L4+1) -> 678.10764 | ... U7: =SUM(U6:$U6)/(1+参数表!$C$61)^(现金流量!$X4-现金流量!X4+1) -> 1804.9098
A8: 100%股权卖出价格 | B8: =B7 -> 383.08087 | C8: =C7 -> 415.64275 | D8: =D7 -> 450.97238 | E8: =E7 -> 489.30503 | F8: =F7 -> 530.89596 | G8: =G7 -> 576.02212 | H8: =H7 -> 624.984 | I8: =I7 -> 678.10764 | ... U8: =U7 -> 1804.9098
A9: 所得税 | B9: =MAX((B8-B14)*参数表!$C$62,0) -> 0 | C9: =MAX((C8-C14)*参数表!$C$62,0) -> 0 | D9: =MAX((D8-D14)*参数表!$C$62,0) -> 0 | E9: =MAX((E8-E14)*参数表!$C$62,0) -> 0 | F9: =MAX((F8-F14)*参数表!$C$62,0) -> 0 | G9: =MAX((G8-G14)*参数表!$C$62,0) -> 0 | H9: =MAX((H8-H14)*参数表!$C$62,0) -> 0 | I9: =MAX((I8-I14)*参数表!$C$62,0) -> 0 | ... U9: =MAX((U8-U14)*参数表!$C$62,0) -> 0
A10: 印花税 | B10: =B16*0.05% -> 0.19154044 | C10: =C16*0.05% -> 0.20782137 | D10: =D16*0.05% -> 0.22548619 | E10: =E16*0.05% -> 0.24465252 | F10: =F16*0.05% -> 0.26544798 | G10: =G16*0.05% -> 0.28801106 | H10: =H16*0.05% -> 0.312492 | I10: =I16*0.05% -> 0.33905382 | ... U10: =U16*0.05% -> 0.90245488
A11: 税后收益 | B11: =B8-B9-B10 -> 382.88933 | C11: =C8-C9-C10 -> 415.43493 | D11: =D8-D9-D10 -> 450.74689 | E11: =E8-E9-E10 -> 489.06038 | F11: =F8-F9-F10 -> 530.63051 | G11: =G8-G9-G10 -> 575.73411 | H11: =H8-H9-H10 -> 624.6715 | I11: =I8-I9-I10 -> 677.76858 | ... U11: =U8-U9-U10 -> 1804.0073
A12: 溢价率 | B12: =(B7+B15)/B14-1 -> -0.9555901 | C12: =(C7+C15)/C14-1 -> -0.95181526 | D12: =(D7+D15)/D14-1 -> -0.94771956 | E12: =(E7+E15)/E14-1 -> -0.94327572 | F12: =(F7+F15)/F14-1 -> -0.93845416 | G12: =(G7+G15)/G14-1 -> -0.93322276 | H12: =(H7+H15)/H14-1 -> -0.9275467 | I12: =(I7+I15)/I14-1 -> -0.92138816 | ... U12: =(U7+U15)/U14-1 -> -0.79075996
A13: 备注：上述价格仅为未来现金流，不包括公司账面盈余资金。
A14: 资本金 | B14: =资产负债!D19 -> 8626.0247 | C14: =资产负债!E19 -> 8626.0247 | D14: =资产负债!F19 -> 8626.0247 | E14: =资产负债!G19 -> 8626.0247 | F14: =资产负债!H19 -> 8626.0247 | G14: =资产负债!I19 -> 8626.0247 | H14: =资产负债!J19 -> 8626.0247 | I14: =资产负债!K19 -> 8626.0247 | ... U14: =资产负债!W19 -> 8626.0247
A15: 累计未分配利润 | B15: =资产负债!D20 -> 0 | C15: =资产负债!E20 -> 0 | D15: =资产负债!F20 -> 0 | E15: =资产负债!G20 -> 0 | F15: =资产负债!H20 -> 0 | G15: =资产负债!I20 -> 0 | H15: =资产负债!J20 -> 0 | I15: =资产负债!K20 -> 0 | ... U15: =资产负债!W20 -> 0
A16: 股权+利润分配 | B16: =B7+B15 -> 383.08087 | C16: =C7+C15 -> 415.64275 | D16: =D7+D15 -> 450.97238 | E16: =E7+E15 -> 489.30503 | F16: =F7+F15 -> 530.89596 | G16: =G7+G15 -> 576.02212 | H16: =H7+H15 -> 624.984 | I16: =I7+I15 -> 678.10764 | ... U16: =U7+U15 -> 1804.9098
A17: 溢价率 | B17: =B16/B14-1 -> -0.9555901 | C17: =C16/C14-1 -> -0.95181526 | D17: =D16/D14-1 -> -0.94771956 | E17: =E16/E14-1 -> -0.94327572 | F17: =F16/F14-1 -> -0.93845416 | G17: =G16/G14-1 -> -0.93322276 | H17: =H16/H14-1 -> -0.9275467 | I17: =I16/I14-1 -> -0.92138816 | ... U17: =U16/U14-1 -> -0.79075996
A18: 市场价值法：自由现金流量=息前税后利润+所得税抵扣额+折旧及摊销-资本性支出-营运资金追加额
A19: 运营年 | B19: 1 | C19: 2 | D19: 3 | E19: 4 | F19: 5 | G19: 6 | H19: 7 | I19: 8 | J19: 9 | K19: 10 | L19: 11 | M19: 12 | N19: 13 | O19: 14 | P19: 15 | Q19: 16 | R19: 17 | S19: 18 | T19: 19 | U19: 20
A20: 资本性支出 | B20: =成本!E31 -> 36685.994 | C20: =成本!F31 -> 34205.447 | D20: =成本!G31 -> 31724.899 | E20: =成本!H31 -> 29244.351 | F20: =成本!I31 -> 26763.804 | G20: =成本!J31 -> 24283.256 | H20: =成本!K31 -> 21802.708 | I20: =成本!L31 -> 19322.161 | ... U20: =成本!X31 -> 1958.3271
A21: 息税前利润-调整所得税+折旧摊销 | B21: =现金流量!E20-现金流量!E19+成本!E6 -> 1417.3696 | C21: =现金流量!F20-现金流量!F19+成本!F6 -> 1423.571 | D21: =现金流量!G20-现金流量!G19+成本!G6 -> 1429.7724 | E21: =现金流量!H20-现金流量!H19+成本!H6 -> 1566.5455 | F21: =现金流量!I20-现金流量!I19+成本!I6 -> 1571.9717 | G21: =现金流量!J20-现金流量!J19+成本!J6 -> 1303.2321 | H21: =现金流量!K20-现金流量!K19+成本!K6 -> 1476.071 | I21: =现金流量!L20-现金流量!L19+成本!L6 -> 1480.7221 | ... U21: =现金流量!X20-现金流量!X19+成本!X6 -> 670.03857
A22: 净现金流量 | B22: =B21 -> 1417.3696 | C22: =现金流量!F20-现金流量!F19+成本!F6 -> 1423.571 | D22: =现金流量!G20-现金流量!G19+成本!G6 -> 1429.7724 | E22: =现金流量!H20-现金流量!H19+成本!H6 -> 1566.5455 | F22: =现金流量!I20-现金流量!I19+成本!I6 -> 1571.9717 | G22: =现金流量!J20-现金流量!J19+成本!J6 -> 1303.2321 | H22: =现金流量!K20-现金流量!K19+成本!K6 -> 1476.071 | I22: =现金流量!L20-现金流量!L19+成本!L6 -> 1480.7221 | J22: =现金流量!M20-现金流量!M19+成本!M6 -> 1485.3731 | ... U22: =现金流量!X20-现金流量!X19+成本!X6 -> 670.03857
A23: 终值 | B23: =B22*(1+参数表!$C$61)^(现金流量!$X$4-现金流量!E$4) -> 6678.0267 | C23: =C22*(1+参数表!$C$61)^(现金流量!$X$4-现金流量!F$4) -> 6181.7924 | D23: =D22*(1+参数表!$C$61)^(现金流量!$X$4-现金流量!G$4) -> 5722.3241 | E23: =E22*(1+参数表!$C$61)^(现金流量!$X$4-现金流量!H$4) -> 5778.5492 | F23: =F22*(1+参数表!$C$61)^(现金流量!$X$4-现金流量!I$4) -> 5344.2995 | G23: =G22*(1+参数表!$C$61)^(现金流量!$X$4-现金流量!J$4) -> 4083.5521 | H23: =H22*(1+参数表!$C$61)^(现金流量!$X$4-现金流量!K$4) -> 4262.7892 | I23: =I22*(1+参数表!$C$61)^(现金流量!$X$4-现金流量!L$4) -> 3941.2176 | ... U23: =U22*(1+参数表!$C$61)^(现金流量!$X$4-现金流量!X$4) -> 670.03857
A24: 卖出价格 | B24: =SUM(B23:$U23)/(1+参数表!$C$61)^(现金流量!$X4-现金流量!E4) -> 13771.925 | C24: =SUM(C23:$U23)/(1+参数表!$C$61)^(现金流量!$X4-现金流量!F4) -> 13404.692 | D24: =SUM(D23:$U23)/(1+参数表!$C$61)^(现金流量!$X4-现金流量!G4) -> 12999.517 | E24: =SUM(E23:$U23)/(1+参数表!$C$61)^(现金流量!$X4-现金流量!H4) -> 12553.172 | F24: =SUM(F23:$U23)/(1+参数表!$C$61)^(现金流量!$X4-现金流量!I4) -> 11920.49 | G24: =SUM(G23:$U23)/(1+参数表!$C$61)^(现金流量!$X4-现金流量!J4) -> 11228.143 | H24: =SUM(H23:$U23)/(1+参数表!$C$61)^(现金流量!$X4-现金流量!K4) -> 10768.528 | I24: =SUM(I23:$U23)/(1+参数表!$C$61)^(现金流量!$X4-现金流量!L4) -> 10082.316 | ... U24: =SUM(U23:$U23)/(1+参数表!$C$61)^(现金流量!$X4-现金流量!X4) -> 670.03857
A25: 10%股权卖出价格
A26: 所有者权益 | B26: =资产负债!D18 -> 5870.1239 | C26: =资产负债!E18 -> 3125.4392 | D26: =资产负债!F18 -> 397.12301 | E26: =资产负债!G18 -> -2315.7721 | F26: =资产负债!H18 -> -5012.0974 | G26: =资产负债!I18 -> -8003.9629 | H26: =资产负债!J18 -> -10990.367 | I26: =资产负债!K18 -> -13970.519 | ... U26: =资产负债!W18 -> -39936.657
B27: =B11-B14 -> -8243.1354 | C27: =C11-C14 -> -8210.5898 | D27: =D11-D14 -> -8175.2778 | E27: =E11-E14 -> -8136.9644 | F27: =F11-F14 -> -8095.3942 | G27: =G11-G14 -> -8050.2906 | H27: =H11-H14 -> -8001.3532 | I27: =I11-I14 -> -7948.2561 | ... U27: =U11-U14 -> -6822.0174
B28: =B5 -> 0 | C28: =C5/(1+$B$1)^(C4-$B$4) -> 0 | D28: =D5/(1+$B$1)^(D4-$B$4) -> 0 | E28: =E5/(1+$B$1)^(E4-$B$4) -> 0 | F28: =F5/(1+$B$1)^(F4-$B$4) -> 0 | G28: =G5/(1+$B$1)^(G4-$B$4) -> 0 | H28: =H5/(1+$B$1)^(H4-$B$4) -> 0 | I28: =I5/(1+$B$1)^(I4-$B$4) -> 0 | J28: =J5/(1+$B$1)^(J4-$B$4) -> -1.0654787e-12 | ... U28: =U5/(1+$B$1)^(U4-$B$4) -> 415.64275
