Workbook
Name aa: 投资计划!$J$28
Name ab: 投资计划!$K$28
Name ac: 投资计划!$L$28
Name b: 投资计划!$J$27
Name cc: 投资计划!$J$29
Name i: 投资计划!$J$26
Name j: 投资计划!$J$30
Name 存款利率: 参数表!#REF!
Name 短期贷款利息: 参数表!$C$34
Name 公益金: 指标汇总!#REF!
Name 流动资金贷款比例: 参数表!#REF!
Name 流动资金贷款利率: 参数表!$C$33
Name 流动资金总额: 参数表!$C$29
Name 年发电量: 指标汇总!$D$22
Name 其他费用费率: 参数表!$C$56
Name 所得税率: 参数表!$C$40
Name 盈余公积金: 参数表!$C$46
Name 增值税率: 参数表!$C$36
Name 装机容量: 指标汇总!$D$21
Name 总投资: 指标汇总!$D$23

Sheet 参数表
A1: 序号 | B1: 名 称 | C1: 指标 | D1: 单位 | E1: 说明
A2: 1 | B2: 装机容量（直流侧） | C2: =15 -> 15 | D2: 万kW | E2: 数据来源：预可行性研究报告或可行性研究报告
A3: 2 | B3: 首年无衰减利用小时数（综合考虑技术优化） | C3: 1145 | D3: 小时 | E3: 数据来源：预可行性研究报告或可行性研究报告；初步测算时，可从https://globalsolaratlas.info/查询相关数据
B4: 运营年度 | C4: 2020 | D4: 2021 | E4: 2022 | F4: 2023 | G4: 2024 | H4: 2025 | I4: 2026 | J4: 2027 | K4: 2028 | L4: 2029 | M4: 2030 | N4: 2031 | O4: 2032 | P4: 2033 | Q4: 2034 | R4: 2035 | S4: 2036 | T4: 2037 | U4: 2038 | V4: 2039 | W4: 2040 | X4: 2041 | Y4: 2042 | Z4: 2043 | AA4: 2044 | AB4: 2045
A5: 3 | B5: 衰减后功率比例 | C5: 0 | D5: 0.975 | E5: 0.97 | F5: 0.965 | G5: 0.96 | H5: 0.955 | I5: 0.95 | J5: 0.945 | K5: 0.94 | L5: 0.935 | M5: 0.93 | N5: 0.925 | O5: 0.92 | P5: 0.915 | Q5: 0.91 | R5: 0.905 | S5: 0.9 | T5: 0.895 | U5: 0.89 | V5: 0.885 | W5: 0.88 | X5: 0.875 | Y5: 0.87 | Z5: 0.865 | AA5: 0.86 | AB5: 0.855
A6: 4 | B6: 负荷率 | C6: 0 | D6: =100%*0.95 -> 0.95 | E6: 1 | F6: 1 | G6: 1 | H6: 1 | I6: 1 | J6: 1 | K6: 1 | L6: 1 | M6: 1 | N6: 1 | O6: 1 | P6: 1 | Q6: 1 | R6: 1 | S6: 1 | T6: 1 | U6: 1 | V6: 1 | W6: 1 | X6: 1 | Y6: 1 | Z6: 1 | AA6: 1 | AB6: 1
A7: 5 | B7: 年发电小时数 | C7: =SUM(损益!G5:AE5)/25/参数表!C2 -> 1045.4423 | D7: 小时 | E7: 自动计算
A8: 6 | B8: 上网电价 | C8: =C9+C11 -> 0.401 | D8: 元/kW·h | E8: 平价上网项目为当地煤电标杆电价（现称基准电价，含脱硫脱硝除尘，含增值税），竞价项目为含补贴电价（含增值税）
A9: 6.1 | B9: 无补贴上网电价 | C9: 0.401 | D9: 元/kW·h | E9: 当地煤电标杆电价（现称基准电价），综合考虑市场化交易（若有）和“两个细则”考核成本、省内外辅助服务市场化交易分摊成本。
A10: 6.2 | B10: 市场化交易电价 | C10: 0.39 | D10: 元/kW·h | E10: 市场化交易电价，综合考虑市场化交易（若有）和“两个细则”考核成本、省内外辅助服务市场化交易分摊成本。
A11: 6.3 | B11: 度电补贴强度 | C11: 0 | D11: 元/kW·h | E11: 参考值，《风电、光伏发电项目建设工作方案》（国能发新能〔2019〕49号）规定：列入国家补贴范围的光伏发电项目，应在申报的预计投产时间所在的季度末之前全容量建成并网，逾期未建成并网的，每逾期一个季度并网电价补贴降低0.01元/千瓦时；在申报投产所在季度后两个季度内仍未建成并网的，取消项目补贴资格。本参数按照延期一个季度并网取值，拟申报电价在该参数基础上增加0.01元/千瓦时。
A12: 6.4 | B12: 补贴到位率 | C12: =C4 -> 2020 | D12: =D4 -> 2021 | E12: =E4 -> 2022 | F12: =F4 -> 2023 | G12: =G4 -> 2024 | H12: =H4 -> 2025 | I12: =I4 -> 2026 | J12: =J4 -> 2027 | ... AB12: =AB4 -> 2045
D13: 0 | E13: 2 | F13: 1 | G13: 1 | H13: 1 | I13: 1 | J13: 1 | K13: 1 | L13: 1 | M13: 1 | N13: 1 | O13: 1 | P13: 1 | Q13: 1 | R13: 1 | S13: 1 | T13: 1 | U13: 1 | V13: 1 | W13: 1 | X13: 1 | Y13: 1 | Z13: 1 | AA13: 1 | AB13: 1
A14: 6.5 | B14: 标杆上网电价-保障利用小时数 | C14: 1100 | D14: 小时 | E14: 若为竞价类项目，保障收购年利用小时数按《关于做好风电、光伏发电全额保障性收购管理工作的通知》（发改能源〔2016〕1150号）规定的最低保障收购年利用小时数计算，未规定最低保障收购年利用小时数的，按II类地区1300、III类地区1100基础小时数计算。
A15: 7 | B15: 静态投资 | C15: =C16+C17+C18+C22+C68 -> 56315.741 | D15: 万元 | E15: 自动计算
A16: 7.1 | B16: 建安工程费 | C16: 10046.37 | D16: 万元 | E16: 参考值，数据来源：预可行性研究报告或可行性研究报告
A17: 7.2 | B17: 设备购置费 | C17: 40042.42 | D17: 万元 | E17: 参考值，数据来源：预可行性研究报告或可行性研究报告
A18: 7.3 | B18: 其他费用 | C18: =2281.33+C20 -> 5281.33 | D18: 万元 | E18: 参考值，数据来源：预可行性研究报告或可行性研究报告(本数据不含光伏阵列区土地租金，光伏阵列区租金列入参数26，仍计入静态投资)
A19: 7.3.1 | B19: 其中：建设用地费 | C19: =180 -> 180 | D19: 万元 | E19: 参考值，含土地征用费、临时用地租用费、迁移补偿费、余物清理费等。其中，土地征用费含土地补偿费、安置补助费、耕地占用税、耕地开垦费、勘测定界费、征地管理费、证书费、手续费等。含光伏区用地林木补偿、青苗和经济作物补偿、城市绿化补偿、建构筑物补偿等。另有森林植被恢复费（若有）、草原植被恢复费（若有）。耕地占用税要专项论证。(本数据不含光伏阵列区土地租金，光伏阵列区租金列入参数26，首年支付的租金仍计入静态投资)
A20: 7.3.1.1 | B20: 其中：耕地占用税 | C20: 3000 | D20: 万元 | E20: 参考值，耕地占用税（若有）
A21: 7.3.2 | B21: 其中：勘察设计费 | C21: 600 | D21: 万元 | E21: 参考值，数据来源：预可行性研究报告或可行性研究报告
A22: 7.4 | B22: 基本预备费 | C22: 631.8 | D22: 万元 | E22: 参考值，数据来源：预可行性研究报告或可行性研究报告
A23: 8 | B23: 单位静态投资 | C23: =(C16+C17+C18+C22)/C2 -> 3733.4613 | D23: 元/kW | E23: 参考值，自动计算
A24: 9 | B24: EPC单价 | C24: =(C16+C17+C21)/C2 -> 3379.2527 | D24: 元/kW | E24: 参考值，自动计算
A25: 10 | B25: 建设期可抵扣增值税 | C25: =C16/(1+C26)*C26+C17/(1+C27)*C27+C21/(1+C28)*C28 -> 5470.1291 | D25: 万元 | E25: 参考值，自动计算，假定建安工程费、设备购置费、勘察设计费可足额开具增值税发票
A26: 10.1 | B26: 建安工程费增值税税率 | C26: 0.09 | E26: 可不调整
A27: 10.2 | B27: 设备购置费增值税税率 | C27: 0.13 | E27: 可不调整
A28: 10.3 | B28: 勘察设计费增值税税率 | C28: 0.06 | E28: 可不调整
A29: 11 | B29: 流动资金总额 | C29: =参数表!C2*30 -> 450 | D29: 万元 | E29: 参考值，数据来源：预可行性研究报告或可行性研究报告
A30: 12 | B30: 资本金比例 | C30: 0.2 | E30: 根据《国务院关于加强固定资产投资项目资本金管理的通知》（国发〔2019〕26号），电力项目最低资本金比例取20%。须与可行性研究报告一致。计算资本金基数的总投资，是指投资项目的固定资产投资与铺底流动资金之和，具体核定时以经批准的动态概算为依据
A31: 13 | B31: 长期借款利率 | C31: 0.0465 | E31: 参考值，根据项目情况向银行初步询价
A32: 14 | B32: 长期借款年限（不含建设期） | C32: 15 | D32: 年 | E32: 参考值，根据项目情况向银行初步询价
A33: 15 | B33: 流动资金贷款利率 | C33: 0.0435 | E33: 参考值，根据项目情况向银行初步询价
A34: 16 | B34: 短期贷款利息 | C34: 0.0435 | E34: 参考值，根据项目情况向银行初步询价
A35: 17 | B35: 建设周期 | C35: 6 | D35: 月 | E35: 参考值，数据来源：预可行性研究报告或可行性研究报告
A36: 18.1 | B36: 增值税率 | C36: 0.13 | E36: 目前光伏发电项目增值税税率为13%，若有其他优惠政策可更改该税率。参见《风电、光伏发电项目涉税事项》
A37: 18.2 | B37: 增值税优惠享受年限 | C37: 2020 | D37: 年 | E37: 光伏发电项目即征即退享受年限，目前光伏发电项目无该政策
A38: 19 | B38: 城市建设维护税率 | C38: 0.05 | E38: 参见《风电、光伏发电项目涉税事项》
A39: 20 | B39: 教育费附加费率 | C39: 0.05 | E39: 参见《风电、光伏发电项目涉税事项》
A40: 21 | B40: 所得税税率 | C40: 0.25 | E40: 目前光伏发电项目享受所得税三免三减半优惠政策，参见《风电、光伏发电项目涉税事项》
A41: 21.1 | B41: 是否享受西部大开发优惠税率 | C41: 否 | E41: 根据《关于延续西部大开发企业所得税政策的公告》（财政部 税务总局 国家发展改革委公告2020年第23号）自2021年1月1日至2030年12月31日，对设在西部地区的鼓励类产业企业减按15%的税率征收企业所得税。根据《西部地区鼓励类产业目录（2014年修订版）》，甘肃省、青海省、宁夏回族自治区、新疆维吾尔自治区、内蒙古自治区鼓励产业目录含风力发电场建设及运营、太阳能发电系统建设及运营，可享受15%的所得税税率。参见《风电、光伏发电项目涉税事项》
A42: 21.2 | B42: 西部大开发优惠所得税税率 | C42: 0.15
A43: 22 | B43: 城镇土地使用税 | C43: =C44*C45/10000 -> 0 | D43: 万元 | E43: 参考值，一般在工矿区的建设用地需要征收城镇土地使用税
A44: 22.1 | B44: 城镇土地使用税税率 | C44: 0 | D44: 元/亩 | E44: 参见《风电、光伏发电项目涉税事项》，并咨询当地税务机关。
A45: 22.2 | B45: 征收面积 | C45: 0 | D45: 亩 | E45: 参见《风电、光伏发电项目涉税事项》，并咨询当地税务机关。
A46: 23 | B46: 法定盈余公积金比率 | C46: 0.1 | E46: 可不调整
A47: 24 | B47: 折旧率 | C47: =(1-参数表!C49)/参数表!C48 -> 0.0475 | E47: 参考值
A48: 24.1 | B48: 折旧年限 | C48: 20 | E48: 可不调整。数据来源：预可行性研究报告或可行性研究报告
A49: 24.2 | B49: 残值率 | C49: 0.05 | E49: 可不调整。数据来源：预可行性研究报告或可行性研究报告
A50: 25 | B50: 首年运维费费率 | C50: =(成本!E7+成本!E8+成本!E10+成本!E18)/参数表!C2 -> 49.007102 | D50: 元/kW | E50: 参考值
A51: 25.1 | B51: 年修理费率 | C51: =C4 -> 2020 | D51: =D4 -> 2021 | E51: =E4 -> 2022 | F51: =F4 -> 2023 | G51: =G4 -> 2024 | H51: =H4 -> 2025 | I51: =I4 -> 2026 | J51: =J4 -> 2027 | ... AB51: =AB4 -> 2045
D52: 0.002 | E52: 0.002 | F52: 0.002 | G52: 0.004 | H52: 0.004 | I52: 0.004 | J52: 0.004 | K52: 0.004 | L52: 0.006 | M52: 0.006 | N52: 0.006 | O52: 0.006 | P52: 0.006 | Q52: 0.006 | R52: 0.01 | S52: 0.01 | T52: 0.01 | U52: 0.01 | V52: 0.01 | W52: 0.01 | X52: 0.01 | Y52: 0.01 | Z52: 0.01 | AA52: 0.01 | AB52: 0.01
A53: 25.2 | B53: 员工人数 | C53: 8 | E53: 参考值，数据来源：预可行性研究报告或可行性研究报告
A54: 25.3 | B54: 年均工资 | C54: 9 | D54: 万元 | E54: 参考值，数据来源：预可行性研究报告或可行性研究报告
A55: 25.4 | B55: 福利费率 | C55: 0.5 | E55: 参考值，数据来源：预可行性研究报告或可行性研究报告
A56: 25.5 | B56: 年其他费用费率 | C56: 25 | D56: 元/kW | E56: 参考值，数据来源：预可行性研究报告或可行性研究报告
A57: 25.6 | B57: 年材料费费率 | C57: 10 | D57: 元/kW | E57: 参考值，数据来源：预可行性研究报告或可行性研究报告
A58: 25.7 | B58: 年保险费费率 | C58: 0.0005 | E58: 参考值，数据来源：预可行性研究报告或可行性研究报告
A59: 26 | B59: 首年土地租金 | C59: =C61*C62/10000 -> 156.9105 | E59: 自动计算
A60: 26.1 | B60: 单位占地面积 | C60: 11.623 | D60: hm2/10MW | E60: 参考值，具体指标见预可行性研究报告或可行性研究报告。初步估算时，可根据国土资源部《光伏发电站工程项目用地控制指标》（国土资规〔2015〕11号）选取。本部分仅含光伏阵列区用地。升压站用地默认为建设用地，其费用已包含在项目静态投资中。
A61: 26.2 | B61: 占地面积 | C61: =C2*C60*10000/(1000*2/3) -> 2615.175 | D61: 亩 | E61: 参考值
A62: 26.3 | B62: 首年每亩土地租金 | C62: 600 | D62: 元/亩 | E62: 参考值，数据来源：根据与土地使用权人签订的租赁协议确定
A63: 26.4 | B63: 土地租金上浮频率 | C63: 3 | D63: 年/次 | E63: 参考值，数据来源：根据与土地使用权人签订的租赁协议确定
A64: 26.5 | B64: 土地租金上浮率 | C64: 0.05 | E64: 参考值，数据来源：根据与土地使用权人签订的租赁协议确定
A65: 26.6 | B65: 土地租金支付频率 | C65: 2 | D65: 年/次 | E65: 参考值，数据来源：根据与土地使用权人签订的租赁协议确定
C66: =C4 -> 2020 | D66: =D4 -> 2021 | E66: =E4 -> 2022 | F66: =F4 -> 2023 | G66: =G4 -> 2024 | H66: =H4 -> 2025 | I66: =I4 -> 2026 | J66: =J4 -> 2027 | ... AB66: =AB4 -> 2045
C67: =INT((C66-$C$66)/$C$65)+1 -> 1 | D67: =INT((D66-$C$66)/$C$65)+1 -> 1 | E67: =INT((E66-$C$66)/$C$65)+1 -> 2 | F67: =INT((F66-$C$66)/$C$65)+1 -> 2 | G67: =INT((G66-$C$66)/$C$65)+1 -> 3 | H67: =INT((H66-$C$66)/$C$65)+1 -> 3 | I67: =INT((I66-$C$66)/$C$65)+1 -> 4 | J67: =INT((J66-$C$66)/$C$65)+1 -> 4 | ... AB67: =INT((AB66-$C$66)/$C$65)+1 -> 13
A68: 26.7 | B68: 土地租金支付（万元） | C68: =IF((C66-$C$66)/$C$65-INT((C66-$C$66)/$C$65)=0,SUMIF(C67:AB67,(C66-$C$66)/$C$65+1,C69:AB69),0) -> 313.821 | D68: =IF((D66-$C$66)/$C$65-INT((D66-$C$66)/$C$65)=0,SUMIF(D67:AC67,(D66-$C$66)/$C$65+1,D69:AC69),0) -> 0 | E68: =IF((E66-$C$66)/$C$65-INT((E66-$C$66)/$C$65)=0,SUMIF(E67:AD67,(E66-$C$66)/$C$65+1,E69:AD69),0) -> 321.66653 | F68: =IF((F66-$C$66)/$C$65-INT((F66-$C$66)/$C$65)=0,SUMIF(F67:AE67,(F66-$C$66)/$C$65+1,F69:AE69),0) -> 0 | G68: =IF((G66-$C$66)/$C$65-INT((G66-$C$66)/$C$65)=0,SUMIF(G67:AF67,(G66-$C$66)/$C$65+1,G69:AF69),0) -> 329.51205 | H68: =IF((H66-$C$66)/$C$65-INT((H66-$C$66)/$C$65)=0,SUMIF(H67:AG67,(H66-$C$66)/$C$65+1,H69:AG69),0) -> 0 | I68: =IF((I66-$C$66)/$C$65-INT((I66-$C$66)/$C$65)=0,SUMIF(I67:AH67,(I66-$C$66)/$C$65+1,I69:AH69),0) -> 345.98765 | J68: =IF((J66-$C$66)/$C$65-INT((J66-$C$66)/$C$65)=0,SUMIF(J67:AI67,(J66-$C$66)/$C$65+1,J69:AI69),0) -> 0 | ... AB68: =IF((AB66-$C$66)/$C$65-INT((AB66-$C$66)/$C$65)=0,SUMIF(AB67:BA67,(AB66-$C$66)/$C$65+1,AB69:BA69),0) -> 0
A69: 26.8 | B69: 土地租金年摊销（租金，万元） | C69: =$C$59*(1+$C$64)^(INT((C66-$C$66)/$C$63)) -> 156.9105 | D69: =$C$59*(1+$C$64)^(INT((D66-$C$66)/$C$63)) -> 156.9105 | E69: =$C$59*(1+$C$64)^(INT((E66-$C$66)/$C$63)) -> 156.9105 | F69: =$C$59*(1+$C$64)^(INT((F66-$C$66)/$C$63)) -> 164.75603 | G69: =$C$59*(1+$C$64)^(INT((G66-$C$66)/$C$63)) -> 164.75603 | H69: =$C$59*(1+$C$64)^(INT((H66-$C$66)/$C$63)) -> 164.75603 | I69: =$C$59*(1+$C$64)^(INT((I66-$C$66)/$C$63)) -> 172.99383 | J69: =$C$59*(1+$C$64)^(INT((J66-$C$66)/$C$63)) -> 172.99383 | ... AB69: =$C$59*(1+$C$64)^(INT((AB66-$C$66)/$C$63)) -> 231.82827
A70: 27 | B70: 分红比例 | C70: 0.8 | E70: 参考值，计算投资方内部收益率时适用该参数
A71: 28 | B71: 购买方基准收益率（资本金） | C71: 0.085 | E71: 参考值，购买方对项目的预期资本金财务内部收益率
A72: 29 | B72: 股权出售所得税税率 | C72: 0.15 | E72: 参考值，项目公司股东的所得税税率
A73: 30 | B73: EPC签约价 | C73: =C24 -> 3379.2527 | D73: 元/kW | E73: 参考值，含增值税
A74: 31 | B74: EPC成本价 | C74: 3200 | D74: 元/kW | E74: 参考值，含勘察设计费、项目管理费及增值税
A75: 32 | B75: 管理费分摊比率 | C75: 0 | E75: 参考值，根据各单位管理费分摊比率确定（可参考上一年度财务报表）
A76: 33 | B76: 运营年限 | C76: 25
B77: 工程收益 | C77: 300
B78: 暂列金 | C78: 3000
A79: 使用说明：填写本表中底色为绿色的单元格，主要指标计算结果见指标汇总表

Sheet 指标汇总
E2: 工程概况及关键指标表
B4: 序号 | C4: 名 称 | D4: 指标 | E4: 单位 | F4: 序号 | G4: 名 称 | H4: 指标 | I4: 单位
B5: 1 | C5: 装机容量 | D5: =参数表!C2 -> 15 | E5: 万kW | F5: 10 | G5: 年发电量 | H5: =参数表!C2*参数表!C7 -> 15681.634 | I5: 万kWh
B6: 2 | C6: 单位千瓦投资（静态） | D6: =参数表!C23 -> 3733.4613 | E6: 元/kw | F6: 11 | G6: 静态投资 | H6: =参数表!C15 -> 56315.741 | I6: 万元
B7: 3 | C7: 资本金比例设定 | D7: =参数表!C30*100 -> 20 | E7: % | F7: 12 | G7: 动态投资 | H7: =投资计划!C9 -> 56837.219 | I7: 万元
B8: 4 | C8: 含税上网电价 | D8: =参数表!C8 -> 0.401 | E8: 元/kW·h | F8: 13 | G8: 盈利能力指标
B9: 5 | C9: 年发电小时数 | D9: =参数表!C7 -> 1045.4423 | E9: 小时 | F9: 14 | G9: 项目投资财务内部收益率（所得税前） | H9: =现金流量!L29 -> 7.1209828 | I9: %
B10: 6 | C10: 单位电度投资（动态） | D10: =H7/H5 -> 3.624445 | E10: 元/kwh | G10: 资本金财务内部收益率（所得税后） | H10: =现金流量!H61*100 -> 9.5588554 | I10: %
C11: 经营指标 | G11: 考虑工程收益的资本金财务内部收益率（所得税后） | H11: =现金流量!D69*100 -> 12.353622 | I11: %
B12: 7 | C12: 年均经营成本 | D12: =成本!AD22/25 -> 994.79856 | E12: 万元 | F12: 15 | G12: 偿债能力指标
B13: 8 | C13: 单位电度经营成本 | D13: =D12/年发电量 -> 0.063437176 | E13: 元/kW·h | F13: 16 | G13: 最大资产负债率 | H13: =H38 -> 79.098036 | I13: %
B14: 9 | C14: 单位千瓦经营成本 | D14: =D12/装机容量 -> 66.319904 | E14: 元/kW | F14: 17 | G14: 累计最大短期借款 | H14: =H40 -> 430.05943 | I14: 万元
F15: 18 | G15: 贷款还贷年限（不含建设期） | H15: =参数表!C32 -> 15 | I15: 年
E18: 财务指标汇总表
B20: 序号 | C20: 名 称 | D20: 指标 | E20: 单位 | F20: 序号 | G20: 名 称 | H20: 指标 | I20: 单位
B21: 1 | C21: 装机容量 | D21: =参数表!C2 -> 15 | E21: 万kW | G21: 盈利能力指标
B22: 2 | C22: 年发电量 | D22: =H5 -> 15681.634 | E22: 万kWh | F22: 18 | G22: 项目投资回收期 | H22: =现金流量!I31 -> 11.772371 | I22: 年
B23: 3 | C23: 总投资 | D23: =投资计划!C5 -> 57287.219 | E23: 万元 | F23: 19 | G23: 项目投资财务内部收益率（所得税前） | H23: =现金流量!L29 -> 7.1209828 | I23: %
B24: 4 | C24: 建设期利息 | D24: =投资计划!H7 -> 521.47771 | E24: 万元 | G24: 项目投资财务净现值（所得税前 ic=5%） | H24: =现金流量!L30 -> 11023.467 | I24: 万元
B25: 5 | C25: 流动资金 | D25: =投资计划!C8 -> 450 | E25: 万元 | F25: 20 | G25: 财务内部收益率（所得税后）
B26: 6 | C26: 电价 | F26: 20.1 | G26: 项目投资 | H26: =现金流量!I29 -> 6.1292325 | I26: %
B27: 6.1 | C27: 上网电价（不含增值税） | D27: =D28/(1+增值税率) -> 0.35486726 | E27: 元/kW·h | F27: 20.2 | G27: 资本金 | H27: =现金流量!H61*100 -> 9.5588554 | I27: %
B28: 6.2 | C28: 上网电价（含增值税） | D28: =参数表!C8 -> 0.401 | E28: 元/kW·h | F28: 20.3 | G28: 投资方 | H28: =现金流量!H97*100 -> 7.0287445 | I28: %
C29: 经营指标 | F29: 21 | G29: 财务净现值（所得税后）
B30: 7 | C30: 发电销售收入总额 | D30: =损益!AF8 -> 139087.35 | E30: 万元 | F30: 21.1 | G30: 项目投资（ic=5%） | H30: =现金流量!I30 -> 5520.7271 | I30: %
B31: 8 | C31: 总成本费用总额 | D31: =成本!AD21 -> 97217.02 | E31: 万元 | F31: 21.2 | G31: 资本金（ic=8%） | H31: =现金流量!H62 -> 1908.7093 | I31: 万元
B32: 9 | C32: 销售税金附加总额 | D32: =损益!AF9 -> 1261.1226 | E32: 万元 | F32: 21.3 | G32: 投资方（ic=8%） | H32: =现金流量!H98 -> -1511.6989 | I32: 万元
B33: 10 | C33: 发电利润总额 | D33: =损益!AF15 -> 40609.207 | E33: 万元 | F33: 22 | G33: 单位电度投资（动态） | H33: =D10 -> 3.624445 | I33: 元/kwh
B34: 11 | C34: 年均经营成本 | D34: =成本!AD22/25 -> 994.79856 | E34: 万元 | F34: 23 | G34: 投资利润率（生产期平均） | H34: =D33/总投资/25*100 -> 2.8354811 | I34: %
B35: 12 | C35: 单位电度经营成本 | D35: =D34/年发电量 -> 0.063437176 | E35: 元/kW·h | F35: 24 | G35: 投资利税率（生产期平均） | H35: =(指标汇总!D52+损益!AF21)/25/总投资*100 -> 1.6346573 | I35: %
B36: 13 | C36: 单位千瓦经营成本 | D36: =D34/装机容量 -> 66.319904 | E36: 元/kW | F36: 25 | G36: 资本金净利润率 | H36: =损益!AF26/25/投资计划!C11*100 -> 10.847206 | I36: %
C37: 其他指标 | G37: 偿债负债指标
B38: 14 | C38: 年发电小时数 | D38: =参数表!C7 -> 1045.4423 | E38: 小时 | F38: 26 | G38: 最大资产负债率 | H38: =资产负债!D28*100 -> 79.098036 | I38: %
B39: 15 | C39: 单位电度投资（动态） | D39: =D23/D22 -> 3.653141 | E39: 元/kwh | F39: 27 | G39: 最大累计亏损额 | H39: =MIN(0,损益!AF16) -> 0 | I39: 万元
B40: 16 | C40: 单位千瓦投资（静态） | D40: =参数表!C23 -> 3733.4613 | E40: 元/KW | F40: 28 | G40: 累计最大短期借款 | H40: =财务计划!C22 -> 430.05943 | I40: 万元
B41: 17 | C41: 资本金比例 | D41: =参数表!C30*100 -> 20 | E41: % | F41: 29 | G41: 长期借款还贷年限（不含建设期） | H41: =参数表!C32 -> 15 | I41: 年
C42: 股权出售净利润 | F42: 30 | G42: 全部贷款还贷年限（不含建设期） | H42: =参数表!C32 -> 15 | I42: 年
C43: 资本金出资额 | D43: =投资计划!B27 -> 11457.444 | E43: 万元 | F43: 31 | G43: 利息备付率（平均） | H43: =还贷!AD29 -> 20.994916
C44: 电站转让净利润 | D44: =估值结果!B11-估值结果!B14 -> 1130.7514 | E44: 万元 | F44: 32 | G44: 偿债备付率（平均） | H44: =还贷!AD32 -> 1.1071357
C45: 工程收益 | D45: =((参数表!C73-参数表!C74)*参数表!C2-参数表!C73*参数表!C2/(1+12%)*参数表!C75-((参数表!C73-参数表!C74)*参数表!C2/(1+12%)*12%*1.12))*(1-参数表!C72) -> 2011.2149 | G45: 总投资收益率（ROI） | H45: =现金流量!AD20/25/总投资 -> 0.041737126
C46: 电站转让净利润+EPC净利润 | D46: =D44+D45 -> 3141.9663 | E46: 万元
C48: GDP测算 | G48: 税收和环保效益测算
B49: 序号 | C49: 名称 | D49: 指标 | E49: 单位 | F49: 序号 | G49: 名称 | H49: 指标 | I49: 单位
B50: 1 | C50: 工资福利 | D50: =成本!AD8 -> 2700 | E50: 万元 | F50: 1 | G50: =C52 -> 生产税（增值税、增值税附加税等）金额 | H50: =D52 -> 13872.349 | I50: =E52 -> 万元
B51: 2 | C51: 固定资产折旧 | D51: =成本!AD6+成本!AD12 -> 53181.166 | E51: 万元 | F51: 2 | G51: 所得税金额 | H51: =损益!AF21 -> 9538.8936 | I51: 万元
B52: 3 | C52: 生产税（增值税、增值税附加税等）金额 | D52: =现金流量!AD55+现金流量!AD56 -> 13872.349 | E52: 万元 | F52: 3 | G52: 项目生命周期内税收合计（不含耕地占用税等建设期税收） | H52: =H50+H51 -> 23411.242 | I52: 万元
B53: 4 | C53: 利润总额 | D53: =损益!AF15 -> 40609.207 | E53: 万元 | F53: 4 | G53: 标准煤耗 | H53: 306.9 | I53: 克/kWh
B54: 5 | C54: 利息 | D54: =成本!AD13 -> 19165.89 | E54: 万元 | F54: 5 | G54: 减少标准煤耗 | H54: =H53*年发电量/1000000 -> 4.8126934 | I54: 万吨/年
B55: 6 | C55: 运营期GDP | D55: =D53+D52+D51+D50+D54 -> 129528.61 | E55: 万元 | F55: 6 | G55: 减少二氧化碳排放 | H55: =H54*2.7 -> 12.994272 | I55: 万吨/年
B56: 7 | C56: 固定资本形成总额 | D56: =总投资*0.95 -> 54422.858 | E56: 万元 | F56: 7 | G56: 附近区域碳汇造林项目（PDD）的碳汇强度，可百度检索附近区域PDD项目，如查找关键词“广东 造林 PDD”等 | H56: =115152/111000 -> 1.0374054 | I56: tCO2e/（亩·年）
B57: 8 | C57: 建设期地方产品和服务的采购比例 | D57: 0.3 | F57: 8 | G57: 相当于同等二氧化碳减排量的造林面积 | H57: =H55/H56 -> 12.525742 | I57: 万亩
B58: 9 | C58: 建设期GDP | D58: =D56*D57 -> 16326.857 | E58: 万元
B59: 10 | C59: 土地租金 | D59: 4392 | E59: 万元
B60: 11 | C60: 项目生命周期内产生的地区生产总值（GDP） | D60: =D58+D55+D59 -> 150247.47 | E60: 万元
C63: 当参数表运营年限为20年时：
C64: 全投资财务内部收益率（税前） | D64: =现金流量!L33 -> 5.9648833
C65: 资本金财务内部收益率（税后） | D65: =现金流量!H64 -> 7.8077492

Sheet 投资计划
A1: 投资计划与资金筹措表
A2: 序号 | B2: 年限 | C2: 合计 | D2: 1 | E2: 2 | F2: 1 | G2: 2 | H2: 累计
B3: 静态投资完成比例 | C3: 1 | D3: =aa -> 0 | E3: =ab -> 0 | F3: =ac -> 1 | G3: 0 | H3: 1
B4: 资本金使用比例 | C4: 1 | D4: =D11/$C$11 -> 0 | E4: =E11/$C$11 -> 0 | F4: =F11/$C$11 -> 1 | G4: =G11/$C$11 -> 0 | H4: =SUM(D4:G4) -> 1
A5: 1 | B5: 总投资 | C5: =SUM(C6:C8) -> 57287.219 | D5: =D6+D7+D8 -> 0 | E5: =E6+E7+E8 -> 0 | F5: =F6+F7+F8 -> 56837.219 | G5: =G6+G7+G8 -> 450 | H5: =SUM(D5:G5) -> 57287.219
A6: 1.1 | B6: 建设投资 | C6: =指标汇总!H6 -> 56315.741 | D6: =$C$6*D3 -> 0 | E6: =$C$6*E3 -> 0 | F6: =$C$6*F3 -> 56315.741 | G6: =成本!D54 -> 0 | H6: =SUM(D6:G6) -> 56315.741
A7: 1.2 | B7: 建设期利息 | C7: =B32 -> 521.47771 | D7: =C32 -> 0 | E7: =F32 -> 0 | F7: =G32 -> 521.47771 | H7: =SUM(D7:G7) -> 521.47771
A8: 1.3 | B8: 流动资金 | C8: =流动资金总额 -> 450 | D8: =SUM(D13,D18) -> 0 | E8: =SUM(E13,E18) -> 0 | F8: =SUM(F13,F18) -> 0 | G8: =SUM(G13,G18) -> 450 | H8: =SUM(D8:G8) -> 450
B9: 动态投资 | C9: =C6+C7 -> 56837.219
A10: 2 | B10: 资金筹措 | C10: =SUM(C11,C14) -> 57287.219 | D10: =SUM(D11,D14) -> 0 | E10: =SUM(E11,E14) -> 0 | F10: =SUM(F11,F14) -> 56837.219 | G10: =SUM(G11,G14) -> 450 | H10: =SUM(D10:G10)+D17 -> 57287.219
A11: 2.1 | B11: 自有资金 | C11: =C12+C13 -> 11457.444 | D11: =D12+D13 -> 0 | E11: =E12+E13 -> 0 | F11: =SUM(F12:F13) -> 11457.444 | G11: =SUM(G12:G13) -> 0 | H11: =SUM(D11:G11) -> 11457.444 | I11: =C11/C5 -> 0.2
A12: 2.1.1 | B12: 用于建设投资 | C12: =B27 -> 11457.444 | D12: 0 | E12: 0 | F12: =C12*F3 -> 11457.444 | G12: =C12*G3 -> 0 | H12: =SUM(D12:G12) -> 11457.444
A13: 2.1.2 | B13: 用于流动资金 | C13: =C8*0% -> 0 | G13: =C13 -> 0 | H13: =SUM(D13:G13) -> 0
A14: 2.2 | B14: 借款 | C14: =SUM(C15:C19) -> 45829.775 | D14: =SUM(D15:D19) -> 0 | E14: =SUM(E15:E19) -> 0 | F14: =F15+F18 -> 45379.775 | G14: =SUM(G15:G19) -> 450 | H14: =SUM(D14:G14) -> 45829.775
A15: 2.2.1 | B15: 长期借款 | C15: =F15 -> 45379.775 | D15: =D16+D17 -> 0 | E15: =SUM(E7,E16) -> 0 | F15: =F16+F17 -> 45379.775 | G15: =SUM(G7,G16) -> 0 | H15: =SUM(D15:G15) -> 45379.775
A16: 2.2.1.1 | B16: 长期借款本金 | D16: =C31 -> 0 | E16: =F31 -> 0 | F16: =G31 -> 44858.297 | G16: =G6-G12 -> 0
A17: 2.2.1.2 | B17: 长期借款利息 | D17: =C32 -> 0 | E17: =F32 -> 0 | F17: =G32 -> 521.47771 | G17: =G15-G16 -> 0
A18: 2.2.2 | B18: 流动资金借款 | C18: =C8*100% -> 450 | G18: =C18 -> 450 | H18: =SUM(D18:G18) -> 450
A19: 2.2.3 | B19: 其他短期贷款 | H19: =SUM(D19:G19) -> 0
A20: 2.3 | B20: 其他 | G20: =G7 -> 0 | H20: =SUM(D20:G20) -> 0
A22: 辅助测算表
A23: 合计 | C23: 1 | F23: 2 | G23: 3
A24: 总投资 | B24: =J32 -> 57287.219
A25: 动态投资 | B25: =J31 -> 56837.219
A26: 静态投资 | B26: =参数表!C15 -> 56315.741 | I26: i | J26: =参数表!C31*(参数表!C35/12) -> 0.02325
A27: 资本金 | B27: =B24*J27 -> 11457.444 | I27: b | J27: =参数表!C30 -> 0.2
A28: 贷款 | B28: =B26-B27 -> 44858.297 | I28: a | J28: 0 | K28: 0 | L28: 1
A29: 年度静态投资 | B29: =C29+F29+G29 -> 56315.741 | C29: =$B$26*J28 -> 0 | F29: =$B$26*K28 -> 0 | G29: =$B$26*L28 -> 56315.741 | I29: c | J29: =C8 -> 450
A30: 年度资本金 | B30: =C30+F30+G30 -> 11457.444 | C30: =$B$27*J28 -> 0 | F30: =$B$27*K28 -> 0 | G30: =$B$27*L28 -> 11457.444 | I30: j | J30: =B26 -> 56315.741
A31: 年度贷款 | B31: =C31+F31+G31 -> 44858.297 | C31: =C29-C30 -> 0 | F31: =F29-F30 -> 0 | G31: =G29-G30 -> 44858.297 | I31: D | J31: =(j*(2+i)*(aa*(1+i)^2+ab*(1+i)+ac)+2*cc)/(b*(2+i)*(aa*(1+i)^2+ab*(1+i)+ac)+2*(1-b))-cc -> 56837.219
A32: 年度利息 | B32: =C32+F32+G32 -> 521.47771 | C32: =C31/2*J26 -> 0 | F32: =(F31/2+C32+C31)*J26 -> 0 | G32: =(G31/2+SUM(C31:F32))*J26 -> 521.47771 | I32: Z | J32: =J31+cc -> 57287.219

Sheet 损益
B1: 损 益 表
B3: 序号 | C3: 项目 | G3: 运 营 期 | AF3: 合计
D4: =成本!#REF! -> #REF! | E4: =成本!#REF! -> #REF! | F4: =参数表!C4 -> 2020 | G4: =参数表!D4 -> 2021 | H4: =参数表!E4 -> 2022 | I4: =参数表!F4 -> 2023 | J4: =参数表!G4 -> 2024 | K4: =参数表!H4 -> 2025 | L4: =参数表!I4 -> 2026 | M4: =参数表!J4 -> 2027 | ... AE4: =参数表!AB4 -> 2045
C5: 上网电量(万kW.h) | G5: =参数表!$C$3*参数表!D5*参数表!D6*参数表!$C$2 -> 15908.344 | H5: =参数表!$C$3*参数表!E5*参数表!E6*参数表!$C$2 -> 16659.75 | I5: =参数表!$C$3*参数表!F5*参数表!F6*参数表!$C$2 -> 16573.875 | J5: =参数表!$C$3*参数表!G5*参数表!G6*参数表!$C$2 -> 16488 | K5: =参数表!$C$3*参数表!H5*参数表!H6*参数表!$C$2 -> 16402.125 | L5: =参数表!$C$3*参数表!I5*参数表!I6*参数表!$C$2 -> 16316.25 | M5: =参数表!$C$3*参数表!J5*参数表!J6*参数表!$C$2 -> 16230.375 | N5: =参数表!$C$3*参数表!K5*参数表!K6*参数表!$C$2 -> 16144.5 | ... AE5: =参数表!$C$3*参数表!AB5*参数表!AB6*参数表!$C$2 -> 14684.625
C6: 上网电价（含增值税）(元/kW.h) | G6: =G49 -> 0.401 | H6: =H49 -> 0.40089452 | I6: =I49 -> 0.40095097 | J6: =J49 -> 0.401 | K6: =K49 -> 0.401 | L6: =L49 -> 0.401 | M6: =M49 -> 0.401 | N6: =N49 -> 0.401 | ... AE6: =AE49 -> 0.401
C7: 上网电价（不含增值税）(元/kW.h) | G7: =G6/(1+增值税率) -> 0.35486726 | H7: =H6/(1+增值税率) -> 0.35477391 | I7: =H7 -> 0.35477391 | J7: =I7 -> 0.35477391 | K7: =J7 -> 0.35477391 | L7: =K7 -> 0.35477391 | M7: =L7 -> 0.35477391 | N7: =M7 -> 0.35477391 | O7: =N7 -> 0.35477391 | P7: =O7 -> 0.35477391 | ... AE7: =AD7 -> 0.35477391
B8: 1 | C8: 发电销售收入 | G8: =G5*G7 -> 5645.3503 | H8: =H5*H7 -> 5910.4447 | I8: =I5*I7 -> 5879.9785 | J8: =J5*J7 -> 5849.5123 | K8: =K5*K7 -> 5819.0461 | L8: =L5*L7 -> 5788.5799 | M8: =M5*M7 -> 5758.1136 | N8: =N5*N7 -> 5727.6474 | ... AE8: =AE5*AE7 -> 5209.7219 | AF8: =SUM(D8:AE8) -> 139087.35
B9: 2 | C9: 销售税金附加 | G9: =G10+G11 -> 0 | H9: =H10+H11 -> 0 | I9: =I10+I11 -> 0 | J9: =J10+J11 -> 0 | K9: =K10+K11 -> 0 | L9: =L10+L11 -> 0 | M9: =M10+M11 -> 0 | N9: =N10+N11 -> 55.909831 | ... AE9: =AE10+AE11 -> 67.726384 | AF9: =SUM(D9:AE9) -> 1261.1226
B10: 2.1 | C10: 城市维护建设费 | G10: =G40*参数表!$C$38 -> 0 | H10: =H40*参数表!$C$38 -> 0 | I10: =I40*参数表!$C$38 -> 0 | J10: =J40*参数表!$C$38 -> 0 | K10: =K40*参数表!$C$38 -> 0 | L10: =L40*参数表!$C$38 -> 0 | M10: =M40*参数表!$C$38 -> 0 | N10: =N40*参数表!$C$38 -> 27.954916 | ... AE10: =AE40*参数表!$C$38 -> 33.863192 | AF10: =SUM(D10:AE10) -> 630.56131
B11: 2.2 | C11: 教育费附加 | G11: =G40*参数表!$C$39 -> 0 | H11: =H40*参数表!$C$39 -> 0 | I11: =I40*参数表!$C$39 -> 0 | J11: =J40*参数表!$C$39 -> 0 | K11: =K40*参数表!$C$39 -> 0 | L11: =L40*参数表!$C$39 -> 0 | M11: =M40*参数表!$C$39 -> 0 | N11: =N40*参数表!$C$39 -> 27.954916 | ... AE11: =AE40*参数表!$C$39 -> 33.863192 | AF11: =SUM(D11:AE11) -> 630.56131
B12: 4 | C12: 增值税即征即退补贴 | G12: =IF(G4>参数表!$C$37,0,损益!G41) -> 0 | H12: =IF(H4>参数表!$C$37,0,损益!H41) -> 0 | I12: =IF(I4>参数表!$C$37,0,损益!I41) -> 0 | J12: =IF(J4>参数表!$C$37,0,损益!J41) -> 0 | K12: =IF(K4>参数表!$C$37,0,损益!K41) -> 0 | L12: =IF(L4>参数表!$C$37,0,损益!L41) -> 0 | M12: =IF(M4>参数表!$C$37,0,损益!M41) -> 0 | N12: =IF(N4>参数表!$C$37,0,损益!N41) -> 0 | ... AE12: =IF(AE4>参数表!$C$37,0,损益!AE41) -> 0 | AF12: =SUM(D12:AE12) -> 0
B13: 5 | C13: 营业外收入 | AF13: =SUM(D13:AE13) -> 0
B14: 6 | C14: 总成本费用 | G14: =成本!E21 -> 5349.9051 | H14: =成本!F21 -> 5369.55 | I14: =成本!G21 -> 5271.1206 | J14: =成本!H21 -> 5262.0668 | K14: =成本!I21 -> 5145.7939 | L14: =成本!J21 -> 5032.4085 | M14: =成本!K21 -> 4905.1862 | N14: =成本!L21 -> 4772.1044 | ... AE14: =成本!AC21 -> 1396.2729 | AF14: =SUM(D14:AE14) -> 97217.02
B15: 7 | C15: 利润总额 | G15: =G8-G9-G14+G12+G13 -> 295.44524 | H15: =H8-H9-H14+H12+H13 -> 540.89472 | I15: =I8-I9-I14+I12+I13 -> 608.85791 | J15: =J8-J9-J14+J12+J13 -> 587.44549 | K15: =K8-K9-K14+K12+K13 -> 673.25218 | L15: =L8-L9-L14+L12+L13 -> 756.17138 | M15: =M8-M9-M14+M12+M13 -> 852.92747 | N15: =N8-N9-N14+N12+N13 -> 899.63319 | ... AE15: =AE8-AE9-AE14+AE12+AE13 -> 3745.7226 | AF15: =SUM(D15:AE15) -> 40609.207
B16: 8 | C16: 累计税后利润及弥补亏损 | F16: -0.001 | G16: =G15-G25+G24+F16 -> 295.44424 | H16: =H15-H25+H24+G16 -> 836.33896 | I16: =I15-I25+I24+H16 -> 1445.1969 | J16: =J15-J25+J24+I16 -> 1959.2117 | K16: =K15-K25+K24+J16 -> 2548.3073 | L16: =L15-L25+L24+K16 -> 3209.9573 | M16: =M15-M25+M24+L16 -> 3849.6529 | N16: =N15-N25+N24+M16 -> 4524.3778 | ... AE16: =AE15-AE25+AE24+AD16 -> 31070.312 | AF16: =MIN(G16:AE16) -> 295.44424
A19: C | C19: 所得税
C20: 所得税率 | G20: 0 | H20: 0 | I20: 0 | J20: =IF(参数表!C41="否",所得税率/2,IF(损益!J4<=2030,参数表!C42/2,所得税率/2)) -> 0.125 | K20: =J20 -> 0.125 | L20: =J20 -> 0.125 | M20: =IF(参数表!C41="否",所得税率,IF(损益!J4<=2030,参数表!C42,所得税率)) -> 0.25 | N20: =M20 -> 0.25 | O20: =N20 -> 0.25 | P20: =O20 -> 0.25 | Q20: =所得税率 -> 0.25 | R20: =Q20 -> 0.25 | S20: =R20 -> 0.25 | T20: =S20 -> 0.25 | U20: =T20 -> 0.25 | V20: =U20 -> 0.25 | W20: =V20 -> 0.25 | X20: =W20 -> 0.25 | Y20: =X20 -> 0.25 | ... AE20: =AD20 -> 0.25
B21: 9 | C21: 所得税 | G21: =IF(G15<0,0,(G15-G22)*G20) -> 0 | H21: =IF(H15<0,0,(H15-H22)*H20) -> 0 | I21: =IF(I15<0,0,(I15-I22)*I20) -> 0 | J21: =IF(J15<0,0,(J15-J22)*J20) -> 73.430686 | K21: =IF(K15<0,0,(K15-K22)*K20) -> 84.156522 | L21: =IF(L15<0,0,(L15-L22)*L20) -> 94.521422 | M21: =IF(M15<0,0,(M15-M22)*M20) -> 213.23187 | N21: =IF(N15<0,0,(N15-N22)*N20) -> 224.9083 | ... AE21: =IF(AE15<0,0,(AE15-AE22)*AE20) -> 936.43064 | AF21: =SUM(D21:AE21) -> 9538.8936
B22: 7 | C22: 弥补以前年度亏损 | G22: =IF(G15<0,0,IF(F16>0,0,MIN(G15,-F16))) -> 0.001 | H22: =IF(H15<0,0,IF(G16>0,0,MIN(H15,-G16))) -> 0 | I22: =IF(I15<0,0,IF(H16>0,0,MIN(I15,-H16))) -> 0 | J22: =IF(J15<0,0,IF(I16>0,0,MIN(J15,-I16))) -> 0 | K22: =IF(K15<0,0,IF(J16>0,0,MIN(K15,-J16))) -> 0 | L22: =IF(L15<0,0,IF(K16>0,0,MIN(L15,-K16))) -> 0 | M22: =IF(M15<0,0,IF(L16>0,0,MIN(M15,-L16))) -> 0 | N22: =IF(N15<0,0,IF(M16>0,0,MIN(N15,-M16))) -> 0 | ... AE22: =IF(AE15<0,0,IF(AD16>0,0,MIN(AE15,-AD16))) -> 0
C23: 新增亏损 | G23: =IF(G15<0,-G15,0) -> 0 | H23: =IF(H15<0,-H15,0) -> 0 | I23: =IF(I15<0,-I15,0) -> 0 | J23: =IF(J15<0,-J15,0) -> 0 | K23: =IF(K15<0,-K15,0) -> 0 | L23: =IF(L15<0,-L15,0) -> 0 | M23: =IF(M15<0,-M15,0) -> 0 | N23: =IF(N15<0,-N15,0) -> 0 | ... AE23: =IF(AE15<0,-AE15,0) -> 0
C24: 到期亏损 | L24: =IF(SUM($G$23:G23)>(SUM($G$22:L22)+SUM($G$24:K24)),SUM($G$23:G23)-(SUM($G$22:L22)+SUM($G$24:K24)),0) -> 0 | M24: =IF(SUM($G$23:H23)>(SUM($G$22:M22)+SUM($G$24:L24)),SUM($G$23:H23)-(SUM($G$22:M22)+SUM($G$24:L24)),0) -> 0 | N24: =IF(SUM($G$23:I23)>(SUM($G$22:N22)+SUM($G$24:M24)),SUM($G$23:I23)-(SUM($G$22:N22)+SUM($G$24:M24)),0) -> 0 | O24: =IF(SUM($G$23:J23)>(SUM($G$22:O22)+SUM($G$24:N24)),SUM($G$23:J23)-(SUM($G$22:O22)+SUM($G$24:N24)),0) -> 0 | P24: =IF(SUM($G$23:K23)>(SUM($G$22:P22)+SUM($G$24:O24)),SUM($G$23:K23)-(SUM($G$22:P22)+SUM($G$24:O24)),0) -> 0 | Q24: =IF(SUM($G$23:L23)>(SUM($G$22:Q22)+SUM($G$24:P24)),SUM($G$23:L23)-(SUM($G$22:Q22)+SUM($G$24:P24)),0) -> 0 | R24: =IF(SUM($G$23:M23)>(SUM($G$22:R22)+SUM($G$24:Q24)),SUM($G$23:M23)-(SUM($G$22:R22)+SUM($G$24:Q24)),0) -> 0 | S24: =IF(SUM($G$23:N23)>(SUM($G$22:S22)+SUM($G$24:R24)),SUM($G$23:N23)-(SUM($G$22:S22)+SUM($G$24:R24)),0) -> 0 | ... AE24: =IF(SUM($G$23:Z23)>(SUM($G$22:AE22)+SUM($G$24:AD24)),SUM($G$23:Z23)-(SUM($G$22:AE22)+SUM($G$24:AD24)),0) -> 0
C25: 所得税 | G25: =G21 -> 0 | H25: =H21 -> 0 | I25: =I21 -> 0 | J25: =J21 -> 73.430686 | K25: =K21 -> 84.156522 | L25: =L21 -> 94.521422 | M25: =M21 -> 213.23187 | N25: =N21 -> 224.9083 | ... AE25: =AE21 -> 936.43064
B26: 10 | C26: 净利润 | G26: =IF(G15<=0,0,G15-G22-G25) -> 295.44424 | H26: =IF(H15<=0,0,H15-H22-H25) -> 540.89472 | I26: =IF(I15<=0,0,I15-I22-I25) -> 608.85791 | J26: =IF(J15<=0,0,J15-J22-J25) -> 514.0148 | K26: =IF(K15<=0,0,K15-K22-K25) -> 589.09566 | L26: =IF(L15<=0,0,L15-L22-L25) -> 661.64996 | M26: =IF(M15<=0,0,M15-M22-M25) -> 639.69561 | N26: =IF(N15<=0,0,N15-N22-N25) -> 674.7249 | ... AE26: =IF(AE15<=0,0,AE15-AE22-AE25) -> 2809.2919 | AF26: =SUM(D26:AE26) -> 31070.312
B27: 11 | C27: 法定盈余公积金 | G27: =IF(G16<=0,0,G26*盈余公积金) -> 29.544424 | H27: =IF(H16<=0,0,H26*盈余公积金) -> 54.089472 | I27: =IF(I16<=0,0,I26*盈余公积金) -> 60.885791 | J27: =IF(J16<=0,0,J26*盈余公积金) -> 51.40148 | K27: =IF(K16<=0,0,K26*盈余公积金) -> 58.909566 | L27: =IF(L16<=0,0,L26*盈余公积金) -> 66.164996 | M27: =IF(M16<=0,0,M26*盈余公积金) -> 63.969561 | N27: =IF(N16<=0,0,N26*盈余公积金) -> 67.47249 | ... AE27: =IF(AE16<=0,0,AE26*盈余公积金) -> 280.92919 | AF27: =SUM(D27:AE27) -> 3107.0312
B28: 12 | C28: 法定公益金 | G28: 0 | H28: 0 | I28: 0 | J28: 0 | K28: 0 | L28: 0 | M28: 0 | N28: 0 | O28: 0 | P28: 0 | Q28: 0 | R28: 0 | S28: 0 | T28: 0 | U28: 0 | V28: 0 | W28: 0 | X28: 0 | Y28: 0 | Z28: 0 | AA28: 0 | AB28: 0 | AC28: 0 | AD28: 0 | AE28: 0 | AF28: =SUM(D28:AE28) -> 0
B29: 13 | C29: 可供分配利润 | G29: =IF(G16<=0,0,G26-G27-G28) -> 265.89982 | H29: =IF(H16<=0,0,H26-H27-H28) -> 486.80524 | I29: =IF(I16<=0,0,I26-I27-I28) -> 547.97212 | J29: =IF(J16<=0,0,J26-J27-J28) -> 462.61332 | K29: =IF(K16<=0,0,K26-K27-K28) -> 530.18609 | L29: =IF(L16<=0,0,L26-L27-L28) -> 595.48496 | M29: =IF(M16<=0,0,M26-M27-M28) -> 575.72604 | N29: =IF(N16<=0,0,N26-N27-N28) -> 607.25241 | ... AE29: =IF(AE16<=0,0,AE26-AE27-AE28) -> 2528.3627 | AF29: =SUM(D29:AE29) -> 27963.281
B30: 14 | C30: 偿还上年短期借款需要利润
B31: 15 | C31: 偿还本年长期贷款需要利润
B32: 16 | C32: 实际利润分配 | G32: =财务计划!E31 -> 212.71985 | H32: =财务计划!F31 -> 389.4442 | I32: =财务计划!G31 -> 438.37769 | J32: =财务计划!H31 -> 370.09066 | K32: =财务计划!I31 -> 424.14887 | L32: =财务计划!J31 -> 476.38797 | M32: =财务计划!K31 -> 460.58084 | N32: =财务计划!L31 -> 485.80192 | ... AE32: =财务计划!AC31 -> 2022.6902
B33: 17 | C33: 未分配利润 | G33: =G29-G32+IF(G15<0,G15,G22) -> 53.180964 | H33: =H29-H32+IF(H15<0,H15,H22) -> 97.361049 | I33: =I29-I32+IF(I15<0,I15,I22) -> 109.59442 | J33: =J29-J32+IF(J15<0,J15,J22) -> 92.522664 | K33: =K29-K32+IF(K15<0,K15,K22) -> 106.03722 | L33: =L29-L32+IF(L15<0,L15,L22) -> 119.09699 | M33: =M29-M32+IF(M15<0,M15,M22) -> 115.14521 | N33: =N29-N32+IF(N15<0,N15,N22) -> 121.45048 | ... AE33: =AE29-AE32+IF(AE15<0,AE15,AE22) -> 505.67255
B34: 18 | C34: 累计未分配利润
C35: 营业外收入(增值税即征即退)
C36: 设备进项税总额 | G36: =成本!D28 -> 5470.1291
C37: 销项税额 | G37: =G8*增值税率 -> 733.89554 | H37: =H8*增值税率 -> 768.35781 | I37: =I8*增值税率 -> 764.3972 | J37: =J8*增值税率 -> 760.4366 | K37: =K8*增值税率 -> 756.47599 | L37: =L8*增值税率 -> 752.51538 | M37: =M8*增值税率 -> 748.55477 | N37: =N8*增值税率 -> 744.59417 | ... AE37: =AE8*增值税率 -> 677.26384
C38: 代抵扣的增值税进项净值 | G38: =G36-G37 -> 4736.2336 | H38: =G38-H37 -> 3967.8758 | I38: =IF(H38-I37>0,H38-I37,0) -> 3203.4786 | J38: =IF(I38-J37>0,I38-J37,0) -> 2443.042 | K38: =IF(J38-K37>0,J38-K37,0) -> 1686.566 | L38: =IF(K38-L37>0,K38-L37,0) -> 934.05063 | M38: =IF(L38-M37>0,L38-M37,0) -> 185.49585 | N38: =IF(M38-N37>0,M38-N37,0) -> 0 | O38: =IF(N38-O37>0,N38-O37,0) -> 0 | P38: =IF(O38-P37>0,O38-P37,0) -> 0 | ... AE38: =IF(AD38-AE37>0,AD38-AE37,0) -> 0
C39: 进项税额抵扣 | G39: =G37 -> 733.89554 | H39: =IF(G38>H37,H37,G38) -> 768.35781 | I39: =IF(H38>I37,I37,H38) -> 764.3972 | J39: =IF(I38>J37,J37,I38) -> 760.4366 | K39: =IF(J38>K37,K37,J38) -> 756.47599 | L39: =IF(K38>L37,L37,K38) -> 752.51538 | M39: =IF(L38>M37,M37,L38) -> 748.55477 | N39: =IF(M38>N37,N37,M38) -> 185.49585 | O39: =IF(N38>O37,O37,N38) -> 0 | ... AE39: =IF(AD38>AE37,AE37,AD38) -> 0
C40: 应交税金 | G40: =(G37-G39)/2 -> 0 | H40: =(H37-H39)/2 -> 0 | I40: =(I37-I39) -> 0 | J40: =(J37-J39) -> 0 | K40: =(K37-K39) -> 0 | L40: =(L37-L39) -> 0 | M40: =(M37-M39) -> 0 | N40: =(N37-N39) -> 559.09831 | O40: =(O37-O39) -> 740.63356 | P40: =(P37-P39) -> 736.67295 | ... AE40: =(AE37-AE39) -> 677.26384
C41: 营业外收入(增值税减半征收) | G41: =(G37-G39)/2 -> 0 | H41: =(H37-H39)/2 -> 0 | I41: =(I37-I39)/2 -> 0 | J41: =(J37-J39)/2 -> 0 | K41: =(K37-K39)/2 -> 0 | L41: =(L37-L39)/2 -> 0 | M41: =(M37-M39)/2 -> 0 | N41: =(N37-N39)/2 -> 279.54916 | ... AE41: =(AE37-AE39)/2 -> 338.63192
C43: EVA | G43: =G26+成本!E13*(1-25%)-资产负债!D13*(资产负债!D23*参数表!$C$31+(1-资产负债!D23)*损益!$G$44) -> -645.71275 | H43: =H26+成本!F13*(1-25%)-资产负债!E13*(资产负债!E23*参数表!$C$31+(1-资产负债!E23)*损益!$G$44) -> -377.15925 | I43: =I26+成本!G13*(1-25%)-资产负债!F13*(资产负债!F23*参数表!$C$31+(1-资产负债!F23)*损益!$G$44) -> -285.54618 | J43: =J26+成本!H13*(1-25%)-资产负债!G13*(资产负债!G23*参数表!$C$31+(1-资产负债!G23)*损益!$G$44) -> -354.12243 | K43: =K26+成本!I13*(1-25%)-资产负债!H13*(资产负债!H23*参数表!$C$31+(1-资产负债!H23)*损益!$G$44) -> -252.18382 | L43: =L26+成本!J13*(1-25%)-资产负债!I13*(资产负债!I23*参数表!$C$31+(1-资产负债!I23)*损益!$G$44) -> -152.07928 | M43: =M26+成本!K13*(1-25%)-资产负债!J13*(资产负债!J23*参数表!$C$31+(1-资产负债!J23)*损益!$G$44) -> -144.55278 | N43: =N26+成本!L13*(1-25%)-资产负债!K13*(资产负债!K23*参数表!$C$31+(1-资产负债!K23)*损益!$G$44) -> -78.736869 | ... AE43: =AE26+成本!AC13*(1-25%)-资产负债!AB13*(资产负债!AB23*参数表!$C$31+(1-资产负债!AB23)*损益!$G$44) -> 1916.1344
C44: 权益资本成本率 | G44: 0.044
G47: =MIN(参数表!$C$14*参数表!$C$2,损益!G5) -> 15908.344 | H47: =MIN(参数表!$C$14*参数表!$C$2,损益!H5) -> 16500 | I47: =MIN(参数表!$C$14*参数表!$C$2,损益!I5) -> 16500 | J47: =MIN(参数表!$C$14*参数表!$C$2,损益!J5) -> 16488 | K47: =MIN(参数表!$C$14*参数表!$C$2,损益!K5) -> 16402.125 | L47: =MIN(参数表!$C$14*参数表!$C$2,损益!L5) -> 16316.25 | M47: =MIN(参数表!$C$14*参数表!$C$2,损益!M5) -> 16230.375 | N47: =MIN(参数表!$C$14*参数表!$C$2,损益!N5) -> 16144.5 | ... AE47: =MIN(参数表!$C$14*参数表!$C$2,损益!AE5) -> 14684.625
G48: =G5-G47 -> 0 | H48: =H5-H47 -> 159.75 | I48: =I5-I47 -> 73.875 | J48: =J5-J47 -> 0 | K48: =K5-K47 -> 0 | L48: =L5-L47 -> 0 | M48: =M5-M47 -> 0 | N48: =N5-N47 -> 0 | ... AE48: =AE5-AE47 -> 0
G49: =G47/G5*参数表!$C$8+损益!G48/损益!G5*参数表!$C$10 -> 0.401 | H49: =H47/H5*参数表!$C$8+损益!H48/损益!H5*参数表!$C$10 -> 0.40089452 | I49: =I47/I5*参数表!$C$8+损益!I48/损益!I5*参数表!$C$10 -> 0.40095097 | J49: =J47/J5*参数表!$C$8+损益!J48/损益!J5*参数表!$C$10 -> 0.401 | K49: =K47/K5*参数表!$C$8+损益!K48/损益!K5*参数表!$C$10 -> 0.401 | L49: =L47/L5*参数表!$C$8+损益!L48/损益!L5*参数表!$C$10 -> 0.401 | M49: =M47/M5*参数表!$C$8+损益!M48/损益!M5*参数表!$C$10 -> 0.401 | N49: =N47/N5*参数表!$C$8+损益!N48/损益!N5*参数表!$C$10 -> 0.401 | ... AE49: =AE47/AE5*参数表!$C$8+损益!AE48/损益!AE5*参数表!$C$10 -> 0.401

Sheet 成本
B1: 总成本估算表
B2: 表
B3: 序号 | C3: 项目 | D3: 建设期 | E3: 运 营 期 | AD3: 合计
D4: 1 | E4: 1 | F4: =E4+1 -> 2 | G4: =F4+1 -> 3 | H4: =G4+1 -> 4 | I4: =H4+1 -> 5 | J4: =I4+1 -> 6 | K4: =J4+1 -> 7 | L4: =K4+1 -> 8 | M4: =L4+1 -> 9 | ... AC4: =AB4+1 -> 25
B6: 1 | C6: 折旧费 | E6: =E30 -> 2303.7787 | F6: =F30 -> 2425.0303 | G6: =G30 -> 2425.0303 | H6: =H30 -> 2425.0303 | I6: =I30 -> 2425.0303 | J6: =J30 -> 2425.0303 | K6: =K30 -> 2425.0303 | L6: =L30 -> 2425.0303 | ... AB6: =AB30 -> 0 | AD6: =SUM(D6:AC6) -> 48379.354
B7: 2 | C7: 修理费 | E7: =$D$29*参数表!D52 -> 102.10654 | F7: =$D$29*参数表!E52 -> 102.10654 | G7: =$D$29*参数表!F52 -> 102.10654 | H7: =$D$29*参数表!G52 -> 204.21307 | I7: =$D$29*参数表!H52 -> 204.21307 | J7: =$D$29*参数表!I52 -> 204.21307 | K7: =$D$29*参数表!J52 -> 204.21307 | L7: =$D$29*参数表!K52 -> 204.21307 | ... AC7: =$D$29*参数表!AB52 -> 510.53269 | AD7: =SUM(D7:AC7) -> 8781.1622
B8: 3 | C8: 工资及福利等 | E8: =参数表!$C$53*参数表!$C$54*(1+参数表!$C$55) -> 108 | F8: =参数表!$C$53*参数表!$C$54*(1+参数表!$C$55) -> 108 | G8: =参数表!$C$53*参数表!$C$54*(1+参数表!$C$55) -> 108 | H8: =参数表!$C$53*参数表!$C$54*(1+参数表!$C$55) -> 108 | I8: =参数表!$C$53*参数表!$C$54*(1+参数表!$C$55) -> 108 | J8: =参数表!$C$53*参数表!$C$54*(1+参数表!$C$55) -> 108 | K8: =参数表!$C$53*参数表!$C$54*(1+参数表!$C$55) -> 108 | L8: =参数表!$C$53*参数表!$C$54*(1+参数表!$C$55) -> 108 | ... AC8: =参数表!$C$53*参数表!$C$54*(1+参数表!$C$55) -> 108 | AD8: =SUM(D8:AC8) -> 2700
B9: 4 | C9: 保险费 | E9: =E31*参数表!$C$58 -> 24.374745 | F9: =F31*参数表!$C$58 -> 23.16223 | G9: =G31*参数表!$C$58 -> 21.949715 | H9: =H31*参数表!$C$58 -> 20.7372 | I9: =I31*参数表!$C$58 -> 19.524684 | J9: =J31*参数表!$C$58 -> 18.312169 | K9: =K31*参数表!$C$58 -> 17.099654 | L9: =L31*参数表!$C$58 -> 15.887139 | ... AC9: =AC31*参数表!$C$58 -> 1.3369575 | AD9: =SUM(D9:AC9) -> 263.80181
B10: 5 | C10: 材料费 | E10: =参数表!$C$57*参数表!$C$2 -> 150 | F10: =参数表!$C$57*参数表!$C$2 -> 150 | G10: =参数表!$C$57*参数表!$C$2 -> 150 | H10: =参数表!$C$57*参数表!$C$2 -> 150 | I10: =参数表!$C$57*参数表!$C$2 -> 150 | J10: =参数表!$C$57*参数表!$C$2 -> 150 | K10: =参数表!$C$57*参数表!$C$2 -> 150 | L10: =参数表!$C$57*参数表!$C$2 -> 150 | ... AC10: =参数表!$C$57*参数表!$C$2 -> 150 | AD10: =SUM(D10:AC10) -> 3750
B11: 6 | C11: 城镇土地使用税 | E11: =参数表!$C$43 -> 0 | F11: =参数表!$C$43 -> 0 | G11: =参数表!$C$43 -> 0 | H11: =参数表!$C$43 -> 0 | I11: =参数表!$C$43 -> 0 | J11: =参数表!$C$43 -> 0 | K11: =参数表!$C$43 -> 0 | L11: =参数表!$C$43 -> 0 | ... AC11: =参数表!$C$43 -> 0 | AD11: =SUM(D11:AC11) -> 0
B12: 7 | C12: 长期待摊费用 | E12: =F56 -> 156.9105 | F12: =G56 -> 156.9105 | G12: =H56 -> 164.75603 | H12: =I56 -> 164.75603 | I12: =J56 -> 164.75603 | J12: =K56 -> 172.99383 | K12: =L56 -> 172.99383 | L12: =M56 -> 172.99383 | ... AC12: =AD56 -> 231.82827 | AD12: =SUM(D12:AC12) -> 4801.8124
B13: 8 | C13: 利息支出 | E13: =SUM(E14:E17) -> 2129.7345 | F13: =SUM(F14:F17) -> 2029.3405 | G13: =SUM(G14:G17) -> 1924.278 | H13: =SUM(H14:H17) -> 1814.3302 | I13: =SUM(I14:I17) -> 1699.2698 | J13: =SUM(J14:J17) -> 1578.8591 | K13: =SUM(K14:K17) -> 1452.8494 | L13: =SUM(L14:L17) -> 1320.9801 | ... AC13: =SUM(AC14:AC17) -> 19.575 | AD13: =SUM(D13:AC13) -> 19165.89
B14: 8.1 | C14: 长期贷款利息 | E14: =还贷!E11 -> 2110.1595 | F14: =还贷!F11 -> 2009.7655 | G14: =还贷!G11 -> 1904.703 | H14: =还贷!H11 -> 1794.7552 | I14: =还贷!I11 -> 1679.6948 | J14: =还贷!J11 -> 1559.2841 | K14: =还贷!K11 -> 1433.2744 | L14: =还贷!L11 -> 1301.4051 | ... AC14: =还贷!AC11 -> 2.3260327e-13 | AD14: =SUM(D14:AC14) -> 18657.807
B15: 8.2 | C15: 流动资金贷款利息 | E15: =还贷!E16 -> 19.575 | F15: =还贷!F16 -> 19.575 | G15: =还贷!G16 -> 19.575 | H15: =还贷!H16 -> 19.575 | I15: =还贷!I16 -> 19.575 | J15: =还贷!J16 -> 19.575 | K15: =还贷!K16 -> 19.575 | L15: =还贷!L16 -> 19.575 | ... AC15: =还贷!AC16 -> 19.575 | AD15: =SUM(D15:AC15) -> 489.375
B16: 8.3 | C16: 短期借款利息 | E16: =还贷!E21 -> 0 | F16: =还贷!F21 -> 0 | G16: =还贷!G21 -> 0 | H16: =还贷!H21 -> 0 | I16: =还贷!I21 -> 0 | J16: =还贷!J21 -> 0 | K16: =还贷!K21 -> 0 | L16: =还贷!L21 -> 0 | ... AC16: =还贷!AC21 -> 0 | AD16: =SUM(D16:AC16) -> 18.707585
B17: 8.4 | C17: 盈余资金利息收入 | AD17: =SUM(D17:AC17) -> 0
B18: 9 | C18: 其他费用 | E18: =参数表!$C$56*参数表!$C$2 -> 375 | F18: =参数表!$C$56*参数表!$C$2 -> 375 | G18: =参数表!$C$56*参数表!$C$2 -> 375 | H18: =参数表!$C$56*参数表!$C$2 -> 375 | I18: =参数表!$C$56*参数表!$C$2 -> 375 | J18: =参数表!$C$56*参数表!$C$2 -> 375 | K18: =参数表!$C$56*参数表!$C$2 -> 375 | L18: =参数表!$C$56*参数表!$C$2 -> 375 | ... AC18: =参数表!$C$56*参数表!$C$2 -> 375 | AD18: =SUM(D18:AC18) -> 9375
C19: 固定成本 | AD19: =SUM(D19:AC19) -> 0
C20: 可变成本 | AD20: =SUM(D20:AC20) -> 0
C21: 总成本费用 | E21: =SUM(E6:E13)+E18 -> 5349.9051 | F21: =SUM(F6:F13)+F18 -> 5369.55 | G21: =SUM(G6:G13)+G18 -> 5271.1206 | H21: =SUM(H6:H13)+H18 -> 5262.0668 | I21: =SUM(I6:I13)+I18 -> 5145.7939 | J21: =SUM(J6:J13)+J18 -> 5032.4085 | K21: =SUM(K6:K13)+K18 -> 4905.1862 | L21: =SUM(L6:L13)+L18 -> 4772.1044 | ... AC21: =SUM(AC6:AC13)+AC18 -> 1396.2729 | AD21: =SUM(D21:AC21) -> 97217.02
C22: 其中：经营成本 | E22: =E7+E8+E9+E10+E11+E18 -> 759.48128 | F22: =F7+F8+F9+F10+F11+F18 -> 758.26877 | G22: =G7+G8+G9+G10+G11+G18 -> 757.05625 | H22: =H7+H8+H9+H10+H11+H18 -> 857.95027 | I22: =I7+I8+I9+I10+I11+I18 -> 856.73776 | J22: =J7+J8+J9+J10+J11+J18 -> 855.52524 | K22: =K7+K8+K9+K10+K11+K18 -> 854.31273 | L22: =L7+L8+L9+L10+L11+L18 -> 853.10021 | ... AC22: =AC7+AC8+AC9+AC10+AC11+AC18 -> 1144.8696 | AD22: =SUM(D22:AC22) -> 24869.964
S24: 人民币单位：万元
B25: 序号 | C25: 项目 | D25: 合计 | E25: 运 营 期
E26: 1 | F26: =F4 -> 2 | G26: =G4 -> 3 | H26: =H4 -> 4 | I26: =I4 -> 5 | J26: =J4 -> 6 | K26: =K4 -> 7 | L26: =L4 -> 8 | M26: =M4 -> 9 | ... AD26: =AD4 -> 0
B27: 1 | C27: 固定资产
C28: 待抵扣的固定资产进项税额 | D28: =参数表!C25 -> 5470.1291
C29: 原值 | D29: =投资计划!C9-D28-E55 -> 51053.269
C30: 当期折旧费 | E30: =IF(参数表!$C$48-E26+$E$26-1>=0,$D$29*参数表!$C$47*参数表!D6,0) -> 2303.7787 | F30: =IF(参数表!$C$48-F26+$E$26-1>=0,$D$29*参数表!$C$47*参数表!E6,0) -> 2425.0303 | G30: =IF(参数表!$C$48-G26+$E$26-1>=0,$D$29*参数表!$C$47*参数表!F6,0) -> 2425.0303 | H30: =IF(参数表!$C$48-H26+$E$26-1>=0,$D$29*参数表!$C$47*参数表!G6,0) -> 2425.0303 | I30: =IF(参数表!$C$48-I26+$E$26-1>=0,$D$29*参数表!$C$47*参数表!H6,0) -> 2425.0303 | J30: =IF(参数表!$C$48-J26+$E$26-1>=0,$D$29*参数表!$C$47*参数表!I6,0) -> 2425.0303 | K30: =IF(参数表!$C$48-K26+$E$26-1>=0,$D$29*参数表!$C$47*参数表!J6,0) -> 2425.0303 | L30: =IF(参数表!$C$48-L26+$E$26-1>=0,$D$29*参数表!$C$47*参数表!K6,0) -> 2425.0303 | ... AC30: =IF(参数表!$C$48-AC26+$E$26-1>=0,$D$29*参数表!$C$47*参数表!AB6,0) -> 0
C31: 净值 | E31: =D29-E30 -> 48749.49 | F31: =E31-F30 -> 46324.46 | G31: =F31-G30 -> 43899.429 | H31: =G31-H30 -> 41474.399 | I31: =H31-I30 -> 39049.369 | J31: =I31-J30 -> 36624.339 | K31: =J31-K30 -> 34199.308 | L31: =K31-L30 -> 31774.278 | M31: =L31-M30 -> 29349.248 | ... Y31: =X31-Y30 -> 2673.9149 | Z31: =Y31 -> 2673.9149 | AA31: =Z31 -> 2673.9149 | AB31: =AA31 -> 2673.9149 | AC31: =AB31 -> 2673.9149
B45: 流动负债-购进固定资产进项税待抵扣估算表
S46: 人民币单位：万元
B47: 序号 | C47: 项目 | D47: 合计 | E47: 建设期 | F47: 运营期
E48: 1 | F48: 1 | G48: =F26 -> 2 | H48: =G26 -> 3 | I48: =H26 -> 4 | J48: =I26 -> 5 | K48: =J26 -> 6 | L48: =K26 -> 7 | M48: =L26 -> 8 | N48: =M26 -> 9 | ... AD48: =AC26 -> 25
B49: 1 | C49: 递延资产(代抵扣固定资产进项税额)
C50: 原值 | D50: =D28 -> 5470.1291
C51: 当期摊销费 | F51: =损益!G8*增值税率 -> 733.89554 | G51: =IF(F52<=损益!H8*增值税率,F52,损益!H8*增值税率) -> 768.35781 | H51: =IF(G52<=损益!I8*增值税率,G52,损益!I8*增值税率) -> 764.3972 | I51: =IF(H52<=损益!J8*增值税率,H52,损益!J8*增值税率) -> 760.4366 | J51: =IF(I52<=损益!K8*增值税率,I52,损益!K8*增值税率) -> 756.47599 | K51: =IF(J52<=损益!L8*增值税率,J52,损益!L8*增值税率) -> 752.51538 | L51: =IF(K52<=损益!M8*增值税率,K52,损益!M8*增值税率) -> 748.55477 | M51: =IF(L52<=损益!N8*增值税率,L52,损益!N8*增值税率) -> 185.49585 | N51: =IF(M52<=损益!O8*增值税率,M52,损益!O8*增值税率) -> 0 | ... AD51: =IF(AC52<=损益!AE8*增值税率,AC52,损益!AE8*增值税率) -> 0
C52: 净值 | F52: =D50-F51 -> 4736.2336 | G52: =F52-G51 -> 3967.8758 | H52: =G52-H51 -> 3203.4786 | I52: =H52-I51 -> 2443.042 | J52: =I52-J51 -> 1686.566 | K52: =J52-K51 -> 934.05063 | L52: =K52-L51 -> 185.49585 | M52: =L52-M51 -> 0 | N52: =M52-N51 -> 0 | ... AD52: =AC52-AD51 -> 0
B54: 2 | C54: 长期待摊费用 | D54: 0
C55: 原值 | E55: =参数表!C68 -> 313.821 | F55: =参数表!D68 -> 0 | G55: =参数表!E68 -> 321.66653 | H55: =参数表!F68 -> 0 | I55: =参数表!G68 -> 329.51205 | J55: =参数表!H68 -> 0 | K55: =参数表!I68 -> 345.98765 | L55: =参数表!J68 -> 0 | ... AD55: =参数表!AB68 -> 0
C56: 当期摊销费 | F56: =参数表!D69 -> 156.9105 | G56: =参数表!E69 -> 156.9105 | H56: =参数表!F69 -> 164.75603 | I56: =参数表!G69 -> 164.75603 | J56: =参数表!H69 -> 164.75603 | K56: =参数表!I69 -> 172.99383 | L56: =参数表!J69 -> 172.99383 | M56: =参数表!K69 -> 172.99383 | ... AD56: =参数表!AB69 -> 231.82827
C57: 净值 | E57: =-E56+E55 -> 313.821 | F57: =E57-F56+F55 -> 156.9105 | G57: =F57-G56+G55 -> 321.66653 | H57: =G57-H56+H55 -> 156.9105 | I57: =H57-I56+I55 -> 321.66653 | J57: =I57-J56+J55 -> 156.9105 | K57: =J57-K56+K55 -> 329.90433 | L57: =K57-L56+L55 -> 156.9105 | M57: =L57-M56+M55 -> 338.55402 | ... AD57: =AC57-AD56+AD55 -> 156.9105

Sheet 现金流量
B1: 项目现金流量表
B3: 序号 | C3: 项目 | D3: 建设期 | E3: 运 营 期 | AD3: 合计
D4: =成本!D4 -> 1 | E4: 1 | F4: 2 | G4: 3 | H4: 4 | I4: 5 | J4: 6 | K4: 7 | L4: 8 | M4: 9 | N4: 10 | O4: 11 | P4: 12 | Q4: 13 | R4: 14 | S4: 15 | T4: 16 | U4: 17 | V4: 18 | W4: 19 | X4: 20 | Y4: 21 | Z4: 22 | AA4: 23 | AB4: 24 | AC4: 25
B5: 1 | C5: 现金流入 | E5: =SUM(E6:E10) -> 6379.2458 | F5: =SUM(F6:F10) -> 6678.8025 | G5: =SUM(G6:G10) -> 6644.3757 | H5: =SUM(H6:H10) -> 6609.9489 | I5: =SUM(I6:I10) -> 6575.522 | J5: =SUM(J6:J10) -> 6541.0952 | K5: =SUM(K6:K10) -> 6506.6684 | L5: =SUM(L6:L10) -> 6472.2416 | ... AC5: =SUM(AC6:AC10) -> 9010.9006 | AD5: =SUM(E5:AC5) -> 160292.62
B6: 1.1 | C6: 发电销售收入 | E6: =损益!G8-财务计划!E10 -> 5645.3503 | F6: =损益!H8-财务计划!F10 -> 5910.4447 | G6: =损益!I8-财务计划!G10 -> 5879.9785 | H6: =损益!J8-财务计划!H10 -> 5849.5123 | I6: =损益!K8-财务计划!I10 -> 5819.0461 | J6: =损益!L8-财务计划!J10 -> 5788.5799 | K6: =损益!M8-财务计划!K10 -> 5758.1136 | L6: =损益!N8-财务计划!L10 -> 5727.6474 | ... AC6: =损益!AE8-财务计划!AC10 -> 5209.7219 | AD6: =SUM(E6:AC6) -> 139087.35
B7: 1.2 | C7: 增值税即征即退补贴 | E7: =损益!G12 -> 0 | F7: =损益!H12 -> 0 | G7: =损益!I12 -> 0 | H7: =损益!J12 -> 0 | I7: =损益!K12 -> 0 | J7: =损益!L12 -> 0 | K7: =损益!M12 -> 0 | L7: =损益!N12 -> 0 | ... AC7: =损益!AE12 -> 0 | AD7: =SUM(E7:AC7) -> 0
B8: 1.3 | C8: 增值税销项税额 | E8: =损益!G37 -> 733.89554 | F8: =损益!H37 -> 768.35781 | G8: =损益!I37 -> 764.3972 | H8: =损益!J37 -> 760.4366 | I8: =损益!K37 -> 756.47599 | J8: =损益!L37 -> 752.51538 | K8: =损益!M37 -> 748.55477 | L8: =损益!N37 -> 744.59417 | ... AC8: =损益!AE37 -> 677.26384 | AD8: =SUM(E8:AC8) -> 18081.355
B9: 1.4 | C9: 回收固定资产余值 | E9: 0 | F9: 0 | G9: 0 | H9: 0 | I9: 0 | J9: 0 | K9: 0 | L9: 0 | M9: 0 | N9: 0 | O9: 0 | P9: 0 | Q9: 0 | R9: 0 | S9: 0 | T9: 0 | U9: 0 | V9: 0 | W9: 0 | Y9: =IF(参数表!$C$76=20,成本!Y31,0) -> 0 | AC9: =IF(参数表!$C$76=25,成本!Y31,0) -> 2673.9149 | AD9: =SUM(E9:AC9) -> 2673.9149
B10: 1.5 | C10: 回收流动资金 | E10: 0 | F10: 0 | G10: 0 | H10: 0 | I10: 0 | J10: 0 | K10: 0 | L10: 0 | M10: 0 | N10: 0 | O10: 0 | P10: 0 | Q10: 0 | R10: 0 | S10: 0 | T10: 0 | U10: 0 | V10: 0 | W10: 0 | Y10: =IF(参数表!$C$76=20,参数表!C29,0) -> 0 | AC10: =IF(参数表!$C$76=25,参数表!C29,0) -> 450 | AD10: =SUM(E10:AC10) -> 450
AD11: =SUM(E11:AC11) -> 0
B12: 2 | C12: 现金流出 | D12: =SUM(D13:D19) -> 56765.741 | E12: =SUM(E13:E19) -> 759.48128 | F12: =SUM(F13:F19) -> 1079.9353 | G12: =SUM(G13:G19) -> 757.05625 | H12: =SUM(H13:H19) -> 1487.6843 | I12: =SUM(I13:I19) -> 1153.303 | J12: =SUM(J13:J19) -> 1493.3917 | K12: =SUM(K13:K19) -> 1430.7569 | ... AC12: =SUM(AC13:AC19) -> 2831.1843 | AD12: =SUM(E12:AC12) -> 55560.185
B13: 2.1 | C13: 固定资产投资 | D13: =投资计划!F6 -> 56315.741 | E13: =投资计划!G6 -> 0 | F13: 0 | G13: 0 | H13: 0 | I13: 0 | J13: 0 | K13: 0 | L13: 0 | M13: 0 | N13: 0 | O13: 0 | P13: 0 | Q13: 0 | R13: 0 | S13: 0 | T13: 0 | U13: 0 | V13: 0 | W13: 0 | X13: 0 | Y13: 0 | Z13: 0 | AA13: 0 | AB13: 0 | AC13: 0 | AD13: =SUM(E13:AC13) -> 0
B14: 2.2 | C14: 流动资金 | D14: =投资计划!H8 -> 450 | E14: =投资计划!I8 -> 0 | F14: =投资计划!J8 -> 0 | G14: =投资计划!I8 -> 0 | H14: =投资计划!J8 -> 0 | I14: =投资计划!K8 -> 0 | J14: =投资计划!L8 -> 0 | K14: =投资计划!M8 -> 0 | L14: =投资计划!N8 -> 0 | M14: =投资计划!O8 -> 0 | N14: =投资计划!P8 -> 0 | ... AC14: =投资计划!AE8 -> 0 | AD14: =SUM(D14:AC14) -> 450
B15: 2.3 | C15: 应交增值税金 | E15: =损益!G40 -> 0 | F15: =损益!H40 -> 0 | G15: =损益!I40 -> 0 | H15: =损益!J40 -> 0 | I15: =损益!K40 -> 0 | J15: =损益!L40 -> 0 | K15: =损益!M40 -> 0 | L15: =损益!N40 -> 559.09831 | ... AC15: =损益!AE40 -> 677.26384 | AD15: =SUM(E15:AC15) -> 12611.226
B16: 2.4 | C16: 土地租金 | E16: =财务计划!E14 -> 0 | F16: =财务计划!F14 -> 321.66653 | G16: =财务计划!G14 -> 0 | H16: =财务计划!H14 -> 329.51205 | I16: =财务计划!I14 -> 0 | J16: =财务计划!J14 -> 345.98765 | K16: =财务计划!K14 -> 0 | L16: =财务计划!L14 -> 354.63734 | ... AC16: =财务计划!AC14 -> 0
B17: 2.5 | E17: =成本!E22 -> 759.48128 | F17: =成本!F22 -> 758.26877 | G17: =成本!G22 -> 757.05625 | H17: =成本!H22 -> 857.95027 | I17: =成本!I22 -> 856.73776 | J17: =成本!J22 -> 855.52524 | K17: =成本!K22 -> 854.31273 | L17: =成本!L22 -> 853.10021 | ... AC17: =成本!AC22 -> 1144.8696 | AD17: =SUM(E17:AC17) -> 24869.964
B18: 2.6 | C18: 销售税金附加 | E18: =损益!G9 -> 0 | F18: =损益!H9 -> 0 | G18: =损益!I9 -> 0 | H18: =损益!J9 -> 0 | I18: =损益!K9 -> 0 | J18: =损益!L9 -> 0 | K18: =损益!M9 -> 0 | L18: =损益!N9 -> 55.909831 | ... AC18: =损益!AE9 -> 67.726384 | AD18: =SUM(E18:AC18) -> 1261.1226
B19: 2.7 | C19: 调整所得税 | E19: 0 | F19: 0 | G19: 0 | H19: =H20*所得税率/2 -> 300.22196 | I19: =I20*所得税率/2 -> 296.56525 | J19: =J20*所得税率/2 -> 291.87882 | K19: =K20*所得税率 -> 576.44421 | L19: =L20*所得税率 -> 555.15333 | M19: =M20*所得税率 -> 515.61246 | N19: =N20*所得税率 -> 508.39806 | O19: =O20*所得税率 -> 501.18365 | P19: =P20*所得税率 -> 491.69869 | Q19: =Q20*所得税率 -> 484.48429 | R19: =R20*所得税率 -> 477.26988 | ... AC19: =AC20*所得税率 -> 941.32439 | AD19: =SUM(E19:AC19) -> 12172.97
B20: 2.8 | C20: 息税前利润 | E20: =损益!G15+成本!E13 -> 2425.1798 | F20: =损益!H15+成本!F13 -> 2570.2352 | G20: =损益!I15+成本!G13 -> 2533.1359 | H20: =损益!J15+成本!H13 -> 2401.7757 | I20: =损益!K15+成本!I13 -> 2372.522 | J20: =损益!L15+成本!J13 -> 2335.0305 | K20: =损益!M15+成本!K13 -> 2305.7768 | L20: =损益!N15+成本!L13 -> 2220.6133 | ... AC20: =损益!AE15+成本!AC13 -> 3765.2976 | AD20: =SUM(E20:AC20) -> 59775.096
AD21: =SUM(E21:Y21) -> 0
B22: 3 | C22: 净现金流量 | D22: =D5-D12 -> -56765.741 | E22: =E5-E12 -> 5619.7646 | F22: =F5-F12 -> 5598.8672 | G22: =G5-G12 -> 5887.3194 | H22: =H5-H12 -> 5122.2646 | I22: =I5-I12 -> 5422.219 | J22: =J5-J12 -> 5047.7035 | K22: =K5-K12 -> 5075.9115 | ... AC22: =AC5-AC12 -> 6179.7164 | AD22: =SUM(E22:AC22) -> 104732.43
B23: 4 | C23: 累计净现金流量 | D23: =D22 -> -56765.741 | E23: =D23+E22 -> -51145.976 | F23: =E23+F22 -> -45547.109 | G23: =F23+G22 -> -39659.79 | H23: =G23+H22 -> -34537.525 | I23: =H23+I22 -> -29115.306 | J23: =I23+J22 -> -24067.603 | K23: =J23+K22 -> -18991.691 | L23: =K23+L22 -> -14897.349 | ... AC23: =AB23+AC22 -> 47966.693
C24: 所得税后投资回收年 | J24: =IF(AND(I23<0,J23>0),I4-I23/J22,0) -> 0 | K24: =IF(AND(J23<0,K23>0),J4-J23/K22,0) -> 0 | L24: =IF(AND(K23<0,L23>0),K4-K23/L22,0) -> 0 | M24: =IF(AND(L23<0,M23>0),L4-L23/M22,0) -> 0 | N24: =IF(AND(M23<0,N23>0),M4-M23/N22,0) -> 0 | O24: =IF(AND(N23<0,O23>0),N4-N23/O22,0) -> 0 | P24: =IF(AND(O23<0,P23>0),O4-O23/P22,0) -> 11.772371 | Q24: =IF(AND(P23<0,Q23>0),P4-P23/Q22,0) -> 0 | ... AC24: =IF(AND(AB23<0,AC23>0),AB4-AB23/AC22,0) -> 0 | AD24: =SUM(E24:AC24) -> 11.772371
C25: 所得税前净现金流量 | D25: =D22+D19 -> -56765.741 | E25: =E22+E19 -> 5619.7646 | F25: =F22+F19 -> 5598.8672 | G25: =G22+G19 -> 5887.3194 | H25: =H22+H19 -> 5422.4865 | I25: =I22+I19 -> 5718.7843 | J25: =J22+J19 -> 5339.5823 | K25: =K22+K19 -> 5652.3557 | ... AC25: =AC22+AC19 -> 7121.0408
C26: 累计税前净现金流量 | D26: =D25 -> -56765.741 | E26: =D26+E25 -> -51145.976 | F26: =E26+F25 -> -45547.109 | G26: =F26+G25 -> -39659.79 | H26: =G26+H25 -> -34237.303 | I26: =H26+I25 -> -28518.519 | J26: =I26+J25 -> -23178.937 | K26: =J26+K25 -> -17526.581 | L26: =K26+L25 -> -12877.085 | ... AC26: =AB26+AC25 -> 60139.664
C27: 所得税前投资回收年 | D27: =0 -> 0 | E27: =IF(AND(D26<0,E26>0),D4-D26/E25,0) -> 0 | F27: =IF(AND(E26<0,F26>0),E4-E26/F25,0) -> 0 | G27: =IF(AND(F26<0,G26>0),F4-F26/G25,0) -> 0 | H27: =IF(AND(G26<0,H26>0),G4-G26/H25,0) -> 0 | I27: =IF(AND(H26<0,I26>0),H4-H26/I25,0) -> 0 | J27: =IF(AND(I26<0,J26>0),I4-I26/J25,0) -> 0 | K27: =IF(AND(J26<0,K26>0),J4-J26/K25,0) -> 0 | L27: =IF(AND(K26<0,L26>0),K4-K26/L25,0) -> 0 | ... AC27: =IF(AND(AB26<0,AC26>0),AB4-AB26/AC25,0) -> 0 | AD27: =SUM(E27:AC27) -> 10.852447
I28: 所得税后 | L28: 所得税前
C29: 计算指标：财务内部收益率(％) | I29: =IRR(D22:AC22)*100 -> 6.1292325 | L29: =IRR(D25:AC25)*100 -> 7.1209828
C30: 财务净现值(万元) | E30: Ic= | F30: 0.05 | I30: =NPV(F30,D22:AC22) -> 5520.7271 | L30: =NPV(F30,D25:AC25) -> 11023.467
C31: 投资回收期(含建设期)(年) | I31: =AD24 -> 11.772371 | L31: =AD27 -> 10.852447
H33: 20年计算 | I33: =IRR(D22:X22)*100 -> 5.0252143 | L33: =IRR(D25:X25)*100 -> 5.9648833
B37: 资本金财务现金流量表
B39: 序号 | C39: 项目 | E39: 运 营 期 | AD39: 合计
D40: =D4 -> 1 | E40: =E4 -> 1 | F40: =F4 -> 2 | G40: =G4 -> 3 | H40: =H4 -> 4 | I40: =I4 -> 5 | J40: =J4 -> 6 | K40: =K4 -> 7 | ... AC40: =AC4 -> 25
B42: 1 | C42: 现金流入 | E42: =SUM(E43:E47) -> 6379.2458 | F42: =SUM(F43:F47) -> 6678.8025 | G42: =SUM(G43:G47) -> 6644.3757 | H42: =SUM(H43:H47) -> 6609.9489 | I42: =SUM(I43:I47) -> 6575.522 | J42: =SUM(J43:J47) -> 6541.0952 | K42: =SUM(K43:K47) -> 6506.6684 | L42: =SUM(L43:L47) -> 6472.2416 | ... AC42: =SUM(AC43:AC47) -> 8560.9006 | AD42: =SUM(E42:AC42) -> 159842.62
B43: 1.1 | C43: 发电销售收入 | E43: =E6 -> 5645.3503 | F43: =F6 -> 5910.4447 | G43: =G6 -> 5879.9785 | H43: =H6 -> 5849.5123 | I43: =I6 -> 5819.0461 | J43: =J6 -> 5788.5799 | K43: =K6 -> 5758.1136 | L43: =L6 -> 5727.6474 | ... AC43: =AC6 -> 5209.7219 | AD43: =SUM(E43:AC43) -> 139087.35
C44: 增值税即征即退补贴 | E44: =损益!G12 -> 0 | F44: =损益!H12 -> 0 | G44: =损益!I12 -> 0 | H44: =损益!J12 -> 0 | I44: =损益!K12 -> 0 | J44: =损益!L12 -> 0 | K44: =损益!M12 -> 0 | L44: =损益!N12 -> 0 | ... AC44: =损益!AE12 -> 0 | AD44: =SUM(E44:AC44) -> 0
C45: 增值税销项税额 | E45: =损益!G37 -> 733.89554 | F45: =损益!H37 -> 768.35781 | G45: =损益!I37 -> 764.3972 | H45: =损益!J37 -> 760.4366 | I45: =损益!K37 -> 756.47599 | J45: =损益!L37 -> 752.51538 | K45: =损益!M37 -> 748.55477 | L45: =损益!N37 -> 744.59417 | ... AC45: =损益!AE37 -> 677.26384 | AD45: =SUM(E45:AC45) -> 18081.355
B46: 1.2 | C46: 回收固定资产余值 | E46: 0 | F46: =F9 -> 0 | G46: 0 | H46: 0 | I46: 0 | J46: 0 | K46: 0 | L46: 0 | M46: 0 | N46: 0 | O46: 0 | P46: 0 | Q46: 0 | R46: 0 | S46: 0 | T46: 0 | U46: 0 | V46: 0 | W46: 0 | Y46: =IF(参数表!$C$76=20,成本!Y31,0) -> 0 | AC46: =IF(参数表!$C$76=25,成本!Y31,0) -> 2673.9149 | AD46: =SUM(E46:AC46) -> 2673.9149
B47: 1.3 | C47: 回收流动资金 | E47: 0 | F47: 0 | G47: 0 | H47: 0 | I47: 0 | J47: 0 | K47: 0 | L47: 0 | M47: 0 | N47: 0 | O47: 0 | P47: 0 | Q47: 0 | R47: 0 | S47: 0 | T47: 0 | U47: 0 | V47: 0 | W47: 0 | Y47: 0 | AD47: =SUM(E47:AC47) -> 0
AD48: =SUM(E48:AC48) -> 0
B49: 2 | C49: 现金流出 | D49: =SUM(D50:D58) -> 11457.444 | E49: =SUM(E50:E58) -> 5048.2284 | F49: =SUM(F50:F58) -> 5368.6824 | G49: =SUM(G50:G58) -> 5045.8034 | H49: =SUM(H50:H58) -> 5549.6401 | I49: =SUM(I50:I58) -> 5229.6414 | J49: =SUM(J50:J58) -> 5584.7814 | K49: =SUM(K50:K58) -> 5356.2917 | ... AC49: =SUM(AC50:AC58) -> 2845.8655 | AD49: =SUM(D49:AC49) -> 128929.22
B50: 2.1 | C50: 资本金 | D50: =投资计划!F11 -> 11457.444 | E50: =投资计划!G11 -> 0 | F50: 0 | G50: 0 | H50: 0 | I50: 0 | J50: 0 | K50: 0 | L50: 0 | M50: 0 | N50: 0 | O50: 0 | P50: 0 | Q50: 0 | R50: 0 | S50: 0 | T50: 0 | U50: 0 | V50: 0 | W50: 0 | X50: 0 | Y50: 0 | Z50: 0 | AA50: 0 | AB50: 0 | AC50: 0 | AD50: =SUM(D50:AC50) -> 11457.444
B51: 2.2 | C51: 借款本金偿还 | E51: =还贷!E10-财务计划!E22+财务计划!E28 -> 2159.0126 | F51: =还贷!F10-财务计划!F22+财务计划!F28 -> 2259.4067 | G51: =还贷!G10-财务计划!G22+财务计划!G28 -> 2364.4691 | H51: =还贷!H10-财务计划!H22+财务计划!H28 -> 2474.4169 | I51: =还贷!I10-财务计划!I22+财务计划!I28 -> 2589.4773 | J51: =还贷!J10-财务计划!J22+财务计划!J28 -> 2709.888 | K51: =还贷!K10-财务计划!K22+财务计划!K28 -> 2835.8978 | L51: =还贷!L10-财务计划!L22+财务计划!L28 -> 2967.767 | ... W51: =还贷!W10-财务计划!W22+财务计划!W28 -> 0 | X51: =还贷!X10-还贷!X18+还贷!X20 -> 0 | Y51: =还贷!Y10-还贷!Y18+还贷!Y20 -> 0 | Z51: =还贷!Z10-还贷!Z18+还贷!Z20 -> 0 | AA51: =还贷!AA10-还贷!AA18+还贷!AA20 -> 0 | AB51: =还贷!AB10-还贷!AB18+还贷!AB20 -> 0 | AC51: =还贷!AC10-还贷!AC18+还贷!AC20 -> 0 | AD51: =SUM(E51:AC51) -> 45379.775
B52: 2.3 | C52: 借款利息支付 | E52: =成本!E13 -> 2129.7345 | F52: =成本!F13 -> 2029.3405 | G52: =成本!G13 -> 1924.278 | H52: =成本!H13 -> 1814.3302 | I52: =成本!I13 -> 1699.2698 | J52: =成本!J13 -> 1578.8591 | K52: =成本!K13 -> 1452.8494 | L52: =成本!L13 -> 1320.9801 | ... AC52: =成本!AC13 -> 19.575 | AD52: =SUM(E52:AC52) -> 19165.89
B53: 2.4 | C53: 经营成本 | E53: =成本!E22 -> 759.48128 | F53: =成本!F22 -> 758.26877 | G53: =成本!G22 -> 757.05625 | H53: =成本!H22 -> 857.95027 | I53: =成本!I22 -> 856.73776 | J53: =成本!J22 -> 855.52524 | K53: =成本!K22 -> 854.31273 | L53: =成本!L22 -> 853.10021 | ... AC53: =成本!AC22 -> 1144.8696 | AD53: =SUM(E53:AC53) -> 24869.964
C54: 土地租金 | E54: =E16 -> 0 | F54: =F16 -> 321.66653 | G54: =G16 -> 0 | H54: =H16 -> 329.51205 | I54: =I16 -> 0 | J54: =J16 -> 345.98765 | K54: =K16 -> 0 | L54: =L16 -> 354.63734 | ... AC54: =AC16 -> 0
B55: 2.5 | C55: 应交增值税 | E55: =损益!G40 -> 0 | F55: =损益!H40 -> 0 | G55: =损益!I40 -> 0 | H55: =损益!J40 -> 0 | I55: =损益!K40 -> 0 | J55: =损益!L40 -> 0 | K55: =损益!M40 -> 0 | L55: =损益!N40 -> 559.09831 | ... AC55: =损益!AE40 -> 677.26384 | AD55: =SUM(E55:AC55) -> 12611.226
B56: 2.7 | C56: 销售税金附加 | E56: =损益!G9 -> 0 | F56: =损益!H9 -> 0 | G56: =损益!I9 -> 0 | H56: =损益!J9 -> 0 | I56: =损益!K9 -> 0 | J56: =损益!L9 -> 0 | K56: =损益!M9 -> 0 | L56: =损益!N9 -> 55.909831 | ... AC56: =损益!AE9 -> 67.726384 | AD56: =SUM(E56:AC56) -> 1261.1226
B57: 2.8 | C57: 所得税 | E57: =损益!G21 -> 0 | F57: =损益!H21 -> 0 | G57: =损益!I21 -> 0 | H57: =损益!J21 -> 73.430686 | I57: =损益!K21 -> 84.156522 | J57: =损益!L21 -> 94.521422 | K57: =损益!M21 -> 213.23187 | L57: =损益!N21 -> 224.9083 | ... AC57: =损益!AE21 -> 936.43064 | AD57: =SUM(E57:AC57) -> 9538.8936 | AE57: =AD57+AD55+AD56 -> 23411.242
B58: 2.9 | C58: 长期待摊租金 | E58: =E13 -> 0
B59: 3 | C59: 净现金流量 | D59: =D42-D49 -> -11457.444 | E59: =E42-E49 -> 1331.0174 | F59: =F42-F49 -> 1310.1201 | G59: =G42-G49 -> 1598.5723 | H59: =H42-H49 -> 1060.3087 | I59: =I42-I49 -> 1345.8806 | J59: =J42-J49 -> 956.31379 | K59: =K42-K49 -> 1150.3767 | ... AC59: =AC42-AC49 -> 5715.0351 | AD59: =SUM(D59:AC59) -> 30913.403
B60: 4 | C60: 累计净现金流量 | D60: =D59 -> -11457.444 | E60: =D60+E59 -> -10126.426 | F60: =E60+F59 -> -8816.3062 | G60: =F60+G59 -> -7217.7339 | H60: =G60+H59 -> -6157.4252 | I60: =H60+I59 -> -4811.5446 | J60: =I60+J59 -> -3855.2308 | K60: =J60+K59 -> -2704.8541 | L60: =K60+L59 -> -2569.0136 | ... AC60: =AB60+AC59 -> 30913.403
C61: 计算指标：资本金财务内部收益率(%)： | H61: =IRR(D59:AC59) -> 0.095588554
C62: 资本金财务净现值(万元) | F62: ic= | G62: 0.08 | H62: =NPV(G62,D59:AC59) -> 1908.7093
G64: 20年计算 | H64: =IRR(D59:Y59)*100 -> 7.8077492
D67: =(参数表!C77+参数表!C78/(1.09)*(1-0.09*0.1))*(1-参数表!C72) -> 2573.3945
D68: =D67+D59 -> -8884.0492 | E68: =E67+E59 -> 1331.0174 | F68: =F67+F59 -> 1310.1201 | G68: =G67+G59 -> 1598.5723 | H68: =H67+H59 -> 1060.3087 | I68: =I67+I59 -> 1345.8806 | J68: =J67+J59 -> 956.31379 | K68: =K67+K59 -> 1150.3767 | ... AC68: =AC67+AC59 -> 5715.0351
D69: =IRR(D68:AC68) -> 0.12353622
B80: 投资方财务现金流量表
B82: 序号 | C82: 项目 | E82: 建设期 | H82: 运 营 期 | AD82: 合计
D83: =D40 -> 1 | E83: =E40 -> 1 | F83: =F40 -> 2 | G83: =G40 -> 3 | H83: =H40 -> 4 | I83: =I40 -> 5 | J83: =J40 -> 6 | K83: =K40 -> 7 | ... AC83: =AC40 -> 25
B84: 1 | C84: 现金流入 | E84: =E85+E86 -> 212.71985 | F84: =F85+F86 -> 389.4442 | G84: =G85+G86 -> 438.37769 | H84: =H85+H86 -> 370.09066 | I84: =I85+I86 -> 424.14887 | J84: =J85+J86 -> 476.38797 | K84: =K85+K86 -> 460.58084 | L84: =L85+L86 -> 485.80192 | ... AC84: =AC85+AC86 -> 22022.912
B85: 1.1 | C85: 利润分配 | E85: =损益!G32 -> 212.71985 | F85: =损益!H32 -> 389.4442 | G85: =损益!I32 -> 438.37769 | H85: =损益!J32 -> 370.09066 | I85: =损益!K32 -> 424.14887 | J85: =损益!L32 -> 476.38797 | K85: =损益!M32 -> 460.58084 | L85: =损益!N32 -> 485.80192 | ... AC85: =损益!AE32 -> 2022.6902 | AD85: =SUM(E85:AC85) -> 22370.625
B86: 1.2 | C86: 资产处置收益分配 | F86: =F87+F88+F89+F90 -> 0 | G86: =G87+G88+G89+G90 -> 0 | H86: =H87+H88+H89+H90 -> 0 | I86: =I87+I88+I89+I90 -> 0 | J86: =J87+J88+J89+J90 -> 0 | K86: =K87+K88+K89+K90 -> 0 | L86: =L87+L88+L89+L90 -> 0 | M86: =M87+M88+M89+M90 -> 0 | ... AB86: =AB87+AB88+AB89+AB90 -> 0 | AC86: =AC87+AC88+AC90 -> 20000.222
B87: 1.2.1 | C87: 回收固定资产和无形资产余值 | AC87: =AC9 -> 2673.9149
B88: 1.2.2 | C88: 回收累计盈余资金（含法定公积金） | AC88: =财务计划!AC34 -> 17326.307
B89: 1.2.3 | C89: 回收自有流动资金 | AC89: 0
B90: 1.2.4 | C90: 回收法定公积金 | AC90: 0
B91: 2 | C91: 现金流出 | D91: =D92+D93 -> 11457.444 | E91: =E92+E93 -> 0
B92: 2.1 | C92: 建设投资资本金 | D92: =D50 -> 11457.444 | E92: 0
B93: 2.2 | C93: 自有流动资金 | E93: =投资计划!G13 -> 0
B94: 3 | C94: 净现金流量 | D94: =D84-D91 -> -11457.444 | E94: =E84-E91 -> 212.71985 | F94: =F84-F91 -> 389.4442 | G94: =G84-G91 -> 438.37769 | H94: =H84-H91 -> 370.09066 | I94: =I84-I91 -> 424.14887 | J94: =J84-J91 -> 476.38797 | K94: =K84-K91 -> 460.58084 | ... AC94: =AC84-AC91 -> 22022.912
B95: 4 | C95: 累计净现金流 | D95: =D94 -> -11457.444 | E95: =E94+D95 -> -11244.724 | F95: =F94+E95 -> -10855.28 | G95: =G94+F95 -> -10416.902 | H95: =H94+G95 -> -10046.811 | I95: =I94+H95 -> -9622.6625 | J95: =J94+I95 -> -9146.2745 | K95: =K94+J95 -> -8685.6937 | L95: =L94+K95 -> -8199.8917 | ... AC95: =AC94+AB95 -> 30913.403
C97: 计算指标：投资方财务内部收益率(%)： | H97: =IRR(D94:AC94) -> 0.070287445
C98: 投资方财务净现值(万元) | F98: ic= | G98: 0.08 | H98: =NPV(G98,D94:AC94) -> -1511.6989

Sheet 资产负债
A1: 资产负债表
A3: 序号 | B3: 项目 | C3: 建设期 | D3: 运 营 期
C4: =成本!D4 -> 1 | D4: 1 | E4: 2 | F4: 3 | G4: 4 | H4: 5 | I4: 6 | J4: 7 | K4: 8 | L4: 9 | M4: 10 | N4: 11 | O4: 12 | P4: 13 | Q4: 14 | R4: 15 | S4: 16 | T4: 17 | U4: 18 | V4: 19 | W4: 20 | X4: 21 | Y4: 22 | Z4: 23 | AA4: 24 | AB4: 25
A5: 1 | B5: 资产 | C5: =C6+C10+C11+C12+C9 -> 56837.219 | D5: =D6+D10+D11+D12+D9 -> 55210.932 | E5: =E6+E10+E11+E12+E9 -> 53102.975 | F5: =F6+F10+F11+F12+F9 -> 50908.986 | G5: =G6+G10+G11+G12+G9 -> 48578.494 | H5: =H6+H10+H11+H12+H9 -> 46153.963 | I5: =I6+I10+I11+I12+I9 -> 43629.337 | J5: =J6+J10+J11+J12+J9 -> 40972.554 | ... AB5: =AB6+AB10+AB11+AB12+AB9 -> 20607.132
A6: 1.1 | B6: 流动资产总值 | D6: =SUM(D7:D8) -> 1568.2976 | E6: =SUM(E7:E8) -> 2488.9735 | F6: =SUM(F7:F8) -> 3649.1681 | G6: =SUM(G7:G8) -> 4339.3861 | H6: =SUM(H7:H8) -> 5261.1179 | I6: =SUM(I7:I8) -> 5741.0437 | J6: =SUM(J7:J8) -> 6430.8396 | K6: =SUM(K7:K8) -> 6080.8781 | ... AB6: =SUM(AB7:AB8) -> 17776.307
A7: 1.1.1 | B7: 流动资产 | D7: =投资计划!C8 -> 450 | E7: =D7 -> 450 | F7: =E7 -> 450 | G7: =F7 -> 450 | H7: =G7 -> 450 | I7: =H7 -> 450 | J7: =I7 -> 450 | K7: =J7 -> 450 | L7: =K7 -> 450 | ... AB7: =AA7 -> 450
A8: 1.1.2 | B8: 累计盈余资金 | D8: =财务计划!E34 -> 1118.2976 | E8: =财务计划!F34 -> 2038.9735 | F8: =财务计划!G34 -> 3199.1681 | G8: =财务计划!H34 -> 3889.3861 | H8: =财务计划!I34 -> 4811.1179 | I8: =财务计划!J34 -> 5291.0437 | J8: =财务计划!K34 -> 5980.8396 | K8: =财务计划!L34 -> 5630.8781 | ... AB8: =财务计划!AC34 -> 17326.307
A9: 1.1.3 | B9: 应收账款 | D9: =SUM(财务计划!$E$10:'财务计划'!E10) -> 0 | E9: =SUM(财务计划!$E$10:'财务计划'!F10) -> 0 | F9: =SUM(财务计划!$E$10:'财务计划'!G10) -> 0 | G9: =SUM(财务计划!$E$10:'财务计划'!H10) -> 0 | H9: =SUM(财务计划!$E$10:'财务计划'!I10) -> 0 | I9: =SUM(财务计划!$E$10:'财务计划'!J10) -> 0 | J9: =SUM(财务计划!$E$10:'财务计划'!K10) -> 0 | K9: =SUM(财务计划!$E$10:'财务计划'!L10) -> 0 | ... AB9: =SUM(财务计划!$E$10:'财务计划'!AC10) -> 0
A10: 1.2 | B10: 在建工程 | C10: =投资计划!F5 -> 56837.219 | E10: 0 | F10: 0 | G10: 0 | H10: 0 | I10: 0 | J10: 0 | K10: 0 | L10: 0 | M10: 0 | N10: 0 | O10: 0 | P10: 0 | Q10: 0 | R10: 0 | S10: 0 | T10: 0 | U10: 0 | V10: 0 | W10: 0 | X10: 0 | Y10: 0 | Z10: 0 | AA10: 0 | AB10: 0
A11: 1.3 | B11: 固定资产净值 | D11: =成本!E31 -> 48749.49 | E11: =成本!F31 -> 46324.46 | F11: =成本!G31 -> 43899.429 | G11: =成本!H31 -> 41474.399 | H11: =成本!I31 -> 39049.369 | I11: =成本!J31 -> 36624.339 | J11: =成本!K31 -> 34199.308 | K11: =成本!L31 -> 31774.278 | ... X11: =成本!Y31 -> 2673.9149 | Y11: =X11 -> 2673.9149 | Z11: =Y11 -> 2673.9149 | AA11: =Z11 -> 2673.9149 | AB11: =AA11 -> 2673.9149
A12: 1.4 | B12: 无形及其他资产净值 | D12: =成本!F52+成本!F57 -> 4893.1441 | E12: =成本!G52+成本!G57 -> 4289.5423 | F12: =成本!H52+成本!H57 -> 3360.3891 | G12: =成本!I52+成本!I57 -> 2764.7085 | H12: =成本!J52+成本!J57 -> 1843.4765 | I12: =成本!K52+成本!K57 -> 1263.955 | J12: =成本!L52+成本!L57 -> 342.40635 | K12: =成本!M52+成本!M57 -> 338.55402 | ... AB12: =成本!AD52+成本!AD57 -> 156.9105
A13: 2 | B13: 负债及所有者权益 | C13: =C17+C18 -> 56837.219 | D13: =D17+D18 -> 55210.932 | E13: =E17+E18 -> 53102.975 | F13: =F17+F18 -> 50908.986 | G13: =G17+G18 -> 48578.494 | H13: =H17+H18 -> 46153.963 | I13: =I17+I18 -> 43629.337 | J13: =J17+J18 -> 40972.554 | ... AB13: =AB17+AB18 -> 20607.132
A14: 2.1 | B14: 流动负债总值 | D14: =投资计划!$G$18 -> 450 | E14: =投资计划!$G$18 -> 450 | F14: =投资计划!$G$18 -> 450 | G14: =投资计划!$G$18 -> 450 | H14: =投资计划!$G$18 -> 450 | I14: =投资计划!$G$18 -> 450 | J14: =投资计划!$G$18 -> 450 | K14: =投资计划!$G$18 -> 450 | ... AB14: =投资计划!$G$18 -> 450
A15: 2.2 | B15: 长期借款 | C15: =还贷!D6 -> 45379.775 | D15: =还贷!F6 -> 43220.762 | E15: =还贷!G6 -> 40961.356 | F15: =还贷!H6 -> 38596.887 | G15: =还贷!I6 -> 36122.47 | H15: =还贷!J6 -> 33532.992 | I15: =还贷!K6 -> 30823.104 | J15: =还贷!L6 -> 27987.207 | K15: =还贷!M6 -> 25019.44 | ... W15: =还贷!Y6 -> 5.0022209e-12 | X15: =还贷!AD6 -> 0 | Y15: =还贷!AE6 -> 0 | Z15: =还贷!AF6 -> 0 | AA15: =还贷!AG6 -> 0 | AB15: =还贷!AH6 -> 0
A16: 2.3 | B16: 短期借款 | C16: =财务计划!D22 -> 0 | D16: =财务计划!E22 -> 0 | E16: =财务计划!F22 -> 0 | F16: =财务计划!G22 -> 0 | G16: =财务计划!H22 -> 0 | H16: =财务计划!I22 -> 0 | I16: =财务计划!J22 -> 0 | J16: =财务计划!K22 -> 0 | ... AB16: =财务计划!AC22 -> 0
B17: 负债小计 | C17: =C14+C15+C16 -> 45379.775 | D17: =D14+D15+D16 -> 43670.762 | E17: =E14+E15+E16 -> 41411.356 | F17: =F14+F15+F16 -> 39046.887 | G17: =G14+G15+G16 -> 36572.47 | H17: =H14+H15+H16 -> 33982.992 | I17: =I14+I15+I16 -> 31273.104 | J17: =J14+J15+J16 -> 28437.207 | ... AB17: =AB14+AB15+AB16 -> 450
A18: 2.4 | B18: 所有者权益 | C18: =SUM(C19:C21) -> 11457.444 | D18: =SUM(D19:D21) -> 11540.169 | E18: =SUM(E19:E21) -> 11691.62 | F18: =SUM(F19:F21) -> 11862.1 | G18: =SUM(G19:G21) -> 12006.024 | H18: =SUM(H19:H21) -> 12170.971 | I18: =SUM(I19:I21) -> 12356.233 | J18: =SUM(J19:J21) -> 12535.348 | ... AB18: =SUM(AB19:AB21) -> 20157.132
A19: 2.4.1 | B19: 资本金 | C19: =投资计划!F12 -> 11457.444 | D19: =C19+投资计划!G13 -> 11457.444 | E19: =现金流量!F50+D19 -> 11457.444 | F19: =现金流量!G50+E19 -> 11457.444 | G19: =现金流量!H50+F19 -> 11457.444 | H19: =现金流量!I50+G19 -> 11457.444 | I19: =现金流量!J50+H19 -> 11457.444 | J19: =现金流量!K50+I19 -> 11457.444 | K19: =现金流量!L50+J19 -> 11457.444 | L19: =现金流量!M50+K19 -> 11457.444 | ... AB19: =现金流量!AC50+AA19 -> 11457.444
A20: 2.4.2 | B20: 累计三金 | D20: =损益!G27+损益!G28 -> 29.544424 | E20: =损益!H27+损益!H28+D20 -> 83.633896 | F20: =损益!I27+损益!I28+E20 -> 144.51969 | G20: =损益!J27+损益!J28+F20 -> 195.92117 | H20: =损益!K27+损益!K28+G20 -> 254.83073 | I20: =损益!L27+损益!L28+H20 -> 320.99573 | J20: =损益!M27+损益!M28+I20 -> 384.96529 | K20: =损益!N27+损益!N28+J20 -> 452.43778 | L20: =损益!O27+损益!O28+K20 -> 518.3981 | ... AB20: =损益!AE27+损益!AE28+AA20 -> 3107.0312
A21: 2.4.3 | B21: 累计未分配利润 | D21: =损益!G33 -> 53.180964 | E21: =损益!H33+D21 -> 150.54201 | F21: =损益!I33+E21 -> 260.13644 | G21: =损益!J33+F21 -> 352.6591 | H21: =损益!K33+G21 -> 458.69632 | I21: =损益!L33+H21 -> 577.79331 | J21: =损益!M33+I21 -> 692.93852 | K21: =损益!N33+J21 -> 814.389 | L21: =损益!O33+K21 -> 933.11757 | ... AB21: =损益!AE33+AA21 -> 5592.6572
B23: 资产负债率(%) | D23: =D17/D5 -> 0.79098036 | E23: =E17/E5 -> 0.77983118 | F23: =F17/F5 -> 0.76699399 | G23: =G17/G5 -> 0.7528531 | H23: =H17/H5 -> 0.7362963 | I23: =I17/I5 -> 0.71679073 | J23: =J17/J5 -> 0.69405501 | K23: =K17/K5 -> 0.66684906 | ... AB23: =AB17/AB5 -> 0.0218371
C25: =C5-C13 -> 0 | D25: =D5-D13 -> 0 | E25: =E5-E13 -> 0 | F25: =F5-F13 -> 0 | G25: =G5-G13 -> 0 | H25: =H5-H13 -> 0 | I25: =I5-I13 -> 0 | J25: =J5-J13 -> 0 | ... AB25: =AB5-AB13 -> 0
C26: =C6-C14 -> 0 | D26: =D25-C25 -> 0 | E26: =E25-D25 -> 0 | F26: =F25-E25 -> 0 | G26: =G25-F25 -> 0 | H26: =H25-G25 -> 0 | I26: =I25-H25 -> 0 | J26: =J25-I25 -> 0 | K26: =K25-J25 -> 0 | ... AB26: =AB25-AA25 -> 0
D28: =MAX(D23:AB23) -> 0.79098036

Sheet 还贷
B1: 借款还本付息计划表
B3: 序号 | C3: 项目 | E3: 建设期 | H3: 运 营 期 | AD3: 合计
D4: =成本!D4 -> 1 | E4: =成本!E4 -> 1 | F4: =成本!F4 -> 2 | G4: =成本!G4 -> 3 | H4: =成本!H4 -> 4 | I4: =成本!I4 -> 5 | J4: =成本!J4 -> 6 | K4: =成本!K4 -> 7 | ... AC4: =成本!AC4 -> 25
B5: 1 | C5: 长期借款
B6: 1.1 | C6: 年初借款余额 | D6: =D8+D7 -> 45379.775 | E6: =E8+E7 -> 45379.775 | F6: =F7+F8 -> 43220.762 | G6: =G7+G8 -> 40961.356 | H6: =H7+H8 -> 38596.887 | I6: =I7+I8 -> 36122.47 | J6: =J7+J8 -> 33532.992 | K6: =K7+K8 -> 30823.104 | L6: =L7+L8 -> 27987.207 | M6: =M7+M8 -> 25019.44 | ... AC6: =AC7+AC8 -> 5.0022209e-12
B7: 1.1.1 | C7: 本金 | D7: =投资计划!F16 -> 44858.297 | E7: =SUM(D6:D6) -> 45379.775 | F7: =E6-E10 -> 43220.762 | G7: =F6-F10 -> 40961.356 | H7: =G6-G10 -> 38596.887 | I7: =H6-H10 -> 36122.47 | J7: =I6-I10 -> 33532.992 | K7: =J6-J10 -> 30823.104 | L7: =K6-K10 -> 27987.207 | M7: =L6-L10 -> 25019.44 | ... AC7: =AB6-AB10 -> 5.0022209e-12
B8: 1.1.2 | C8: 建设期利息 | D8: =投资计划!F7 -> 521.47771 | E8: =投资计划!G7 -> 0
B9: 1.2 | C9: 当期还本付息 | E9: =$E$35 -> 4269.1721 | F9: =$E$35 -> 4269.1721 | G9: =$E$35 -> 4269.1721 | H9: =$E$35 -> 4269.1721 | I9: =$E$35 -> 4269.1721 | J9: =$E$35 -> 4269.1721 | K9: =$E$35 -> 4269.1721 | L9: =$E$35 -> 4269.1721 | ... S9: =$E$35 -> 4269.1721 | T9: =T10+T11 -> 2.3260327e-13 | U9: =U10+U11 -> 2.3260327e-13 | V9: =V10+V11 -> 2.3260327e-13 | W9: =W10+W11 -> 2.3260327e-13 | X9: =X10+X11 -> 2.3260327e-13 | Y9: =Y10+Y11 -> 2.3260327e-13 | Z9: =Z10+Z11 -> 2.3260327e-13 | AA9: =AA10+AA11 -> 2.3260327e-13 | ... AC9: =AC10+AC11 -> 2.3260327e-13
C10: 其中：还本 | E10: =E36 -> 2159.0126 | F10: =F36 -> 2259.4067 | G10: =G36 -> 2364.4691 | H10: =H36 -> 2474.4169 | I10: =I36 -> 2589.4773 | J10: =J36 -> 2709.888 | K10: =K36 -> 2835.8978 | L10: =L36 -> 2967.767 | ... S10: =S36 -> 4079.4765 | T10: =T37 -> 0 | U10: =U37 -> 0 | V10: =V37 -> 0 | W10: =W37 -> 0 | X10: =X37 -> 0 | Y10: =Y37 -> 0 | Z10: =Z37 -> 0 | AA10: =AA37 -> 0 | ... AC10: =AC37 -> 0
C11: 付息 | E11: =E6*参数表!$C$31 -> 2110.1595 | F11: =F6*参数表!$C$31 -> 2009.7655 | G11: =G6*参数表!$C$31 -> 1904.703 | H11: =H6*参数表!$C$31 -> 1794.7552 | I11: =I6*参数表!$C$31 -> 1679.6948 | J11: =J6*参数表!$C$31 -> 1559.2841 | K11: =K6*参数表!$C$31 -> 1433.2744 | L11: =L6*参数表!$C$31 -> 1301.4051 | ... AC11: =AC6*参数表!$C$31 -> 2.3260327e-13
B12: 2 | C12: 流动资金借款
B13: 2.1 | C13: 年初借款余额 | E13: =投资计划!G18 -> 450 | F13: =E13 -> 450 | G13: =F13 -> 450 | H13: =G13 -> 450 | I13: =H13 -> 450 | J13: =I13 -> 450 | K13: =J13 -> 450 | L13: =K13 -> 450 | M13: =L13 -> 450 | ... AC13: =AB13 -> 450
B14: 2.2 | C14: 当期还本付息
C15: 其中：还本
C16: 付息 | E16: =E13*流动资金贷款利率 -> 19.575 | F16: =F13*流动资金贷款利率 -> 19.575 | G16: =G13*流动资金贷款利率 -> 19.575 | H16: =H13*流动资金贷款利率 -> 19.575 | I16: =I13*流动资金贷款利率 -> 19.575 | J16: =J13*流动资金贷款利率 -> 19.575 | K16: =K13*流动资金贷款利率 -> 19.575 | L16: =L13*流动资金贷款利率 -> 19.575 | ... AC16: =AC13*流动资金贷款利率 -> 19.575
B17: 3 | C17: 短期借款
B18: 3.1 | C18: 年初借款余额 | E18: =财务计划!D22 -> 0 | F18: =财务计划!E22 -> 0 | G18: =财务计划!F22 -> 0 | H18: =财务计划!G22 -> 0 | I18: =财务计划!H22 -> 0 | J18: =财务计划!I22 -> 0 | K18: =财务计划!J22 -> 0 | L18: =财务计划!K22 -> 0 | ... U18: =财务计划!T22 -> 0 | V18: =财务计划!V22 -> 0 | W18: =财务计划!W22 -> 0 | X18: =财务计划!X22 -> 0 | Y18: =财务计划!Y22 -> 0 | Z18: =财务计划!Z22 -> 0 | AA18: =财务计划!AA22 -> 0 | AB18: =财务计划!AB22 -> 0 | AC18: =财务计划!AC22 -> 0
B19: 3.2 | C19: 当期还本付息
C20: 其中：还本 | D20: =财务计划!D28 -> 0 | E20: =财务计划!E28 -> 0 | F20: =财务计划!F28 -> 0 | G20: =财务计划!G28 -> 0 | H20: =财务计划!H28 -> 0 | I20: =财务计划!I28 -> 0 | J20: =财务计划!J28 -> 0 | K20: =财务计划!K28 -> 0 | ... AC20: =财务计划!AC28 -> 0
C21: 付息 | D21: =D20*短期贷款利息 -> 0 | E21: =E20*短期贷款利息 -> 0 | F21: =F20*短期贷款利息 -> 0 | G21: =G20*短期贷款利息 -> 0 | H21: =H20*短期贷款利息 -> 0 | I21: =I20*短期贷款利息 -> 0 | J21: =J20*短期贷款利息 -> 0 | K21: =K20*短期贷款利息 -> 0 | ... AC21: =AC20*短期贷款利息 -> 0
B22: 4 | C22: 借款合计
B23: 4.1 | C23: 年初借款余额 | E23: =E6+E13+E18 -> 45829.775 | F23: =F6+F13+F18 -> 43670.762 | G23: =G6+G13+G18 -> 41411.356 | H23: =H6+H13+H18 -> 39046.887 | I23: =I6+I13+I18 -> 36572.47 | J23: =J6+J13+J18 -> 33982.992 | K23: =K6+K13+K18 -> 31273.104 | L23: =L6+L13+L18 -> 28437.207 | ... AC23: =AC6+AC13+AC18 -> 450
B24: 4.2 | C24: 当期还本付息
C25: 其中：还本 | E25: =E10+E15+E20 -> 2159.0126 | F25: =F10+F15+F20 -> 2259.4067 | G25: =G10+G15+G20 -> 2364.4691 | H25: =H10+H15+H20 -> 2474.4169 | I25: =I10+I15+I20 -> 2589.4773 | J25: =J10+J15+J20 -> 2709.888 | K25: =K10+K15+K20 -> 2835.8978 | L25: =L10+L15+L20 -> 2967.767 | ... AC25: =AC10+AC15+AC20 -> 0
C26: 付息 | E26: =E11+E16+E21 -> 2129.7345 | F26: =F11+F16+F21 -> 2029.3405 | G26: =G11+G16+G21 -> 1924.278 | H26: =H11+H16+H21 -> 1814.3302 | I26: =I11+I16+I21 -> 1699.2698 | J26: =J11+J16+J21 -> 1578.8591 | K26: =K11+K16+K21 -> 1452.8494 | L26: =L11+L16+L21 -> 1320.9801 | ... AC26: =AC11+AC16+AC21 -> 19.575
C27: 息税前利润（EBIT） | E27: =成本!E13+损益!G15 -> 2425.1798 | F27: =成本!F13+损益!H15 -> 2570.2352 | G27: =成本!G13+损益!I15 -> 2533.1359 | H27: =成本!H13+损益!J15 -> 2401.7757 | I27: =成本!I13+损益!K15 -> 2372.522 | J27: =成本!J13+损益!L15 -> 2335.0305 | K27: =成本!K13+损益!M15 -> 2305.7768 | L27: =成本!L13+损益!N15 -> 2220.6133 | ... AC27: =成本!AC13+损益!AE15 -> 3765.2976
C28: 息税前利润(含增值税） | E28: =E27+成本!F51 -> 3159.0753 | F28: =F27+成本!G51 -> 3338.593 | G28: =G27+成本!H51 -> 3297.5331 | H28: =H27+成本!I51 -> 3162.2123 | I28: =I27+成本!J51 -> 3128.998 | J28: =J27+成本!K51 -> 3087.5459 | K28: =K27+成本!L51 -> 3054.3316 | L28: =L27+成本!M51 -> 2406.1092 | ... AC28: =AC27+成本!AD51 -> 3765.2976
C29: 利息备付率（ICR） | E29: =E28/成本!E13 -> 1.4833188 | F29: =F28/成本!F13 -> 1.6451616 | G29: =G28/成本!G13 -> 1.7136469 | H29: =H28/成本!H13 -> 1.7429089 | I29: =I28/成本!I13 -> 1.8413779 | J29: =J28/成本!J13 -> 1.955555 | K29: =K28/成本!K13 -> 2.1023044 | L29: =L28/成本!L13 -> 1.8214575 | ... X29: =X28/成本!X13 -> 77.250128 | AD29: =AVERAGE(F29:AC29) -> 20.994916
C30: ebitda | E30: =E27+成本!E6 -> 4728.9585 | F30: =F27+成本!F6 -> 4995.2654 | G30: =G27+成本!G6 -> 4958.1662 | H30: =H27+成本!H6 -> 4826.806 | I30: =I27+成本!I6 -> 4797.5523 | J30: =J27+成本!J6 -> 4760.0608 | K30: =K27+成本!K6 -> 4730.8071 | L30: =L27+成本!L6 -> 4645.6436 | ... AC30: =AC27+成本!AC6 -> 3765.2976
C31: ebitda+-tax | E31: =E30+成本!F51-损益!G21 -> 5462.8541 | F31: =F30+成本!G51-损益!H21 -> 5763.6232 | G31: =G30+成本!H51-损益!I21 -> 5722.5634 | H31: =H30+成本!I51-损益!J21 -> 5513.8119 | I31: =I30+成本!J51-损益!K21 -> 5469.8717 | J31: =J30+成本!K51-损益!L21 -> 5418.0547 | K31: =K30+成本!L51-损益!M21 -> 5266.13 | L31: =L30+成本!M51-损益!N21 -> 4606.2311 | ... AC31: =AC30+成本!AD51-损益!AE21 -> 2828.8669
C32: 偿债备付率（dscr） | E32: =E31/(E11+E10) -> 1.279605 | F32: =F31/(F11+F10) -> 1.3500564 | G32: =G31/(G11+G10) -> 1.3404387 | H32: =H31/(H11+H10) -> 1.2915412 | I32: =I31/(I11+I10) -> 1.2812488 | J32: =J31/(J11+J10) -> 1.2691113 | K32: =K31/(K11+K10) -> 1.2335249 | L32: =L31/(L11+L10) -> 1.0789518 | ... S32: =S31/(S11+S10) -> 0.87305037 | AD32: =AVERAGE(F32:AC32) -> 1.1071357
E35: =-PMT(参数表!C31,参数表!C32,投资计划!C15) -> 4269.1721
E36: =$E$35-还贷!E11 -> 2159.0126 | F36: =$E$35-还贷!F11 -> 2259.4067 | G36: =$E$35-还贷!G11 -> 2364.4691 | H36: =$E$35-还贷!H11 -> 2474.4169 | I36: =$E$35-还贷!I11 -> 2589.4773 | J36: =$E$35-还贷!J11 -> 2709.888 | K36: =$E$35-还贷!K11 -> 2835.8978 | L36: =$E$35-还贷!L11 -> 2967.767 | ... S36: =$E$35-还贷!S11 -> 4079.4765

Sheet 财务计划
A1: 财务计划现金流量表
A2: 附表7 | T2: 单位：万元
A3: 序号 | B3: 项 目 | C3: 合计 | E3: 运 营 期
D4: =成本!D4 -> 1 | E4: =成本!E4 -> 1 | F4: =成本!F4 -> 2 | G4: =成本!G4 -> 3 | H4: =成本!H4 -> 4 | I4: =成本!I4 -> 5 | J4: =成本!J4 -> 6 | K4: =成本!K4 -> 7 | ... AC4: =成本!AC4 -> 25
A5: 1 | B5: 经营活动净现金流量 | D5: =D6-D11 -> 0 | E5: =E6-E11 -> 5619.7646 | F5: =F6-F11 -> 5598.8672 | G5: =G6-G11 -> 5887.3194 | H5: =H6-H11 -> 5349.0559 | I5: =I6-I11 -> 5634.6278 | J5: =J6-J11 -> 5245.0609 | K5: =K6-K11 -> 5439.1238 | ... AC5: =AC6-AC11 -> 3060.6952
A6: 1.1 | B6: 现金流入 | D6: =D7+D8+D9 -> 0 | E6: =E7+E8+E9-E10 -> 6379.2458 | F6: =F7+F8+F9-F10 -> 6678.8025 | G6: =G7+G8+G9-G10 -> 6644.3757 | H6: =H7+H8+H9-H10 -> 6609.9489 | I6: =I7+I8+I9-I10 -> 6575.522 | J6: =J7+J8+J9-J10 -> 6541.0952 | K6: =K7+K8+K9-K10 -> 6506.6684 | L6: =L7+L8+L9-L10 -> 6472.2416 | ... AC6: =AC7+AC8+AC9-AC10 -> 5886.9857
A7: 1.1.1 | B7: 销售收入 | E7: =损益!G8+损益!G12 -> 5645.3503 | F7: =损益!H8+损益!H12 -> 5910.4447 | G7: =损益!I8+损益!I12 -> 5879.9785 | H7: =损益!J8+损益!J12 -> 5849.5123 | I7: =损益!K8+损益!K12 -> 5819.0461 | J7: =损益!L8+损益!L12 -> 5788.5799 | K7: =损益!M8+损益!M12 -> 5758.1136 | L7: =损益!N8+损益!N12 -> 5727.6474 | ... AC7: =损益!AE8+损益!AE12 -> 5209.7219
A8: 1.1.2 | B8: 增值税 | E8: =损益!G37 -> 733.89554 | F8: =损益!H37 -> 768.35781 | G8: =损益!I37 -> 764.3972 | H8: =损益!J37 -> 760.4366 | I8: =损益!K37 -> 756.47599 | J8: =损益!L37 -> 752.51538 | K8: =损益!M37 -> 748.55477 | L8: =损益!N37 -> 744.59417 | ... AC8: =损益!AE37 -> 677.26384 | AD8: =SUM(D8:AC8) -> 18081.355
A9: 1.1.3 | B9: 回收流动资金
A10: 1.1.4 | B10: 补贴未到位资金 | E10: =(1-参数表!D13)*参数表!$C$11*损益!G47 -> 0 | F10: =(1-参数表!E13)*参数表!$C$11*损益!H47 -> 0 | G10: =(1-参数表!F13)*参数表!$C$11*损益!I47 -> 0 | H10: =(1-参数表!G13)*参数表!$C$11*损益!J47 -> 0 | I10: =(1-参数表!H13)*参数表!$C$11*损益!K47 -> 0 | J10: =(1-参数表!I13)*参数表!$C$11*损益!L47 -> 0 | K10: =(1-参数表!J13)*参数表!$C$11*损益!M47 -> 0 | L10: =(1-参数表!K13)*参数表!$C$11*损益!N47 -> 0 | ... AC10: =(1-参数表!AB13)*参数表!$C$11*损益!AE47 -> 0
A11: 1.2 | B11: 现金流出 | D11: =D12+D13+D14+D15+D16 -> 0 | E11: =E12+E13+E14+E15+E16 -> 759.48128 | F11: =F12+F13+F14+F15+F16 -> 1079.9353 | G11: =G12+G13+G14+G15+G16 -> 757.05625 | H11: =H12+H13+H14+H15+H16 -> 1260.893 | I11: =I12+I13+I14+I15+I16 -> 940.89428 | J11: =J12+J13+J14+J15+J16 -> 1296.0343 | K11: =K12+K13+K14+K15+K16 -> 1067.5446 | ... AC11: =AC12+AC13+AC14+AC15+AC16 -> 2826.2905 | AD11: =AD12+AD13+AD15+AD16 -> 48281.206
A12: 1.2.1 | B12: 经营成本 | E12: =现金流量!E53 -> 759.48128 | F12: =现金流量!F53 -> 758.26877 | G12: =现金流量!G53 -> 757.05625 | H12: =现金流量!H53 -> 857.95027 | I12: =现金流量!I53 -> 856.73776 | J12: =现金流量!J53 -> 855.52524 | K12: =现金流量!K53 -> 854.31273 | L12: =现金流量!L53 -> 853.10021 | ... AC12: =现金流量!AC53 -> 1144.8696 | AD12: =SUM(D12:AC12) -> 24869.964
A13: 1.2.2 | B13: 城建税及教育附加 | E13: =现金流量!E56 -> 0 | F13: =现金流量!F56 -> 0 | G13: =现金流量!G56 -> 0 | H13: =现金流量!H56 -> 0 | I13: =现金流量!I56 -> 0 | J13: =现金流量!J56 -> 0 | K13: =现金流量!K56 -> 0 | L13: =现金流量!L56 -> 55.909831 | ... AC13: =现金流量!AC56 -> 67.726384 | AD13: =SUM(D13:AC13) -> 1261.1226
A14: 1.2.3 | B14: 大额租金 | E14: =参数表!D68 -> 0 | F14: =参数表!E68 -> 321.66653 | G14: =参数表!F68 -> 0 | H14: =参数表!G68 -> 329.51205 | I14: =参数表!H68 -> 0 | J14: =参数表!I68 -> 345.98765 | K14: =参数表!J68 -> 0 | L14: =参数表!K68 -> 354.63734 | ... AC14: =参数表!AB68 -> 0 | AD14: =SUM(D14:AC14) -> 4644.9019
A15: 1.2.4 | B15: 所得税 | E15: =现金流量!E57 -> 0 | F15: =现金流量!F57 -> 0 | G15: =现金流量!G57 -> 0 | H15: =现金流量!H57 -> 73.430686 | I15: =现金流量!I57 -> 84.156522 | J15: =现金流量!J57 -> 94.521422 | K15: =现金流量!K57 -> 213.23187 | L15: =现金流量!L57 -> 224.9083 | ... AC15: =现金流量!AC57 -> 936.43064 | AD15: =SUM(D15:AC15) -> 9538.8936
A16: 1.2.5 | B16: 应缴增值税 | E16: =现金流量!E55 -> 0 | F16: =现金流量!F55 -> 0 | G16: =现金流量!G55 -> 0 | H16: =现金流量!H55 -> 0 | I16: =现金流量!I55 -> 0 | J16: =现金流量!J55 -> 0 | K16: =现金流量!K55 -> 0 | L16: =现金流量!L55 -> 559.09831 | ... AC16: =现金流量!AC55 -> 677.26384 | AD16: =SUM(D16:AC16) -> 12611.226
A17: 2 | B17: 投资、筹资活动净现金流量 | D17: =D18-D24 -> 0 | E17: =E18-E24 -> -4501.467 | F17: =F18-F24 -> -4678.1913 | G17: =G18-G24 -> -4727.1248 | H17: =H18-H24 -> -4658.8378 | I17: =I18-I24 -> -4712.896 | J17: =J18-J24 -> -4765.1351 | K17: =K18-K24 -> -4749.328 | ... AD17: =AD18-AD24 -> -144203.51
A18: 2.1 | B18: 现金流入 | D18: =D19+D20+D21+D22+D23 -> 56837.219 | E18: =E19+E20+E21+E22+E23 -> 450 | F18: =F19+F20+F21+F22+F23 -> 0 | G18: =G19+G20+G21+G22+G23 -> 0 | H18: =H19+H20+H21+H22+H23 -> 0 | I18: =I19+I20+I21+I22+I23 -> 0 | J18: =J19+J20+J21+J22+J23 -> 0 | K18: =K19+K20+K21+K22+K23 -> 0 | ... AD18: =AD19+AD20+AD21+AD22+AD23 -> 0
A19: 2.1.1 | B19: 项目资本金投入 | D19: =投资计划!F11 -> 11457.444 | E19: =投资计划!G11 -> 0
A20: 2.1.2 | B20: 建设投资借款 | D20: =还贷!D6 -> 45379.775
A21: 2.1.3 | B21: 流动资金借款 | E21: =投资计划!G18 -> 450
A22: 2.1.4 | B22: 短期借款 | C22: =MAX(F22:AC22) -> 430.05943 | D22: =IF(D5-D24-D28<0,IF(-D24-D28+D19+D20+D21+D5>=0,0,-D5-D19-D20-D21+D24+D28),0) -> 0 | E22: =IF(E5-E24-E28<0,IF(D34-E24-E28+E19+E20+E21+E5>=0,0,-D34-E5-E19-E20-E21+E24+E28),0) -> 0 | F22: =IF(F5-F24-F28<0,IF(E34-F24-F28+F19+F20+F21+F5>=0,0,-E34-F5-F19-F20-F21+F24+F28),0) -> 0 | G22: =IF(G5-G24-G28<0,IF(F34-G24-G28+G19+G20+G21+G5>=0,0,-F34-G5-G19-G20-G21+G24+G28),0) -> 0 | H22: =IF(H5-H24-H28<0,IF(G34-H24-H28+H19+H20+H21+H5>=0,0,-G34-H5-H19-H20-H21+H24+H28),0) -> 0 | I22: =IF(I5-I24-I28<0,IF(H34-I24-I28+I19+I20+I21+I5>=0,0,-H34-I5-I19-I20-I21+I24+I28),0) -> 0 | J22: =IF(J5-J24-J28<0,IF(I34-J24-J28+J19+J20+J21+J5>=0,0,-I34-J5-J19-J20-J21+J24+J28),0) -> 0 | K22: =IF(K5-K24-K28<0,IF(J34-K24-K28+K19+K20+K21+K5>=0,0,-J34-K5-K19-K20-K21+K24+K28),0) -> 0 | L22: =IF(L5-L24-L28<0,IF(K34-L24-L28+L19+L20+L21+L5>=0,0,-K34-L5-L19-L20-L21+L24+L28),0) -> 0 | ... AC22: =IF(AC5-AC24-AC28<0,IF(AB34-AC24-AC28+AC19+AC20+AC21+AC5>=0,0,-AB34-AC5-AC19-AC20-AC21+AC24+AC28),0) -> 0
A23: 2.1.5 | B23: 回收固定资产余值
A24: 2.2 | B24: 现金流出 | D24: =D25+D26+D27+D30+D31+D32 -> 56837.219 | E24: =E25+E26+E27+E30+E31+E32 -> 4951.467 | F24: =F25+F26+F27+F30+F31+F32 -> 4678.1913 | G24: =G25+G26+G27+G30+G31+G32 -> 4727.1248 | H24: =H25+H26+H27+H30+H31+H32 -> 4658.8378 | I24: =I25+I26+I27+I30+I31+I32 -> 4712.896 | J24: =J25+J26+J27+J30+J31+J32 -> 4765.1351 | K24: =K25+K26+K27+K30+K31+K32 -> 4749.328 | ... AC24: =AC25+AC26+AC27+AC30+AC31+AC32 -> 2042.2652 | AD24: =SUM(D24:AC24) -> 144203.51
A25: 2.2.1 | B25: 建设投资 | D25: =投资计划!F10 -> 56837.219 | E25: =投资计划!G15 -> 0
A26: 2.2.2 | B26: 流动资金 | E26: =投资计划!G8 -> 450
A27: 2.2.3 | B27: 长期借款本金偿还 | E27: =还贷!E10 -> 2159.0126 | F27: =还贷!F10 -> 2259.4067 | G27: =还贷!G10 -> 2364.4691 | H27: =还贷!H10 -> 2474.4169 | I27: =还贷!I10 -> 2589.4773 | J27: =还贷!J10 -> 2709.888 | K27: =还贷!K10 -> 2835.8978 | L27: =还贷!L10 -> 2967.767 | ... S27: =还贷!S10 -> 4079.4765 | AD27: =SUM(D27:AC27) -> 45379.775
B28: 短期借款本金偿还 | E28: =D22 -> 0 | F28: =E22 -> 0 | G28: =F22 -> 0 | H28: =G22 -> 0 | I28: =H22 -> 0 | J28: =I22 -> 0 | K28: =J22 -> 0 | L28: =K22 -> 0 | ... AC28: =AB22 -> 0
B29: 流动负债本金偿还
A30: 2.2.4 | B30: 各种利息支出 | E30: =成本!E13 -> 2129.7345 | F30: =成本!F13 -> 2029.3405 | G30: =成本!G13 -> 1924.278 | H30: =成本!H13 -> 1814.3302 | I30: =成本!I13 -> 1699.2698 | J30: =成本!J13 -> 1578.8591 | K30: =成本!K13 -> 1452.8494 | L30: =成本!L13 -> 1320.9801 | ... AC30: =成本!AC13 -> 19.575 | AD30: =SUM(D30:AC30) -> 19165.89
A31: 2.2.5 | B31: 各投资方利润分配 | E31: =E41 -> 212.71985 | F31: =F41 -> 389.4442 | G31: =G41 -> 438.37769 | H31: =H41 -> 370.09066 | I31: =I41 -> 424.14887 | J31: =J41 -> 476.38797 | K31: =K41 -> 460.58084 | L31: =L41 -> 485.80192 | ... AC31: =AC41 -> 2022.6902 | AD31: =SUM(F31:AC31) -> 22157.905
A32: 2.2.6 | B32: 其他流出 | AD32: =SUM(F32:AC32) -> 0
A33: 3 | B33: 净现金流量 | D33: =D5+D17-D28 -> 0 | E33: =E5+E17-E28 -> 1118.2976 | F33: =F5+F17-F28 -> 920.67588 | G33: =G5+G17-G28 -> 1160.1946 | H33: =H5+H17-H28 -> 690.21807 | I33: =I5+I17-I28 -> 921.73177 | J33: =J5+J17-J28 -> 479.92582 | K33: =K5+K17-K28 -> 689.79585 | ... AC33: =AC5+AC17-AC28 -> 1018.43 | AD33: =SUM(F33:AC33) -> 16208.009
A34: 4 | B34: 累计盈余资金 | D34: =D33 -> 0 | E34: =D34+E33 -> 1118.2976 | F34: =E34+F33 -> 2038.9735 | G34: =F34+G33 -> 3199.1681 | H34: =G34+H33 -> 3889.3861 | I34: =H34+I33 -> 4811.1179 | J34: =I34+J33 -> 5291.0437 | K34: =J34+K33 -> 5980.8396 | L34: =K34+L33 -> 5630.8781 | ... AC34: =AB34+AC33 -> 17326.307 | AD34: =SUM(F34:AC34) -> 167099.21
D36: =IF(+D28=0,0,IF(D28>0,0)) -> 0 | E36: =IF(D28+E28=0,0,IF(E28>0,0,#REF!+D28/#REF!)) -> 0 | F36: =IF(E28+F28=0,0,IF(F28>0,0,D4+E28/D28)) -> 0 | G36: =IF(F28+G28=0,0,IF(G28>0,0,E4+F28/E28)) -> 0 | H36: =IF(G28+H28=0,0,IF(H28>0,0,F4+G28/F28)) -> 0 | I36: =IF(H28+I28=0,0,IF(I28>0,0,G4+H28/G28)) -> 0 | J36: =IF(I28+J28=0,0,IF(J28>0,0,H4+I28/H28)) -> 0 | K36: =IF(J28+K28=0,0,IF(K28>0,0,I4+J28/I28)) -> 0 | L36: =IF(K28+L28=0,0,IF(L28>0,0,J4+K28/J28)) -> 0 | M36: =IF(L28+M28=0,0,IF(M28>0,0,K4+L28/K28)) -> 0 | ... AC36: =IF(AB28+AC28=0,0,IF(AC28>0,0,AA4+AB28/AA28)) -> 0 | AD36: =IF(#REF!+AD28=0,0,IF(AD28>0,0,X4+#REF!/X28)) -> #REF!
B38: 不含利润分配的流出 | E38: =SUM(E25:E30)-E18 -> 4288.7471 | F38: =SUM(F25:F30) -> 4288.7471 | G38: =SUM(G25:G30) -> 4288.7471 | H38: =SUM(H25:H30) -> 4288.7471 | I38: =SUM(I25:I30) -> 4288.7471 | J38: =SUM(J25:J30) -> 4288.7471 | K38: =SUM(K25:K30) -> 4288.7471 | L38: =SUM(L25:L30) -> 4288.7471 | M38: =SUM(M25:M30) -> 4288.7471 | ... AC38: =SUM(AC25:AC30) -> 19.575
B39: 净现金流（不含利润分配） | E39: =E5-E38 -> 1331.0174 | F39: =F5-F38 -> 1310.1201 | G39: =G5-G38 -> 1598.5723 | H39: =H5-H38 -> 1060.3087 | I39: =I5-I38 -> 1345.8806 | J39: =J5-J38 -> 956.31379 | K39: =K5-K38 -> 1150.3767 | L39: =L5-L38 -> 135.84047 | ... AC39: =AC5-AC38 -> 3041.1202
B40: 可分配利润 | E40: =损益!G29*参数表!$C$70 -> 212.71985 | F40: =损益!H29*参数表!$C$70 -> 389.4442 | G40: =损益!I29*参数表!$C$70 -> 438.37769 | H40: =损益!J29*参数表!$C$70 -> 370.09066 | I40: =损益!K29*参数表!$C$70 -> 424.14887 | J40: =损益!L29*参数表!$C$70 -> 476.38797 | K40: =损益!M29*参数表!$C$70 -> 460.58084 | L40: =损益!N29*参数表!$C$70 -> 485.80192 | ... AC40: =损益!AE29*参数表!$C$70 -> 2022.6902
B41: 实际分配利润 | E41: =E40 -> 212.71985 | F41: =F40 -> 389.4442 | G41: =G40 -> 438.37769 | H41: =H40 -> 370.09066 | I41: =I40 -> 424.14887 | J41: =J40 -> 476.38797 | K41: =K40 -> 460.58084 | L41: =L40 -> 485.80192 | ... AC41: =AC40 -> 2022.6902
B42: 累计盈余资金 | E42: =E5+E17-E28 -> 1118.2976 | F42: =F5+F17-F28 -> 920.67588 | G42: =G5+G17-G28 -> 1160.1946 | H42: =H5+H17-H28 -> 690.21807 | I42: =I5+I17-I28 -> 921.73177 | J42: =J5+J17-J28 -> 479.92582 | K42: =K5+K17-K28 -> 689.79585 | L42: =L5+L17-L28 -> -349.96145 | ... AC42: =AC5+AC17-AC28 -> 1018.43

Sheet 估值结果
A1: 基准内部收益率 | B1: =参数表!C71 -> 0.085
A3: 收益现值法
A4: 运营年 | B4: 1 | C4: 2 | D4: 3 | E4: 4 | F4: 5 | G4: 6 | H4: 7 | I4: 8 | J4: 9 | K4: 10 | L4: 11 | M4: 12 | N4: 13 | O4: 14 | P4: 15 | Q4: 16 | R4: 17 | S4: 18 | T4: 19 | U4: 20 | V4: 21 | W4: 22 | X4: 23 | Y4: 24 | Z4: 25
A5: 净现金流量 | B5: =现金流量!E59 -> 1331.0174 | C5: =现金流量!F59 -> 1310.1201 | D5: =现金流量!G59 -> 1598.5723 | E5: =现金流量!H59 -> 1060.3087 | F5: =现金流量!I59 -> 1345.8806 | G5: =现金流量!J59 -> 956.31379 | H5: =现金流量!K59 -> 1150.3767 | I5: =现金流量!L59 -> 135.84047 | ... Z5: =现金流量!AC59 -> 5715.0351
A6: 终值 | B6: =B5*(1+参数表!$C$71)^(现金流量!$AC$4-现金流量!E$4) -> 9429.691 | C6: =C5*(1+参数表!$C$71)^(现金流量!$AC$4-现金流量!F$4) -> 8554.5089 | D6: =D5*(1+参数表!$C$71)^(现金流量!$AC$4-现金流量!G$4) -> 9620.2537 | E6: =E5*(1+参数表!$C$71)^(现金流量!$AC$4-现金流量!H$4) -> 5881.0766 | F6: =F5*(1+参数表!$C$71)^(现金流量!$AC$4-现金流量!I$4) -> 6880.2039 | G6: =G5*(1+参数表!$C$71)^(现金流量!$AC$4-现金流量!J$4) -> 4505.7329 | H6: =H5*(1+参数表!$C$71)^(现金流量!$AC$4-现金流量!K$4) -> 4995.4586 | I6: =I5*(1+参数表!$C$71)^(现金流量!$AC$4-现金流量!L$4) -> 543.66919 | ... Z6: =Z5*(1+参数表!$C$71)^(现金流量!$AC$4-现金流量!AC$4) -> 5715.0351
A7: 该年末卖出价格 | B7: =SUM(B6:$Z6)/(1+参数表!$C$71)^(现金流量!$AC4-现金流量!E4+1) -> 12795.284 | C7: =SUM(C6:$Z6)/(1+参数表!$C$71)^(现金流量!$AC4-现金流量!F4) -> 13618.774 | D7: =SUM(D6:$Z6)/(1+参数表!$C$71)^(现金流量!$AC4-现金流量!G4) -> 13354.889 | E7: =SUM(E6:$Z6)/(1+参数表!$C$71)^(现金流量!$AC4-现金流量!H4) -> 12755.604 | F7: =SUM(F6:$Z6)/(1+参数表!$C$71)^(现金流量!$AC4-现金流量!I4) -> 12689.395 | G7: =SUM(G6:$Z6)/(1+参数表!$C$71)^(现金流量!$AC4-现金流量!J4) -> 12307.713 | H7: =SUM(H6:$Z6)/(1+参数表!$C$71)^(现金流量!$AC4-现金流量!K4) -> 12316.268 | I7: =SUM(I6:$Z6)/(1+参数表!$C$71)^(现金流量!$AC4-现金流量!L4) -> 12114.993 | J7: =SUM(J6:$Z6)/(1+参数表!$C$71)^(现金流量!$AC4-现金流量!M4) -> 12997.38 | ... Z7: =SUM(Z6:$Z6)/(1+参数表!$C$71)^(现金流量!$AC4-现金流量!AC4) -> 5715.0351
A8: 100%股权卖出价格 | B8: =B7 -> 12795.284 | C8: =C7 -> 13618.774 | D8: =D7 -> 13354.889 | E8: =E7 -> 12755.604 | F8: =F7 -> 12689.395 | G8: =G7 -> 12307.713 | H8: =H7 -> 12316.268 | I8: =I7 -> 12114.993 | ... Z8: =Z7 -> 5715.0351
A9: 所得税 | B9: =MAX((B8-B14)*参数表!$C$72,0) -> 200.67597 | C9: =MAX((C8-C14)*参数表!$C$72,0) -> 324.1995 | D9: =MAX((D8-D14)*参数表!$C$72,0) -> 284.61682 | E9: =MAX((E8-E14)*参数表!$C$72,0) -> 194.72401 | F9: =MAX((F8-F14)*参数表!$C$72,0) -> 184.79272 | G9: =MAX((G8-G14)*参数表!$C$72,0) -> 127.54043 | H9: =MAX((H8-H14)*参数表!$C$72,0) -> 128.82371 | I9: =MAX((I8-I14)*参数表!$C$72,0) -> 98.632323 | ... Z9: =MAX((Z8-Z14)*参数表!$C$72,0) -> 0
A10: 印花税 | B10: =B16*0.05% -> 6.412414 | C10: =C16*0.05% -> 6.8512038 | D10: =D16*0.05% -> 6.7497044 | E10: =E16*0.05% -> 6.4757625 | F10: =F16*0.05% -> 6.472113 | G10: =G16*0.05% -> 6.3143545 | H10: =H16*0.05% -> 6.3506169 | I10: =I16*0.05% -> 6.2837152 | ... Z10: =Z16*0.05% -> 4.4110332
A11: 税后收益 | B11: =B8-B9-B10 -> 12588.195 | C11: =C8-C9-C10 -> 13287.723 | D11: =D8-D9-D10 -> 13063.523 | E11: =E8-E9-E10 -> 12554.404 | F11: =F8-F9-F10 -> 12498.13 | G11: =G8-G9-G10 -> 12173.858 | H11: =H8-H9-H10 -> 12181.094 | I11: =I8-I9-I10 -> 12010.077 | ... Z11: =Z8-Z9-Z10 -> 5710.6241
A12: 溢价率 | B12: =(B7+B15)/B14-1 -> 0.11934461 | C12: =(C7+C15)/C14-1 -> 0.19593933 | D12: =(D7+D15)/D14-1 -> 0.1782217 | E12: =(E7+E15)/E14-1 -> 0.13040267 | F12: =(F7+F15)/F14-1 -> 0.12976561 | G12: =(G7+G15)/G14-1 -> 0.10222745 | H12: =(H7+H15)/H14-1 -> 0.10855737 | I12: =(I7+I15)/I14-1 -> 0.096879079 | ... Z12: =(Z7+Z15)/Z14-1 -> -0.23001443
A13: 备注：上述价格仅为未来现金流，不包括公司账面盈余资金。
A14: 资本金 | B14: =资产负债!D19 -> 11457.444 | C14: =资产负债!E19 -> 11457.444 | D14: =资产负债!F19 -> 11457.444 | E14: =资产负债!G19 -> 11457.444 | F14: =资产负债!H19 -> 11457.444 | G14: =资产负债!I19 -> 11457.444 | H14: =资产负债!J19 -> 11457.444 | I14: =资产负债!K19 -> 11457.444 | ... Z14: =资产负债!AB19 -> 11457.444
A15: 累计未分配利润 | B15: =资产负债!D20 -> 29.544424 | C15: =资产负债!E20 -> 83.633896 | D15: =资产负债!F20 -> 144.51969 | E15: =资产负债!G20 -> 195.92117 | F15: =资产负债!H20 -> 254.83073 | G15: =资产负债!I20 -> 320.99573 | H15: =资产负债!J20 -> 384.96529 | I15: =资产负债!K20 -> 452.43778 | ... Z15: =资产负债!AB20 -> 3107.0312
A16: 股权+利润分配 | B16: =B7+B15 -> 12824.828 | C16: =C7+C15 -> 13702.408 | D16: =D7+D15 -> 13499.409 | E16: =E7+E15 -> 12951.525 | F16: =F7+F15 -> 12944.226 | G16: =G7+G15 -> 12628.709 | H16: =H7+H15 -> 12701.234 | I16: =I7+I15 -> 12567.43 | ... Z16: =Z7+Z15 -> 8822.0664
A17: 溢价率 | B17: =B16/B14-1 -> 0.11934461 | C17: =C16/C14-1 -> 0.19593933 | D17: =D16/D14-1 -> 0.1782217 | E17: =E16/E14-1 -> 0.13040267 | F17: =F16/F14-1 -> 0.12976561 | G17: =G16/G14-1 -> 0.10222745 | H17: =H16/H14-1 -> 0.10855737 | I17: =I16/I14-1 -> 0.096879079 | ... U17: =U16/U14-1 -> 0.59187069
A18: 市场价值法：自由现金流量=息前税后利润+所得税抵扣额+折旧及摊销-资本性支出-营运资金追加额
A19: 运营年 | B19: 1 | C19: 2 | D19: 3 | E19: 4 | F19: 5 | G19: 6 | H19: 7 | I19: 8 | J19: 9 | K19: 10 | L19: 11 | M19: 12 | N19: 13 | O19: 14 | P19: 15 | Q19: 16 | R19: 17 | S19: 18 | T19: 19 | U19: 20
A20: 资本性支出 | B20: =成本!E31 -> 48749.49 | C20: =成本!F31 -> 46324.46 | D20: =成本!G31 -> 43899.429 | E20: =成本!H31 -> 41474.399 | F20: =成本!I31 -> 39049.369 | G20: =成本!J31 -> 36624.339 | H20: =成本!K31 -> 34199.308 | I20: =成本!L31 -> 31774.278 | ... U20: =成本!X31 -> 2673.9149
A21: 息税前利润-调整所得税+折旧摊销 | B21: =现金流量!E20-现金流量!E19+成本!E6 -> 4728.9585 | C21: =现金流量!F20-现金流量!F19+成本!F6 -> 4995.2654 | D21: =现金流量!G20-现金流量!G19+成本!G6 -> 4958.1662 | E21: =现金流量!H20-现金流量!H19+成本!H6 -> 4526.584 | F21: =现金流量!I20-现金流量!I19+成本!I6 -> 4500.987 | G21: =现金流量!J20-现金流量!J19+成本!J6 -> 4468.182 | H21: =现金流量!K20-现金流量!K19+成本!K6 -> 4154.3629 | I21: =现金流量!L20-现金流量!L19+成本!L6 -> 4090.4902 | ... U21: =现金流量!X20-现金流量!X19+成本!X6 -> 3559.1587
A22: 净现金流量 | B22: =B21 -> 4728.9585 | C22: =现金流量!F20-现金流量!F19+成本!F6 -> 4995.2654 | D22: =现金流量!G20-现金流量!G19+成本!G6 -> 4958.1662 | E22: =现金流量!H20-现金流量!H19+成本!H6 -> 4526.584 | F22: =现金流量!I20-现金流量!I19+成本!I6 -> 4500.987 | G22: =现金流量!J20-现金流量!J19+成本!J6 -> 4468.182 | H22: =现金流量!K20-现金流量!K19+成本!K6 -> 4154.3629 | I22: =现金流量!L20-现金流量!L19+成本!L6 -> 4090.4902 | J22: =现金流量!M20-现金流量!M19+成本!M6 -> 3971.8676 | ... U22: =现金流量!X20-现金流量!X19+成本!X6 -> 3559.1587
A23: 终值 | B23: =B22*(1+参数表!$C$71)^(现金流量!$X$4-现金流量!E$4) -> 22280.787 | C23: =C22*(1+参数表!$C$71)^(现金流量!$X$4-现金流量!F$4) -> 21691.713 | D23: =D22*(1+参数表!$C$71)^(现金流量!$X$4-现金流量!G$4) -> 19843.882 | E23: =E22*(1+参数表!$C$71)^(现金流量!$X$4-现金流量!H$4) -> 16697.306 | F23: =F22*(1+参数表!$C$71)^(现金流量!$X$4-现金流量!I$4) -> 15302.199 | G23: =G22*(1+参数表!$C$71)^(现金流量!$X$4-现金流量!J$4) -> 14000.617 | H23: =H22*(1+参数表!$C$71)^(现金流量!$X$4-现金流量!K$4) -> 11997.507 | I23: =I22*(1+参数表!$C$71)^(现金流量!$X$4-现金流量!L$4) -> 10887.602 | ... U23: =U22*(1+参数表!$C$71)^(现金流量!$X$4-现金流量!X$4) -> 3559.1587
A24: 卖出价格 | B24: =SUM(B23:$U23)/(1+参数表!$C$71)^(现金流量!$X4-现金流量!E4) -> 43960.8 | C24: =SUM(C23:$U23)/(1+参数表!$C$71)^(现金流量!$X4-现金流量!F4) -> 42566.548 | D24: =SUM(D23:$U23)/(1+参数表!$C$71)^(现金流量!$X4-现金流量!G4) -> 40764.842 | E24: =SUM(E23:$U23)/(1+参数表!$C$71)^(现金流量!$X4-现金流量!H4) -> 38850.243 | F24: =SUM(F23:$U23)/(1+参数表!$C$71)^(现金流量!$X4-现金流量!I4) -> 37241.17 | G24: =SUM(G23:$U23)/(1+参数表!$C$71)^(现金流量!$X4-现金流量!J4) -> 35523.099 | H24: =SUM(H23:$U23)/(1+参数表!$C$71)^(现金流量!$X4-现金流量!K4) -> 33694.585 | I24: =SUM(I23:$U23)/(1+参数表!$C$71)^(现金流量!$X4-现金流量!L4) -> 32051.141 | ... U24: =SUM(U23:$U23)/(1+参数表!$C$71)^(现金流量!$X4-现金流量!X4) -> 3559.1587
A25: 10%股权卖出价格
A26: 所有者权益 | B26: =资产负债!D18 -> 11540.169 | C26: =资产负债!E18 -> 11691.62 | D26: =资产负债!F18 -> 11862.1 | E26: =资产负债!G18 -> 12006.024 | F26: =资产负债!H18 -> 12170.971 | G26: =资产负债!I18 -> 12356.233 | H26: =资产负债!J18 -> 12535.348 | I26: =资产负债!K18 -> 12724.271 | ... Z26: =资产负债!AB18 -> 20157.132
B27: =B11-B14 -> 1130.7514 | C27: =C11-C14 -> 1830.2793 | D27: =D11-D14 -> 1606.0789 | E27: =E11-E14 -> 1096.9603 | F27: =F11-F14 -> 1040.6866 | G27: =G11-G14 -> 716.41475 | H27: =H11-H14 -> 723.65039 | I27: =I11-I14 -> 552.63278 | ... Z27: =Z11-Z14 -> -5746.8196
B28: =B5 -> 1331.0174 | C28: =C5/(1+$B$1)^(C4-$B$4) -> 1207.4839 | D28: =D5/(1+$B$1)^(D4-$B$4) -> 1357.9157 | E28: =E5/(1+$B$1)^(E4-$B$4) -> 830.12429 | F28: =F5/(1+$B$1)^(F4-$B$4) -> 971.15286 | G28: =G5/(1+$B$1)^(G4-$B$4) -> 635.99211 | H28: =H5/(1+$B$1)^(H4-$B$4) -> 705.11774 | I28: =I5/(1+$B$1)^(I4-$B$4) -> 76.739861 | J28: =J5/(1+$B$1)^(J4-$B$4) -> 83.572015 | ... Z28: =Z5/(1+$B$1)^(Z4-$B$4) -> 806.68724
